Workbook
Name INVTYPE: [1]master!$H$2:$H$5
Name POS: [1]master!$G$2:$G$38
Name RATE: [1]master!$F$2:$F$8
Name RCHARGE: [1]master!$C$2:$C$3

Sheet DELHI 3B
A1: GSTR-3B [See rule 61(5)]
A4: GSTIN | B4: 07AABCG4768K1Z9 | D4: Year | F4: 2026-27
A5: Legal name of the registered person | B5: Godfrey Phillips India Limited | D5: Month | F5: Apr-26
A7: 3.1 Details of Outward Supplies and inward supplies liable to reverse charge
A8: Nature of Supplies | B8: Total Taxable value | C8: Integrated Tax | D8: Central Tax | E8: State/UT Tax | F8: Cess
A9: 1 | B9: 2 | C9: 3 | D9: 4 | E9: 5 | F9: 6
A10: (a) Outward Taxable supplies (other than zero rated, nil rated and exempted) | B10: =Outward!AL1 -> 89063008 | C10: =Outward!AQ1 -> 9519863.6 | D10: =Outward!AO1 -> 3255738.9 | E10: =D10 -> 3255738.9 | F10: =Outward!AT1+Outward!AV1 -> 0
A11: (b) Outward Taxable supplies (zero rated )
A12: (c) Other Outward Taxable supplies (Nil rated, exempted)
A13: (d) Inward supplies (liable to reverse charge) | B13: =SUMIF(Inward!AZ:AZ,G13,Inward!AI:AI) -> 1948857 | C13: =SUMIF(Inward!AZ:AZ,G13,Inward!AN:AN) -> 20600.1 | D13: =SUMIF(Inward!AZ:AZ,G13,Inward!AM:AM) -> 165097.08 | E13: =D13 -> 165097.08 | F13: 0 | G13: Y
A14: (e) Non-GST Outward supplies
A15: Total | B15: =SUM(B10:B14) -> 91011865 | C15: =SUM(C10:C14) -> 9540463.7 | D15: =SUM(D10:D14) -> 3420836 | E15: =SUM(E10:E14) -> 3420836 | F15: =SUM(F10:F14) -> 0
A17: 4. Eligible ITC
A18: Details | B18: Integrated Tax | C18: Central Tax | D18: State/UT Tax | E18: Cess
A19: 1 | B19: 2 | C19: 3 | D19: 4 | E19: 5
A20: (A) ITC Available (Whether in full or part)
A21: (1) Import of goods | B21: 0
A22: (2) Import of services
A23: (3) Inward supplies liable to reverse charge (other than 1 &2 above) | B23: =SUMIFS(Inward!AN:AN,Inward!AZ:AZ,G23,Inward!AY:AY,'DELHI 3B'!F23) -> 8100 | C23: =SUMIFS(Inward!AM:AM,Inward!AZ:AZ,G23,Inward!AY:AY,'DELHI 3B'!F23) -> 147097.08 | D23: =C23 -> 147097.08 | E23: 0 | F23: Y | G23: Y
A24: (4) Inward supplies from ISD
A25: (5) All other ITC | B25: =SUMIF(Inward!AZ:AZ,G25,Inward!AN:AN) -> 165504.08 | C25: =SUMIF(Inward!AZ:AZ,G25,Inward!AL:AL) -> 1160702.4 | D25: =C25 -> 1160702.4 | E25: =SUMIF(Inward!AZ:AZ,G25,Inward!AR:AR) -> 0 | F25: Y | G25: N
A26: TOTAL ITC A | B26: =B21+B22+B23+B24+B25 -> 173604.08 | C26: =C21+C22+C23+C24+C25 -> 1307799.4 | D26: =D21+D22+D23+D24+D25 -> 1307799.4 | E26: =E21+E22+E23+E24+E25 -> 0
A27: (B) ITC Reversed
A28: (1) As per Rule 42 & 43 of SGST/CGST rules | B28: =SUMIFS(Inward!AN:AN,Inward!AY:AY,F28,Inward!AZ:AZ,'DELHI 3B'!G28) -> 101580.48 | C28: =SUMIFS(Inward!AM:AM,Inward!AY:AY,F28,Inward!AZ:AZ,'DELHI 3B'!G28) -> 116074.59 | D28: =C28 -> 116074.59 | E28: =SUMIFS(Inward!AR:AR,Inward!AZ:AZ,G28,Inward!AY:AY,'DELHI 3B'!F28) -> 0 | F28: N | G28: N
A29: (2) Others | B29: ='ITC REVERSAL'!C5+'ITC Revers & Reclaim - 180 Days'!R8+'ITC REVERSAL'!I4 -> 8388.3983 | C29: ='ITC REVERSAL'!D5+'ITC Revers - 180 Days'!P17+'ITC REVERSAL'!J4 -> 33233.122 | D29: ='ITC REVERSAL'!E5+'ITC Revers - 180 Days'!Q17+'ITC REVERSAL'!K4 -> 33233.122 | E29: 0 | F29: STT Reversal & Other
A30: TOTAL ITC B | B30: =B28+B29 -> 109968.88 | C30: =C28+C29 -> 149307.71 | D30: =D28+D29 -> 149307.71 | E30: =E28+E29 -> 0
A31: (C) Net ITC Available (A)-(B) | B31: =B26-B30 -> 63635.202 | C31: =C26-C30 -> 1158491.7 | D31: =D26-D30 -> 1158491.7 | E31: =E26-E30 -> 0
A32: (D) Ineligible ITC
A33: (1) As per section 17(5) of CGST//SGST Act | B33: 0 | C33: 0 | D33: =C33 -> 0 | E33: 0
A34: (2) Others | B34: 0 | C34: 0 | D34: =C34 -> 0 | E34: 0
B35: =B26-B28-'ITC Revers & Reclaim - 180 Days'!R8 -> 72023.6 | C35: =C26-C28-'ITC Revers & Reclaim - 180 Days'!S8 -> 1191724.9 | D35: =D26-D28-'ITC Revers & Reclaim - 180 Days'!T8 -> 1191724.9 | E35: =E26-E28 -> 0
B36: =B25-B28 -> 63923.6 | C36: =C25-C28 -> 1044627.8 | D36: =D25-D28 -> 1044627.8 | E36: =E25-E28 -> 0
A37: 5. Values of exempt, Nil-rated and non-GST inward supplies
A38: Nature of supplies | C38: Inter-State supplies | D38: Intra-state supplies
A39: 1 | C39: 2 | D39: 3
A40: From a supplier under composition scheme, Exempt and Nil rated supply | C40: 0 | D40: 0
A41: Non GST supply | D41: 0
A42: Total | C42: =SUM(C40:C41) -> 0 | D42: =SUM(D40:D41) -> 0
A45: 5.1 Interest & late fee payable
A46: Description | B46: Integrated Tax | C46: Central Tax | D46: State/UT Tax | E46: Cess
A47: 1 | B47: 2 | C47: 3 | D47: 4 | E47: 5
A48: Interest | B48: ='ITC Revers & Reclaim - 180 Days'!V8 -> 0 | C48: ='ITC Revers - 180 Days'!S17 -> 0 | D48: =C48 -> 0 | E48: 0 | F48: Interest on ITC Reversal for non payment of 180days
A49: Late fee
A52: 3.2 Of the supplies shown in 3.1 (a), details of inter-state supplies made to unregistered persons, composition taxable person and UIN holders
A53: Place of Supply(State/UT) | B53: Supplies made to Unregistered Persons | D53: Supplies made to Composition Taxable Persons | F53: Supplies made to UIN holders
B54: Total Taxable value | C54: Amount of Integrated Tax | D54: Total Taxable value | E54: Amount of Integrated Tax | F54: Total Taxable value
A55: 1 | B55: 2 | C55: 3 | D55: 4 | E55: 5 | F55: 6
A67: Total | B67: 0 | C67: 0 | D67: 0 | E67: 0 | F67: 0

Sheet ITC REVERSAL
B2: ITC Reversal on Security Transaction | H2: ITC Reversal - Non Recov Trx claimed in 3b as Recov now Reversed
B3: Month | C3: IGST | D3: CGST | E3: SGST | F3: Total | H3: Month | I3: IGST | J3: CGST | K3: SGST | L3: Total
B4: Mar | C4: 8388.3983 | D4: 33233.122 | E4: 33233.122 | F4: =SUM(C4:E4) -> 74854.641 | I4: =-AJ9 -> 0 | J4: =-AH9 -> 0 | K4: =-AI9 -> 0 | L4: =SUM(I4:K4) -> 0
B5: Total | C5: =SUM(C4:C4) -> 8388.3983 | D5: =SUM(D4:D4) -> 33233.122 | E5: =SUM(E4:E4) -> 33233.122 | F5: =SUM(F4:F4) -> 74854.641 | H5: Total | I5: =SUM(I4:I4) -> 0 | J5: =SUM(J4:J4) -> 0 | K5: =SUM(K4:K4) -> 0 | L5: =SUM(L4:L4) -> 0
AH9: =SUM(AH11) -> 0 | AI9: =SUM(AI11) -> 0 | AJ9: =SUM(AJ11) -> 0
A10: Document Type | B10: Trx Category | C10: Org Id | D10: Rec OU | E10: IO Name | F10: GST Inv No | G10: IO Location | H10: FP REGN | I10: ENTITY CODE | J10: EVENT TYPE CODE | K10: SOURCE | L10: TRX TYPE | M10: ACCOUNTING DATE | N10: TRX NUMBER | O10: TRX ID | P10: TRX DATE | Q10: PARTY TYPE | R10: PARTY NUMBER | S10: PARTY NAME | T10: PARTY SITE NAME | U10: TP REGNNO | V10: TRX UOM | W10: UNIT PRICE | X10: TRX QTY | Y10: LINE AMT | Z10: REGIME | AA10: SUPPLIER INVOICE NUM | AB10: SUPPLIER INVOICE DATE | AC10: ITEM CODE | AD10: HSN/SACCODE | AE10: ITEM DES | AF10: GST TAXABLE AMT | AG10: GST TAX RATE | AH10: SGST | AI10: CGST | AJ10: IGST | AK10: IGST IMPORT | AL10: UTGST | AM10: CESS1 RATE | AN10: CESS1 | AO10: CESS2 RATE | AP10: CESS2 | AQ10: TCS RATE/ADHOC | AR10: TCS AMOUNT | AS10: OTHER TAX | AT10: TOTAL AMT | AU10: TRX REC | AV10: TRX SELF | AW10: EXPENSE | AX10: VOUCHARNO | AY10: TAX CATEGORY | AZ10: ITC CATEGORY | BA10: Custom BOE No | BB10: Custom BOE Date | BC10: Port Code | BD10: IRN Status | BE10: State Code | BF10: State Name | BG10: GSTIN & INV | BH10: Total Tax | BI10: V-Lookuop | BJ10: Diff | BK10: Remark | BL10: TRX ID | BM10: ITC Type | BO10: Inv Year | BP10: 2B Year

Sheet ITC Revers - 180 Days

Sheet ITC Revers & Reclaim - 180 Days

Sheet Outward
AL1: =SUBTOTAL(9,AL3:AL46) -> 89063008 | AO1: =SUBTOTAL(9,AO3:AO46) -> 3255738.9 | AP1: =SUBTOTAL(9,AP3:AP46) -> 3255738.9 | AQ1: =SUBTOTAL(9,AQ3:AQ46) -> 9519863.6 | AR1: =SUBTOTAL(9,AR3:AR46) -> 0 | AT1: =SUBTOTAL(9,AT3:AT46) -> 0 | AV1: =SUBTOTAL(9,AV3:AV46) -> 0
A2: Document Type | B2: Trx Category | C2: Org Id | D2: Rec OU | E2: IO Name | F2: GST Inv No | G2: EXC Inv No | H2: IO Location | I2: FP REGN | J2: ENTITY CODE | K2: APPLICATION NAME | L2: EVENT TYPE CODE | M2: SOURCE | N2: TRX TYPE | O2: ACCOUNTING DATE | P2: TRX NUMBER | Q2: TRX ID | R2: TRX DATE | S2: PARTY TYPE | T2: PARTY NUMBER | U2: PARTY NAME | V2: PARTY SITE NAME | W2: TP REGNNAME | X2: TP REGNNO | Y2: TRX UOM | Z2: MRP | AA2: UNIT PRICE | AB2: TRX QTY | AC2: LINE AMT | AD2: REGIME | AE2: ITEM CODE | AF2: HSN/SACCODE | AG2: ITEM DESCRIPTION | AH2: CIGARETTE LENGTH | AI2: NCCD | AJ2: BED | AK2: Deemed Taxable Value Per "M" | AL2: GST TAXABLE AMT | AM2: Tax Type | AN2: GST TAX RATE | AO2: SGST | AP2: CGST | AQ2: IGST | AR2: UTGST | AS2: CESS1 RATE | AT2: CESS1 | AU2: CESS2 RATE | AV2: CESS2 | AW2: TCS RATE/ADHOC | AX2: TCS AMOUNT | AY2: OTHER TAX | AZ2: TOTAL INVOICE AMOUNT | BA2: TRX REC | BB2: TRX SELF | BC2: REVENUE | BD2: CREDITNOTE INV NUM | BE2: TAX CATEGORY | BF2: ITC CATEGORY | BG2: EWAY BILL NUM | BH2: EWAY BILL DATE | BI2: IRN NUMBER | BJ2: IRN DATE
A3: Tax Invoice | B3: AR_INVOICE | C3: 107 | D3: Godfrey_Phillips_India_Limited_HO | E3: GPIL_HO_New_Delhi(Services) | F3: GPI-HOC260300032 | H3: HO New Friends Colony | I3: 07AABCG4768K1Z9 | J3: TRANSACTIONS | K3: Receivables | L3: INV_COMPLETE | O3: 46142 | P3: 11263000032 | Q3: 27210284 | R3: 46142 | S3: Customer | T3: 445074 | U3: Godfrey Phillips India Limited | V3: GPI -CUTTAK | W3: GSTIN | X3: 21AABCG4768K1ZJ | AA3: 243260 | AB3: 1 | AC3: 243260 | AD3: GST_India | AF3: 998599 | AG3: BUSINESS SUPPORT SERVICES CROSS CHARGED FOR THE PERIOD MAR-26 | AJ3: 0 | AK3: 0 | AL3: 243260 | AM3: Normal | AN3: 18 | AO3: 0 | AP3: 0 | AQ3: 43786.8 | AR3: 0 | AS3: 0 | AT3: 0 | AU3: 0 | AV3: 0 | AY3: 0 | AZ3: 287046.8 | BA3: Y | BB3: N | BC3: 11.7100.111.512110.0000.000000.0000.000000.000000.00000000 | BD3: GPI-HOC260300032 | BE3: HO_INTER-STATE_OTH_REC_18% | BF3: INPUT_SERVICE | BI3: 90ee7e29ba933c98780c9a9fe543aa5ba4b47efcc0666108cb4a627bc9f84b99 | BJ3: 46142.587 | BK3: B2B
A4: Tax Invoice | B4: AR_INVOICE | C4: 107 | D4: Godfrey_Phillips_India_Limited_HO | E4: GPIL_HO_New_Delhi(Services) | F4: GPI-HOC260300042 | H4: HO New Friends Colony | I4: 07AABCG4768K1Z9 | J4: TRANSACTIONS | K4: Receivables | L4: INV_COMPLETE | O4: 46142 | P4: 11263000042 | Q4: 27210352 | R4: 46142 | S4: Customer | T4: 2889 | U4: Godfrey Phillips India Limited, Chandigarh | V4: I112101 | W4: GSTIN | X4: 04AABCG4768K1ZF | AA4: 379724 | AB4: 1 | AC4: 379724 | AD4: GST_India | AF4: 998599 | AG4: BUSINESS SUPPORT SERVICES CROSS CHARGED FOR THE PERIOD MAR-26 | AJ4: 0 | AK4: 0 | AL4: 379724 | AM4: Normal | AN4: 18 | AO4: 0 | AP4: 0 | AQ4: 68350.32 | AR4: 0 | AS4: 0 | AT4: 0 | AU4: 0 | AV4: 0 | AY4: 0 | AZ4: 448074.32 | BA4: Y | BB4: N | BC4: 11.7100.111.512110.0000.000000.0000.000000.000000.00000000 | BD4: GPI-HOC260300042 | BE4: HO_INTER-STATE_OTH_REC_18% | BF4: INPUT_SERVICE | BI4: fa1944df608de037db4e0ebe405f00213244878d26b739a443e1d58dbf941b14 | BJ4: 46142.616 | BK4: B2B
A5: Tax Invoice | B5: AR_INVOICE | C5: 107 | D5: Godfrey_Phillips_India_Limited_HO | E5: GPIL_HO_New_Delhi(Services) | F5: GPI-HOC260300038 | H5: HO New Friends Colony | I5: 07AABCG4768K1Z9 | J5: TRANSACTIONS | K5: Receivables | L5: INV_COMPLETE | O5: 46142 | P5: 11263000038 | Q5: 27210294 | R5: 46142 | S5: Customer | T5: 445076 | U5: GODFREY PHILLIPS INDIA LIMITED | V5: GPI TAMIL NADU | W5: GSTIN | X5: 33AABCG4768K1ZE | AA5: 621770 | AB5: 1 | AC5: 621770 | AD5: GST_India | AF5: 998599 | AG5: BUSINESS SUPPORT SERVICES CROSS CHARGED FOR THE PERIOD MAR-26 | AJ5: 0 | AK5: 0 | AL5: 621770 | AM5: Normal | AN5: 18 | AO5: 0 | AP5: 0 | AQ5: 111918.6 | AR5: 0 | AS5: 0 | AT5: 0 | AU5: 0 | AV5: 0 | AY5: 0 | AZ5: 733688.6 | BA5: Y | BB5: N | BC5: 11.7100.111.512110.0000.000000.0000.000000.000000.00000000 | BD5: GPI-HOC260300038 | BE5: HO_INTER-STATE_OTH_REC_18% | BF5: INPUT_SERVICE | BI5: 0269c8365b7deac9cfdcf8c5611795bf1b73cf88592f09a278f8d0e30ec3f843 | BJ5: 46142.595 | BK5: B2B
A6: Tax Invoice | B6: AR_INVOICE | C6: 107 | D6: Godfrey_Phillips_India_Limited_HO | E6: GPIL_HO_New_Delhi(Services) | F6: GPI-HOC260300020 | H6: HO New Friends Colony | I6: 07AABCG4768K1Z9 | J6: TRANSACTIONS | K6: Receivables | L6: INV_COMPLETE | O6: 46141 | P6: 11263000020 | Q6: 27208567 | R6: 46141 | S6: Customer | T6: 866092 | U6: MODI STRATFORD ENTERPRISE MANAGEMENT PRIVATE LIMITED | V6: DELHI-24 | W6: GSTIN | X6: 07AAGCM2799F1Z6 | AA6: 3100 | AB6: 1 | AC6: 3100 | AD6: GST_India | AF6: 997212 | AG6: RENT PREMISES FOR 49,2 ND Floor, COMMUNITY CENTRE,FRIENDS COLONY, NEW DELHI FOR THE M/O APR-'26 | AJ6: 0 | AK6: 0 | AL6: 3100 | AM6: Normal | AN6: 18 | AO6: 279 | AP6: 279 | AQ6: 0 | AR6: 0 | AS6: 0 | AT6: 0 | AU6: 0 | AV6: 0 | AY6: 0 | AZ6: 3658 | BA6: Y | BB6: N | BC6: 11.7100.111.321110.2900.000000.0000.000000.000000.00000000 | BD6: GPI-HOC260300020 | BE6: HO_INTRA-STATE_OTH_REC_18% | BF6: INPUT_SERVICE | BI6: 412b6dbe20b3dd9dd49460f857a82465e70a1c73695ec895a389b4180eb680d3 | BJ6: 46141.666 | BK6: B2B
A7: Tax Invoice | B7: AR_INVOICE | C7: 107 | D7: Godfrey_Phillips_India_Limited_HO | E7: GPIL_HO_New_Delhi(Services) | F7: GPI-HOC260300009 | H7: HO New Friends Colony | I7: 07AABCG4768K1Z9 | J7: TRANSACTIONS | K7: Receivables | L7: INV_COMPLETE | O7: 46135 | P7: 11263000009 | Q7: 27200710 | R7: 46135 | S7: Customer | T7: 1242122 | U7: PHILIP MORRIS INDIA TRADING PRIVATE LIMITED (FORMERLY IPM INDIA WHOLESALE TRADING PVT. LTD.) | V7: 08EB_CIG_GURUG_0001 | W7: GSTIN | X7: 06AACCI0642K2ZQ | AA7: 2069542 | AB7: 1 | AC7: 2069542 | AD7: GST_India | AF7: 998371 | AG7: Being amount of AVF styudy 17 additional cities q1 | AJ7: 0 | AK7: 0 | AL7: 2069542 | AM7: Normal | AN7: 18 | AO7: 0 | AP7: 0 | AQ7: 372517.56 | AR7: 0 | AS7: 0 | AT7: 0 | AU7: 0 | AV7: 0 | AY7: 0 | AZ7: 2442059.6 | BA7: Y | BB7: N | BC7: 11.7100.111.416101.2500.000000.0000.000000.000000.00000000 | BD7: GPI-HOC260300009 | BE7: HO_INTER-STATE_OTH_REC_18% | BF7: INPUT_SERVICE | BI7: a0b2e6bd10d57b94df969e33db9198e583cd8804785eecc23e3811e4bcf2a0a7 | BJ7: 46135.537 | BK7: B2B
A8: Tax Invoice | B8: AR_INVOICE | C8: 107 | D8: Godfrey_Phillips_India_Limited_HO | E8: GPIL_HO_New_Delhi(Services) | F8: GPI-HOC260300024 | H8: HO New Friends Colony | I8: 07AABCG4768K1Z9 | J8: TRANSACTIONS | K8: Receivables | L8: INV_COMPLETE | O8: 46142 | P8: 11263000024 | Q8: 27210244 | R8: 46142 | S8: Customer | T8: 446063 | U8: GODFREY PHILLIPS INDIA LIMITED | V8: GPI UTTARKHAND | W8: GSTIN | X8: 05AABCG4768K1ZD | AA8: 50230 | AB8: 1 | AC8: 50230 | AD8: GST_India | AF8: 998599 | AG8: BUSINESS SUPPORT SERVICES CROSS CHARGED FOR THE PERIOD MAR-26 | AJ8: 0 | AK8: 0 | AL8: 50230 | AM8: Normal | AN8: 18 | AO8: 0 | AP8: 0 | AQ8: 9041.4 | AR8: 0 | AS8: 0 | AT8: 0 | AU8: 0 | AV8: 0 | AY8: 0 | AZ8: 59271.4 | BA8: Y | BB8: N | BC8: 11.7100.111.512110.0000.000000.0000.000000.000000.00000000 | BD8: GPI-HOC260300024 | BE8: HO_INTER-STATE_OTH_REC_18% | BF8: INPUT_SERVICE | BI8: c860f615853261f188f1c404191373b9e3ef5bb45cc2c0e0683b8e3ed3e7d889 | BJ8: 46142.553 | BK8: B2B
A9: Tax Invoice | B9: AR_INVOICE | C9: 107 | D9: Godfrey_Phillips_India_Limited_HO | E9: GPIL_HO_New_Delhi(Services) | F9: GPI-HOC260300033 | H9: HO New Friends Colony | I9: 07AABCG4768K1Z9 | J9: TRANSACTIONS | K9: Receivables | L9: INV_COMPLETE | O9: 46142 | P9: 11263000033 | Q9: 27210289 | R9: 46142 | S9: Customer | T9: 823087 | U9: Godfrey Phillips India Limited, Chhattisgarh | V9: Chhattisgarh_HO | W9: GSTIN | X9: 22AABCG4768K1ZH | AA9: 465529 | AB9: 1 | AC9: 465529 | AD9: GST_India | AF9: 998599 | AG9: BUSINESS SUPPORT SERVICES CROSS CHARGED FOR THE PERIOD MAR-26 | AJ9: 0 | AK9: 0 | AL9: 465529 | AM9: Normal | AN9: 18 | AO9: 0 | AP9: 0 | AQ9: 83795.22 | AR9: 0 | AS9: 0 | AT9: 0 | AU9: 0 | AV9: 0 | AY9: 0 | AZ9: 549324.22 | BA9: Y | BB9: N | BC9: 11.7100.111.512110.0000.000000.0000.000000.000000.00000000 | BD9: GPI-HOC260300033 | BE9: HO_INTER-STATE_OTH_REC_18% | BF9: INPUT_SERVICE | BI9: b11c81bfd051685118061537a33378085dd099874934b2e26748da9c2ac1e20a | BJ9: 46142.587 | BK9: B2B
A10: Tax Invoice | B10: AR_INVOICE | C10: 107 | D10: Godfrey_Phillips_India_Limited_HO | E10: GPIL_HO_New_Delhi(Services) | F10: GPI-HOC260300039 | H10: HO New Friends Colony | I10: 07AABCG4768K1Z9 | J10: TRANSACTIONS | K10: Receivables | L10: INV_COMPLETE | O10: 46142 | P10: 11263000039 | Q10: 27210340 | R10: 46142 | S10: Customer | T10: 2892 | U10: Godfrey Phillips India Limited, Hyderabad | V10: I112001 | W10: GSTIN | X10: 36AABCG4768K1Z8 | AA10: 1057196 | AB10: 1 | AC10: 1057196 | AD10: GST_India | AF10: 998599 | AG10: BUSINESS SUPPORT SERVICES CROSS CHARGED FOR THE PERIOD MAR-26 | AJ10: 0 | AK10: 0 | AL10: 1057196 | AM10: Normal | AN10: 18 | AO10: 0 | AP10: 0 | AQ10: 190295.28 | AR10: 0 | AS10: 0 | AT10: 0 | AU10: 0 | AV10: 0 | AY10: 0 | AZ10: 1247491.3 | BA10: Y | BB10: N | BC10: 11.7100.111.512110.0000.000000.0000.000000.000000.00000000 | BD10: GPI-HOC260300039 | BE10: HO_INTER-STATE_OTH_REC_18% | BF10: INPUT_SERVICE | BI10: cf63d7b74bb26569ab0910c6e6b4c7e48020d1c35e7f801e71cc4b87d97de310 | BJ10: 46142.608 | BK10: B2B
A11: Tax Invoice | B11: AR_INVOICE | C11: 107 | D11: Godfrey_Phillips_India_Limited_HO | E11: GPIL_HO_New_Delhi(Services) | F11: GPI-HOC260300043 | H11: HO New Friends Colony | I11: 07AABCG4768K1Z9 | J11: TRANSACTIONS | K11: Receivables | L11: INV_COMPLETE | O11: 46142 | P11: 11263000043 | Q11: 27210504 | R11: 46142 | S11: Customer | T11: 1006109 | U11: GODFREY PHILLIPS INDIA LIMITED (HR) | V11: 08EB_ALL_DELHI_0004 | W11: GSTIN | X11: 06AABCG4768K1ZB | AA11: 641574 | AB11: 1 | AC11: 641574 | AD11: GST_India | AF11: 998599 | AG11: BUSINESS SUPPORT SERVICES CROSS CHARGED FOR THE PERIOD MAR-26 | AJ11: 0 | AK11: 0 | AL11: 641574 | AM11: Normal | AN11: 18 | AO11: 0 | AP11: 0 | AQ11: 115483.32 | AR11: 0 | AS11: 0 | AT11: 0 | AU11: 0 | AV11: 0 | AY11: 0 | AZ11: 757057.32 | BA11: Y | BB11: N | BC11: 11.7100.111.512110.0000.000000.0000.000000.000000.00000000 | BD11: GPI-HOC260300043 | BE11: HO_INTER-STATE_OTH_REC_18% | BF11: INPUT_SERVICE | BI11: 683241a1e4737ca483c28547f9b7401d539cb1ef305c31be28b2e77e6c008af4 | BJ11: 46142.664 | BK11: B2B
A12: Tax Invoice | B12: AR_INVOICE | C12: 107 | D12: Godfrey_Phillips_India_Limited_HO | E12: GPIL_HO_New_Delhi(Services) | F12: GPI-HOC260300017 | H12: HO New Friends Colony | I12: 07AABCG4768K1Z9 | J12: TRANSACTIONS | K12: Receivables | L12: INV_COMPLETE | O12: 46141 | P12: 11263000017 | Q12: 27208564 | R12: 46141 | S12: Customer | T12: 5137 | U12: Bina Fashion N Food (P) Ltd | V12: Ho45 | W12: GSTIN | X12: 07AABCB5582A1Z1 | AA12: 246500 | AB12: 1 | AC12: 246500 | AD12: GST_India | AF12: 997212 | AG12: RENT PREMISES FOR GROUND FLOOR,4,COMMUNITY CENTRE,FRIENDS COLONY,NEW DELHI-110025 2465 SQ.FT FOR THE M/O APR-'26 | AJ12: 0 | AK12: 0 | AL12: 246500 | AM12: Normal | AN12: 18 | AO12: 22185 | AP12: 22185 | AQ12: 0 | AR12: 0 | AS12: 0 | AT12: 0 | AU12: 0 | AV12: 0 | AY12: 0 | AZ12: 290870 | BA12: Y | BB12: N | BC12: 11.7100.111.321110.2900.000000.0000.000000.000000.00000000 | BD12: GPI-HOC260300017 | BE12: HO_INTRA-STATE_OTH_REC_18% | BF12: INPUT_SERVICE | BI12: 8483eb2ee008d604d62eb296a596609f01c6f41996cd78330bf9c3231458be73 | BJ12: 46141.662 | BK12: B2B
A13: Tax Invoice | B13: AR_INVOICE | C13: 107 | D13: Godfrey_Phillips_India_Limited_HO | E13: GPIL_HO_New_Delhi(Services) | F13: GPI-HOC260300008 | H13: HO New Friends Colony | I13: 07AABCG4768K1Z9 | J13: TRANSACTIONS | K13: Receivables | L13: INV_COMPLETE | O13: 46134 | P13: 11263000008 | Q13: 27198626 | R13: 46134 | S13: Customer | T13: 1242122 | U13: PHILIP MORRIS INDIA TRADING PRIVATE LIMITED (FORMERLY IPM INDIA WHOLESALE TRADING PVT. LTD.) | V13: 08EB_CIG_GURUG_0001 | W13: GSTIN | X13: 06AACCI0642K2ZQ | AA13: 2985024 | AB13: 1 | AC13: 2985024 | AD13: GST_India | AF13: 998371 | AG13: Being amount of AVF Study 5FC Q1JFM | AJ13: 0 | AK13: 0 | AL13: 2985024 | AM13: Normal | AN13: 18 | AO13: 0 | AP13: 0 | AQ13: 537304.32 | AR13: 0 | AS13: 0 | AT13: 0 | AU13: 0 | AV13: 0 | AY13: 0 | AZ13: 3522328.3 | BA13: Y | BB13: N | BC13: 11.7100.111.416101.2500.000000.0000.000000.000000.00000000 | BD13: GPI-HOC260300008 | BE13: HO_INTER-STATE_OTH_REC_18% | BF13: INPUT_SERVICE | BI13: b4bfe34d16f4e5b2e17d203831a50dce31440e36f90d67945e9c9da29e0e8d8b | BJ13: 46134.631 | BK13: B2B
A14: Manual Regime Entry | B14: MANUAL_ENTRY | C14: 107 | D14: Godfrey_Phillips_India_Limited_HO | E14: GPIL_HO_New_Delhi(Services) | F14: GPI-HOC260300066 | H14: HO New Friends Colony | I14: 07AABCG4768K1Z9 | J14: MANUAL_ENTRY | K14: Asia/Pacific Localizations | L14: MANUAL_ENTRY_CREATE | M14: Form Entry | N14: LIABILITY | O14: 46142 | P14: 108621355 | Q14: 108621355 | R14: 46142 | S14: CUSTOMER | T14: 2894 | U14: Godfrey Phillips India Limited, Ho | V14: HOC_ISD | X14: 07AABCG4768K3Z7 | AA14: 0 | AB14: 0 | AC14: 15615254 | AD14: GST_India | AE14: Services_ISD | AF14: 998346 | AG14: Services_ISD | AJ14: 0 | AK14: 0 | AL14: 15615254 | AM14: Normal | AN14: 18 | AO14: 1405372.8 | AP14: 1405372.8 | AQ14: 0 | AR14: 0 | AS14: 0 | AT14: 0 | AU14: 0 | AV14: 0 | AY14: 0 | AZ14: 18425999 | BA14: Y | BB14: N | BC14: 11.7100.111.512120.0000.000000.0000.000000.000000.00000000 | BI14: a541de5602a0b6a8e2003437be64d0e2e63b3ff9065d1760969b1bab75b9f4d0 | BJ14: 46142.843 | BK14: B2B
A15: Tax Invoice | B15: AR_INVOICE | C15: 107 | D15: Godfrey_Phillips_India_Limited_HO | E15: GPIL_HO_New_Delhi(Services) | F15: GPI-HOC260300031 | H15: HO New Friends Colony | I15: 07AABCG4768K1Z9 | J15: TRANSACTIONS | K15: Receivables | L15: INV_COMPLETE | O15: 46142 | P15: 11263000031 | Q15: 27210283 | R15: 46142 | S15: Customer | T15: 445073 | U15: GODFREY PHILLIPS INDIA LIMITED | V15: GPI-JHARKHAND | W15: GSTIN | X15: 20AABCG4768K1ZL | AA15: 226700 | AB15: 1 | AC15: 226700 | AD15: GST_India | AF15: 998599 | AG15: BUSINESS SUPPORT SERVICES CROSS CHARGED FOR THE PERIOD MAR-26 | AJ15: 0 | AK15: 0 | AL15: 226700 | AM15: Normal | AN15: 18 | AO15: 0 | AP15: 0 | AQ15: 40806 | AR15: 0 | AS15: 0 | AT15: 0 | AU15: 0 | AV15: 0 | AY15: 0 | AZ15: 267506 | BA15: Y | BB15: N | BC15: 11.7100.111.512110.0000.000000.0000.000000.000000.00000000 | BD15: GPI-HOC260300031 | BE15: HO_INTER-STATE_OTH_REC_18% | BF15: INPUT_SERVICE | BI15: ebd7cf4d39f52b49f38c34188d5cf8ce4452b6144ded985de6b759edda3a3af7 | BJ15: 46142.585 | BK15: B2B
A16: Tax Invoice | B16: AR_INVOICE | C16: 107 | D16: Godfrey_Phillips_India_Limited_HO | E16: GPIL_HO_New_Delhi(Services) | F16: GPI-HOC260300001 | H16: HO New Friends Colony | I16: 07AABCG4768K1Z9 | J16: TRANSACTIONS | K16: Receivables | L16: INV_COMPLETE | O16: 46113 | P16: 11263000001 | Q16: 27165327 | R16: 46113 | S16: Customer | T16: 1044110 | U16: Godfrey Phillips India Limited, Jaipur | V16: HOJGM | W16: GSTIN | X16: 23AABCG4768K1ZF | AA16: 57185.63 | AB16: 1 | AC16: 57185.63 | AD16: GST_India | AF16: 84713010 | AG16: Dell laptop vide asset no.227618 (S.NO.17W3TB4) | AJ16: 0 | AK16: 0 | AL16: 57185.63 | AM16: Normal | AN16: 18 | AO16: 0 | AP16: 0 | AQ16: 10293.41 | AR16: 0 | AS16: 0 | AT16: 0 | AU16: 0 | AV16: 0 | AY16: 0 | AZ16: 67479.04 | BA16: Y | BB16: N | BC16: 11.7100.111.511050.0000.000000.0000.000000.000000.00000000 | BD16: GPI-HOC260300001 | BE16: HO_INTER-STATE_OTH_REC_18% | BF16: CAPITAL_GOODS | BI16: 6bad53248db99ce5a76d4107c44cb79180273639c0af18f5c9955f81584a64ae | BJ16: 46113.506 | BK16: B2B
A17: Tax Invoice | B17: AR_INVOICE | C17: 107 | D17: Godfrey_Phillips_India_Limited_HO | E17: GPIL_HO_New_Delhi(Services) | F17: GPI-HOC260300005 | H17: HO New Friends Colony | I17: 07AABCG4768K1Z9 | J17: TRANSACTIONS | K17: Receivables | L17: INV_COMPLETE | O17: 46129 | P17: 11263000005 | Q17: 27192922 | R17: 46129 | S17: Customer | T17: 469067 | U17: EMPLOYEE | V17: EMPLOYEE- DELHI | AA17: 3375 | AB17: 1 | AC17: 3375 | AD17: GST_India | AF17: 84713010 | AG17: Dell Latitude Asset no.111591 Mr.Ashutosh (gst assessable value Rs.13500 | AJ17: 0 | AK17: 0 | AL17: 13500 | AM17: Normal | AN17: 18 | AO17: 1215 | AP17: 1215 | AQ17: 0 | AR17: 0 | AS17: 0 | AT17: 0 | AU17: 0 | AV17: 0 | AY17: 0 | AZ17: 5805 | BA17: Y | BB17: N | BC17: 11.7100.111.511500.0000.000000.0000.000000.000000.00000000 | BD17: GPI-HOC260300005 | BE17: HO_INTRA-STATE_OTH_REC_18% | BF17: CAPITAL_GOODS | BK17: B2CS
A18: Tax Invoice | B18: AR_INVOICE | C18: 107 | D18: Godfrey_Phillips_India_Limited_HO | E18: GPIL_HO_New_Delhi(Services) | F18: GPI-HOC260300018 | H18: HO New Friends Colony | I18: 07AABCG4768K1Z9 | J18: TRANSACTIONS | K18: Receivables | L18: INV_COMPLETE | O18: 46141 | P18: 11263000018 | Q18: 27208565 | R18: 46141 | S18: Customer | T18: 5137 | U18: Bina Fashion N Food (P) Ltd | V18: Ho45 | W18: GSTIN | X18: 07AABCB5582A1Z1 | AA18: 285000 | AB18: 1 | AC18: 285000 | AD18: GST_India | AF18: 997212 | AG18: RENT PREMISES FOR GROUND FLOOR,49, COMMUNITY CENTRE, NEW FRIENDS COLONY, NEW DELHI-110025 AREA 1900 SQFT FOR THE M/O APR-'26 | AJ18: 0 | AK18: 0 | AL18: 285000 | AM18: Normal | AN18: 18 | AO18: 25650 | AP18: 25650 | AQ18: 0 | AR18: 0 | AS18: 0 | AT18: 0 | AU18: 0 | AV18: 0 | AY18: 0 | AZ18: 336300 | BA18: Y | BB18: N | BC18: 11.7100.111.321110.2900.000000.0000.000000.000000.00000000 | BD18: GPI-HOC260300018 | BE18: HO_INTRA-STATE_OTH_REC_18% | BF18: INPUT_SERVICE | BI18: addb2878081b8fa351cfce675717d9baa8278c22fb874fa2c45162140cd74ac6 | BJ18: 46141.664 | BK18: B2B
A19: Tax Invoice | B19: AR_INVOICE | C19: 107 | D19: Godfrey_Phillips_India_Limited_HO | E19: GPIL_HO_New_Delhi(Services) | F19: GPI-HOC260300030 | H19: HO New Friends Colony | I19: 07AABCG4768K1Z9 | J19: TRANSACTIONS | K19: Receivables | L19: INV_COMPLETE | O19: 46142 | P19: 11263000030 | Q19: 27210282 | R19: 46142 | S19: Customer | T19: 3311 | U19: Godfrey Phillips India Limited, Kolkata | V19: I111601 | W19: GSTIN | X19: 19AABCG4768K1Z4 | AA19: 248566 | AB19: 1 | AC19: 248566 | AD19: GST_India | AF19: 998599 | AG19: BUSINESS SUPPORT SERVICES CROSS CHARGED FOR THE PERIOD MAR-26 | AJ19: 0 | AK19: 0 | AL19: 248566 | AM19: Normal | AN19: 18 | AO19: 0 | AP19: 0 | AQ19: 44741.88 | AR19: 0 | AS19: 0 | AT19: 0 | AU19: 0 | AV19: 0 | AY19: 0 | AZ19: 293307.88 | BA19: Y | BB19: N | BC19: 11.7100.111.512110.0000.000000.0000.000000.000000.00000000 | BD19: GPI-HOC260300030 | BE19: HO_INTER-STATE_OTH_REC_18% | BF19: INPUT_SERVICE | BI19: 4db2621fcb42dab14cb2b6f13655acda3666344b3c592e41099df98540e0f855 | BJ19: 46142.583 | BK19: B2B
A20: Tax Invoice | B20: AR_INVOICE | C20: 107 | D20: Godfrey_Phillips_India_Limited_HO | E20: GPIL_HO_New_Delhi(Services) | F20: GPI-HOC260300040 | H20: HO New Friends Colony | I20: 07AABCG4768K1Z9 | J20: TRANSACTIONS | K20: Receivables | L20: INV_COMPLETE | O20: 46142 | P20: 11263000040 | Q20: 27210345 | R20: 46142 | S20: Customer | T20: 2893 | U20: GODFREY PHILLIPS INDIA LIMITED, GUNTUR | V20: I111401 | W20: GSTIN | X20: 37AABCG4768K1Z6 | AA20: 4288144 | AB20: 1 | AC20: 4288144 | AD20: GST_India | AF20: 998599 | AG20: BUSINESS SUPPORT SERVICES CROSS CHARGED FOR THE PERIOD MAR-26 | AJ20: 0 | AK20: 0 | AL20: 4288144 | AM20: Normal | AN20: 18 | AO20: 0 | AP20: 0 | AQ20: 771865.92 | AR20: 0 | AS20: 0 | AT20: 0 | AU20: 0 | AV20: 0 | AY20: 0 | AZ20: 5060009.9 | BA20: Y | BB20: N | BC20: 11.7100.111.512110.0000.000000.0000.000000.000000.00000000 | BD20: GPI-HOC260300040 | BE20: HO_INTER-STATE_OTH_REC_18% | BF20: INPUT_SERVICE | BI20: fdd6fdeba31ee4f01676945f84c3b967d0cc6975723786eb7e4c036ccad2f75d | BJ20: 46142.61 | BK20: B2B
A21: Tax Invoice | B21: AR_INVOICE | C21: 107 | D21: Godfrey_Phillips_India_Limited_HO | E21: GPIL_HO_New_Delhi(Services) | F21: GPI-HOC260300029 | H21: HO New Friends Colony | I21: 07AABCG4768K1Z9 | J21: TRANSACTIONS | K21: Receivables | L21: INV_COMPLETE | O21: 46142 | P21: 11263000029 | Q21: 27210281 | R21: 46142 | S21: Customer | T21: 445072 | U21: GODFREY PHILLIPS INDIA LIMITED | V21: GPI -ASSAM | W21: GSTIN | X21: 18AABCG4768K1Z6 | AA21: 96318 | AB21: 1 | AC21: 96318 | AD21: GST_India | AF21: 998599 | AG21: BUSINESS SUPPORT SERVICES CROSS CHARGED FOR THE PERIOD MAR-26 | AJ21: 0 | AK21: 0 | AL21: 96318 | AM21: Normal | AN21: 18 | AO21: 0 | AP21: 0 | AQ21: 17337.24 | AR21: 0 | AS21: 0 | AT21: 0 | AU21: 0 | AV21: 0 | AY21: 0 | AZ21: 113655.24 | BA21: Y | BB21: N | BC21: 11.7100.111.512110.0000.000000.0000.000000.000000.00000000 | BD21: GPI-HOC260300029 | BE21: HO_INTER-STATE_OTH_REC_18% | BF21: INPUT_SERVICE | BI21: 27bbf7a0070406f35b823b2d097dcd71978d6d8027de59ab1bfc311e621b80c5 | BJ21: 46142.581 | BK21: B2B
A22: Tax Invoice | B22: AR_INVOICE | C22: 107 | D22: Godfrey_Phillips_India_Limited_HO | E22: GPIL_HO_New_Delhi(Services) | F22: GPI-HOC260300011 | H22: HO New Friends Colony | I22: 07AABCG4768K1Z9 | J22: TRANSACTIONS | K22: Receivables | L22: INV_COMPLETE | O22: 46141 | P22: 11263000011 | Q22: 27208486 | R22: 46141 | S22: Customer | T22: 56078 | U22: INTERNATIONAL RESEARCH PARK LABORATORIES LTD | V22: INT4CC | AA22: 5000 | AB22: 1 | AC22: 5000 | AD22: GST_India | AF22: 997212 | AG22: RENT PREMISES FOR IST FLOOR, 4,COMMMUNITY CENTRE,NFC,N.DELHI FOR THE M/O APR-'26 | AJ22: 0 | AK22: 0 | AL22: 5000 | AM22: Normal | AN22: 18 | AO22: 450 | AP22: 450 | AQ22: 0 | AR22: 0 | AS22: 0 | AT22: 0 | AU22: 0 | AV22: 0 | AY22: 0 | AZ22: 5900 | BA22: Y | BB22: N | BC22: 11.7100.111.321110.2900.000000.0000.000000.000000.00000000 | BD22: GPI-HOC260300011 | BE22: HO_INTRA-STATE_OTH_REC_18% | BF22: B2C | BK22: B2CS
A23: Tax Invoice | B23: AR_INVOICE | C23: 107 | D23: Godfrey_Phillips_India_Limited_HO | E23: GPIL_HO_New_Delhi(Services) | F23: GPI-HOC260300004 | H23: HO New Friends Colony | I23: 07AABCG4768K1Z9 | J23: TRANSACTIONS | K23: Receivables | L23: INV_COMPLETE | O23: 46128 | P23: 11263000004 | Q23: 27190294 | R23: 46128 | S23: Customer | T23: 2892 | U23: Godfrey Phillips India Limited, Hyderabad | V23: I112001 | W23: GSTIN | X23: 36AABCG4768K1Z8 | AA23: 81783.1 | AB23: 1 | AC23: 81783.1 | AD23: GST_India | AF23: 84713010 | AG23: HP LAPTOP S.NO.5CD6106BJ0 (ASSET NO.278586) | AJ23: 0 | AK23: 0 | AL23: 81783.1 | AM23: Normal | AN23: 18 | AO23: 0 | AP23: 0 | AQ23: 14720.96 | AR23: 0 | AS23: 0 | AT23: 0 | AU23: 0 | AV23: 0 | AY23: 0 | AZ23: 96504.06 | BA23: Y | BB23: N | BC23: 11.7100.111.511100.0000.000000.0000.000000.000000.00000000 | BD23: GPI-HOC260300004 | BE23: HO_INTER-STATE_OTH_REC_18% | BF23: CAPITAL_GOODS | BI23: f3e10e29f82bb3b9a53b56bb22a49de1eba23d8154b2d1289272b5848803356d | BJ23: 46128.533 | BK23: B2B
A24: Credit Memo | B24: AR_INVOICE | C24: 107 | D24: Godfrey_Phillips_India_Limited_HO | E24: GPIL_HO_New_Delhi(Services) | F24: GPI-HOC260300001-01-APR-26 | H24: HO New Friends Colony | I24: 07AABCG4768K1Z9 | J24: TRANSACTIONS | K24: Receivables | L24: CM_COMPLETE | O24: 46113 | P24: 11261000001 | Q24: 27165331 | R24: 46113 | S24: Customer | T24: 1044110 | U24: Godfrey Phillips India Limited, Jaipur | V24: HOJGM | W24: GSTIN | X24: 23AABCG4768K1ZF | AA24: -57185.63 | AB24: 1 | AC24: -57185.63 | AD24: GST_India | AF24: 84713010 | AG24: CANCELLATION OF INVOICE NO.GPI/HOC260300001 (ASSET NO.227618) | AJ24: 0 | AK24: 0 | AL24: -57185.63 | AM24: Normal | AN24: 18 | AO24: 0 | AP24: 0 | AQ24: -10293.41 | AR24: 0 | AS24: 0 | AT24: 0 | AU24: 0 | AV24: 0 | AY24: 0 | AZ24: -67479.04 | BA24: Y | BB24: N | BC24: 11.7100.111.511050.0000.000000.0000.000000.000000.00000000 | BD24: GPI-HOC260200001 | BE24: HO_INTER-STATE_OTH_REC_18% | BF24: CAPITAL_GOODS | BI24: 8060ffbe52f2cc7c64cd919d7d678517a205864fd9793b127d837e0fc9c1b456 | BJ24: 46113.533 | BK24: B2B-CN
A25: Tax Invoice | B25: AR_INVOICE | C25: 107 | D25: Godfrey_Phillips_India_Limited_HO | E25: GPIL_HO_New_Delhi(Services) | F25: GPI-HOC260300021 | H25: HO New Friends Colony | I25: 07AABCG4768K1Z9 | J25: TRANSACTIONS | K25: Receivables | L25: INV_COMPLETE | O25: 46141 | P25: 11263000021 | Q25: 27208568 | R25: 46141 | S25: Customer | T25: 1052115 | U25: A AND V ZIPPERS PVT. LIMITED | V25: 08EB_ALL_DELHI_0007 | W25: GSTIN | X25: 07AADCA3655R1Z7 | AA25: 5000 | AB25: 1 | AC25: 5000 | AD25: GST_India | AF25: 997212 | AG25: RENT PREMISES FOR 2ND FLOOR,49, COMMUNITY CENTRE,NFC,N.DELHI 40 SQFT@125/- FOR THE M/O APR-'26 | AJ25: 0 | AK25: 0 | AL25: 5000 | AM25: Normal | AN25: 18 | AO25: 450 | AP25: 450 | AQ25: 0 | AR25: 0 | AS25: 0 | AT25: 0 | AU25: 0 | AV25: 0 | AY25: 0 | AZ25: 5900 | BA25: Y | BB25: N | BC25: 11.7100.111.321110.2900.000000.0000.000000.000000.00000000 | BD25: GPI-HOC260300021 | BE25: HO_INTRA-STATE_OTH_REC_18% | BF25: INPUT_SERVICE | BI25: e8e37ff586f2aab0e14f38d9b3bd4f473d3024f751fb6ae5783d79a5998c5fba | BJ25: 46141.668 | BK25: B2B
A26: Tax Invoice | B26: AR_INVOICE | C26: 107 | D26: Godfrey_Phillips_India_Limited_HO | E26: GPIL_HO_New_Delhi(Services) | F26: GPI-HOC260300019 | H26: HO New Friends Colony | I26: 07AABCG4768K1Z9 | J26: TRANSACTIONS | K26: Receivables | L26: INV_COMPLETE | O26: 46141 | P26: 11263000019 | Q26: 27208566 | R26: 46141 | S26: Customer | T26: 5137 | U26: Bina Fashion N Food (P) Ltd | V26: Ho45 | W26: GSTIN | X26: 07AABCB5582A1Z1 | AA26: 500000 | AB26: 1 | AC26: 500000 | AD26: GST_India | AF26: 997212 | AG26: RENT PREMISES FOR 2ND & 3RD FLOOR, 49, COMMUNITY CENTRE,FRIENDS COLONY , NEW DELHI-110025 AREA 4000 SQFT FOR THE M/O APR-'26 | AJ26: 0 | AK26: 0 | AL26: 500000 | AM26: Normal | AN26: 18 | AO26: 45000 | AP26: 45000 | AQ26: 0 | AR26: 0 | AS26: 0 | AT26: 0 | AU26: 0 | AV26: 0 | AY26: 0 | AZ26: 590000 | BA26: Y | BB26: N | BC26: 11.7100.111.321110.2900.000000.0000.000000.000000.00000000 | BD26: GPI-HOC260300019 | BE26: HO_INTRA-STATE_OTH_REC_18% | BF26: INPUT_SERVICE | BI26: bbf022a3da0bdd7fb98cfea252dce2c9fee214d3a6169a56eb4b9c0d4765bda1 | BJ26: 46141.666 | BK26: B2B
A27: Tax Invoice | B27: AR_INVOICE | C27: 107 | D27: Godfrey_Phillips_India_Limited_HO | E27: GPIL_HO_New_Delhi(Services) | F27: GPI-HOC260300002 | H27: HO New Friends Colony | I27: 07AABCG4768K1Z9 | J27: TRANSACTIONS | K27: Receivables | L27: INV_COMPLETE | O27: 46113 | P27: 11263000002 | Q27: 27165329 | R27: 46113 | S27: Customer | T27: 1045110 | U27: Godfrey Phillips India Limited, Jammu | V27: HOJBG | W27: GSTIN | X27: 01AABCG4768K1ZL | AA27: 50526 | AB27: 1 | AC27: 50526 | AD27: GST_India | AF27: 84713010 | AG27: Being amount of dell laptop vide asset no.201615 (Nitin Gupta) | AJ27: 0 | AK27: 0 | AL27: 50526 | AM27: Normal | AN27: 18 | AO27: 0 | AP27: 0 | AQ27: 9094.68 | AR27: 0 | AS27: 0 | AT27: 0 | AU27: 0 | AV27: 0 | AY27: 0 | AZ27: 59620.68 | BA27: Y | BB27: N | BC27: 11.7100.111.511250.0000.000000.0000.000000.000000.00000000 | BD27: GPI-HOC260300002 | BE27: HO_INTER-STATE_OTH_REC_18% | BF27: CAPITAL_GOODS | BI27: 1d0f50957afc2bbf15981ceefdf6919df62eb1aa189ff407681f554b1fdaea8c | BJ27: 46113.516 | BK27: B2B
A28: Tax Invoice | B28: AR_INVOICE | C28: 107 | D28: Godfrey_Phillips_India_Limited_HO | E28: GPIL_HO_New_Delhi(Services) | F28: GPI-HOC260300035 | H28: HO New Friends Colony | I28: 07AABCG4768K1Z9 | J28: TRANSACTIONS | K28: Receivables | L28: INV_COMPLETE | O28: 46142 | P28: 11263000035 | Q28: 27210291 | R28: 46142 | S28: Customer | T28: 446062 | U28: Godfrey Phillips India Limited | V28: GPI GOA | W28: GSTIN | X28: 30AABCG4768K1ZK | AA28: 99004 | AB28: 1 | AC28: 99004 | AD28: GST_India | AF28: 998599 | AG28: BUSINESS SUPPORT SERVICES CROSS CHARGED FOR THE PERIOD MAR-26 | AJ28: 0 | AK28: 0 | AL28: 99004 | AM28: Normal | AN28: 18 | AO28: 0 | AP28: 0 | AQ28: 17820.72 | AR28: 0 | AS28: 0 | AT28: 0 | AU28: 0 | AV28: 0 | AY28: 0 | AZ28: 116824.72 | BA28: Y | BB28: N | BC28: 11.7100.111.512110.0000.000000.0000.000000.000000.00000000 | BD28: GPI-HOC260300035 | BE28: HO_INTER-STATE_OTH_REC_18% | BF28: INPUT_SERVICE | BI28: ab165f6a9243ab3283f5013b6586a65b4d06b7fe408b230d392ebd7250e08445 | BJ28: 46142.591 | BK28: B2B
A29: Tax Invoice | B29: AR_INVOICE | C29: 107 | D29: Godfrey_Phillips_India_Limited_HO | E29: GPIL_HO_New_Delhi(Services) | F29: GPI-HOC260300012 | H29: HO New Friends Colony | I29: 07AABCG4768K1Z9 | J29: TRANSACTIONS | K29: Receivables | L29: INV_COMPLETE | O29: 46141 | P29: 11263000012 | Q29: 27208487 | R29: 46141 | S29: Customer | T29: 156023 | U29: RAJPUTANA DEVELOPERS LIMITED | V29: 53 CC | W29: GSTIN | X29: 07AAECR2482G1ZD | AA29: 11000 | AB29: 1 | AC29: 11000 | AD29: GST_India | AF29: 997212 | AG29: RENT PREMISES FOR 14,OMAXE SQAURE, JASOLA, NEW DELHI FOR THE M/O APR-'26 | AJ29: 0 | AK29: 0 | AL29: 11000 | AM29: Normal | AN29: 18 | AO29: 990 | AP29: 990 | AQ29: 0 | AR29: 0 | AS29: 0 | AT29: 0 | AU29: 0 | AV29: 0 | AY29: 0 | AZ29: 12980 | BA29: Y | BB29: N | BC29: 11.7100.111.321110.2900.000000.0000.000000.000000.00000000 | BD29: GPI-HOC260300012 | BE29: HO_INTRA-STATE_OTH_REC_18% | BF29: INPUT_SERVICE | BI29: 5158c19577192d526170ffe5a5f51a18273f61bbe5cf3d68b4522f8d9185b506 | BJ29: 46141.649 | BK29: B2B
A30: Tax Invoice | B30: AR_INVOICE | C30: 107 | D30: Godfrey_Phillips_India_Limited_HO | E30: GPIL_HO_New_Delhi(Services) | F30: GPI-HOC260300041 | H30: HO New Friends Colony | I30: 07AABCG4768K1Z9 | J30: TRANSACTIONS | K30: Receivables | L30: INV_COMPLETE | O30: 46142 | P30: 11263000041 | Q30: 27210351 | R30: 46142 | S30: Customer | T30: 445067 | U30: GODFREY PHILLIPS INDIA LIMITED | V30: GPI MOHALI | W30: GSTIN | X30: 03AABCG4768K1ZH | AA30: 462317 | AB30: 1 | AC30: 462317 | AD30: GST_India | AF30: 998599 | AG30: BUSINESS SUPPORT SERVICES CROSS CHARGED FOR THE PERIOD MAR-26 | AJ30: 0 | AK30: 0 | AL30: 462317 | AM30: Normal | AN30: 18 | AO30: 0 | AP30: 0 | AQ30: 83217.06 | AR30: 0 | AS30: 0 | AT30: 0 | AU30: 0 | AV30: 0 | AY30: 0 | AZ30: 545534.06 | BA30: Y | BB30: N | BC30: 11.7100.111.512110.0000.000000.0000.000000.000000.00000000 | BD30: GPI-HOC260300041 | BE30: HO_INTER-STATE_OTH_REC_18% | BF30: INPUT_SERVICE | BI30: 672bd21e04b274039757f9ef2196cba8edad1f325101a1fdd8748915be5bd8f0 | BJ30: 46142.614 | BK30: B2B
A31: Tax Invoice | B31: AR_INVOICE | C31: 107 | D31: Godfrey_Phillips_India_Limited_HO | E31: GPIL_HO_New_Delhi(Services) | F31: GPI-HOC260300006 | H31: HO New Friends Colony | I31: 07AABCG4768K1Z9 | J31: TRANSACTIONS | K31: Receivables | L31: INV_COMPLETE | O31: 46133 | P31: 11263000006 | Q31: 27199210 | R31: 46133 | S31: Customer | T31: 1077115 | U31: FERRERO INDIA PVT LTD-PUNE | V31: 08EB_ALL_PUNE_0001 | W31: GSTIN | X31: 27AAACF8110B1Z8 | AA31: 329343.3 | AB31: 1 | AC31: 329343.3 | AD31: GST_India | AF31: 998599 | AG31: Being amount of other support services for ferrero fusion Q4 FY26 | AJ31: 0 | AK31: 0 | AL31: 329343.3 | AM31: Normal | AN31: 18 | AO31: 0 | AP31: 0 | AQ31: 59281.79 | AR31: 0 | AS31: 0 | AT31: 0 | AU31: 0 | AV31: 0 | AY31: 0 | AZ31: 388625.09 | BA31: Y | BB31: N | BC31: 11.7100.371.416101.2500.000000.0000.000000.000000.00000000 | BD31: GPI-HOC260300006 | BE31: HO_INTER-STATE_OTH_REC_18% | BF31: INPUT_SERVICE | BI31: eb694a307d43ef7c9ad79cd32033351d2c065acd2740bf9b9b2352c292a8d475 | BJ31: 46133.797 | BK31: B2B
A32: Tax Invoice | B32: AR_INVOICE | C32: 107 | D32: Godfrey_Phillips_India_Limited_HO | E32: GPIL_HO_New_Delhi(Services) | F32: GPI-HOC260300025 | H32: HO New Friends Colony | I32: 07AABCG4768K1Z9 | J32: TRANSACTIONS | K32: Receivables | L32: INV_COMPLETE | O32: 46142 | P32: 11263000025 | Q32: 27210245 | R32: 46142 | S32: Customer | T32: 445069 | U32: GODFREY PHILLIPS INDIA LIMITED | V32: GPI JAIPUR | W32: GSTIN | X32: 08AABCG4768K1Z7 | AA32: 1495479 | AB32: 1 | AC32: 1495479 | AD32: GST_India | AF32: 998599 | AG32: BUSINESS SUPPORT SERVICES CROSS CHARGED FOR THE PERIOD MAR-26 | AJ32: 0 | AK32: 0 | AL32: 1495479 | AM32: Normal | AN32: 18 | AO32: 0 | AP32: 0 | AQ32: 269186.22 | AR32: 0 | AS32: 0 | AT32: 0 | AU32: 0 | AV32: 0 | AY32: 0 | AZ32: 1764665.2 | BA32: Y | BB32: N | BC32: 11.7100.111.512110.0000.000000.0000.000000.000000.00000000 | BD32: GPI-HOC260300025 | BE32: HO_INTER-STATE_OTH_REC_18% | BF32: INPUT_SERVICE | BI32: 6d4f37769b8339f491f3b3d120057f66cdf1131907f50cc3e5652c35d04ab850 | BJ32: 46142.553 | BK32: B2B
A33: Tax Invoice | B33: AR_INVOICE | C33: 107 | D33: Godfrey_Phillips_India_Limited_HO | E33: GPIL_HO_New_Delhi(Services) | F33: GPI-HOC260300034 | H33: HO New Friends Colony | I33: 07AABCG4768K1Z9 | J33: TRANSACTIONS | K33: Receivables | L33: INV_COMPLETE | O33: 46142 | P33: 11263000034 | Q33: 27210290 | R33: 46142 | S33: Customer | T33: 445075 | U33: Godfrey Phillips India Limited | V33: GPI INDORE | W33: GSTIN | X33: 23AABCG4768K1ZF | AA33: 901643 | AB33: 1 | AC33: 901643 | AD33: GST_India | AF33: 998599 | AG33: BUSINESS SUPPORT SERVICES CROSS CHARGED FOR THE PERIOD MAR-26 | AJ33: 0 | AK33: 0 | AL33: 901643 | AM33: Normal | AN33: 18 | AO33: 0 | AP33: 0 | AQ33: 162295.74 | AR33: 0 | AS33: 0 | AT33: 0 | AU33: 0 | AV33: 0 | AY33: 0 | AZ33: 1063938.7 | BA33: Y | BB33: N | BC33: 11.7100.111.512110.0000.000000.0000.000000.000000.00000000 | BD33: GPI-HOC260300034 | BE33: HO_INTER-STATE_OTH_REC_18% | BF33: INPUT_SERVICE | BI33: 3287af05dc718a3825d3212fb712505177eabc9b6b6e4bd8f2ebbf0f4c626a52 | BJ33: 46142.589 | BK33: B2B
A34: Tax Invoice | B34: AR_INVOICE | C34: 107 | D34: Godfrey_Phillips_India_Limited_HO | E34: GPIL_HO_New_Delhi(Services) | F34: GPI-HOC260300022 | H34: HO New Friends Colony | I34: 07AABCG4768K1Z9 | J34: TRANSACTIONS | K34: Receivables | L34: INV_COMPLETE | O34: 46142 | P34: 11263000022 | Q34: 27210238 | R34: 46142 | S34: Customer | T34: 445065 | U34: Godfrey Phillips India Limited | V34: jammu | W34: GSTIN | X34: 01AABCG4768K1ZL | AA34: 1151268 | AB34: 1 | AC34: 1151268 | AD34: GST_India | AF34: 998599 | AG34: BUSINESS SUPPORT SERVICES CROSS CHARGED FOR THE PERIOD MAR-26 | AJ34: 0 | AK34: 0 | AL34: 1151268 | AM34: Normal | AN34: 18 | AO34: 0 | AP34: 0 | AQ34: 207228.24 | AR34: 0 | AS34: 0 | AT34: 0 | AU34: 0 | AV34: 0 | AY34: 0 | AZ34: 1358496.2 | BA34: Y | BB34: N | BC34: 11.7100.111.512110.0000.000000.0000.000000.000000.00000000 | BD34: GPI-HOC260300022 | BE34: HO_INTER-STATE_OTH_REC_18% | BF34: INPUT_SERVICE | BI34: 354f0f0e296b7f1b3388a52b8a97e1998d0a082eabf1a913480fabcef6664bfa | BJ34: 46142.666 | BK34: B2B
... A41: Tax Invoice | B41: AR_INVOICE | C41: 107 | D41: Godfrey_Phillips_India_Limited_HO | E41: GPIL_HO_New_Delhi(Services) | F41: GPI-HOC260300023 | H41: HO New Friends Colony | I41: 07AABCG4768K1Z9 | J41: TRANSACTIONS | K41: Receivables | L41: INV_COMPLETE | O41: 46142 | P41: 11263000023 | Q41: 27210243 | R41: 46142 | S41: Customer | T41: 679080 | U41: GODFREY PHILLIPS INDIA LIMITED | V41: GODFREY-LADAKH | W41: GSTIN | X41: 38AABCG4768K1Z4 | AA41: 15454 | AB41: 1 | AC41: 15454 | AD41: GST_India | AF41: 998599 | AG41: BUSINESS SUPPORT SERVICES CROSS CHARGED FOR THE PERIOD MAR-26 | AJ41: 0 | AK41: 0 | AL41: 15454 | AM41: Normal | AN41: 18 | AO41: 0 | AP41: 0 | AQ41: 2781.72 | AR41: 0 | AS41: 0 | AT41: 0 | AU41: 0 | AV41: 0 | AY41: 0 | AZ41: 18235.72 | BA41: Y | BB41: N | BC41: 11.7100.111.512110.0000.000000.0000.000000.000000.00000000 | BD41: GPI-HOC260300023 | BE41: HO_INTER-STATE_OTH_REC_18% | BF41: INPUT_SERVICE | BI41: 753a435e541c04fac29f51fc211127f1e8448773e9b2971650aea831823b00e5 | BJ41: 46142.551 | BK41: B2B
A42: Manual Regime Entry | B42: MANUAL_ENTRY | C42: 107 | D42: Godfrey_Phillips_India_Limited_HO | E42: GPIL_HO_New_Delhi(Services) | F42: GPI-HOC260300070 | H42: HO New Friends Colony | I42: 07AABCG4768K1Z9 | J42: MANUAL_ENTRY | K42: Asia/Pacific Localizations | L42: MANUAL_ENTRY_CREATE | M42: Form Entry | N42: LIABILITY | O42: 46142 | P42: 108636040 | Q42: 108636040 | R42: 46142 | S42: CUSTOMER | T42: 2894 | U42: Godfrey Phillips India Limited, Ho | V42: HOC_ISD | X42: 07AABCG4768K3Z7 | AA42: 0 | AB42: 0 | AC42: 19283523 | AD42: GST_India | AE42: Services_ISD | AF42: 998346 | AG42: Services_ISD | AJ42: 0 | AK42: 0 | AL42: 19283523 | AM42: Normal | AN42: 18 | AO42: 1735517.1 | AP42: 1735517.1 | AQ42: 0 | AR42: 0 | AS42: 0 | AT42: 0 | AU42: 0 | AV42: 0 | AY42: 0 | AZ42: 22754557 | BA42: Y | BB42: N | BC42: 11.7100.111.512120.0000.000000.0000.000000.000000.00000000 | BI42: 8a08358c4e559433d403614a5c015a88e36c840b1de36ce67db84028b2f70e7e | BJ42: 46142.899 | BK42: B2B
A43: Tax Invoice | B43: AR_INVOICE | C43: 107 | D43: Godfrey_Phillips_India_Limited_HO | E43: GPIL_HO_New_Delhi(Services) | F43: GPI-HOC260300007 | H43: HO New Friends Colony | I43: 07AABCG4768K1Z9 | J43: TRANSACTIONS | K43: Receivables | L43: INV_COMPLETE | O43: 46133 | P43: 11263000007 | Q43: 27199220 | R43: 46133 | S43: Customer | T43: 1242122 | U43: PHILIP MORRIS INDIA TRADING PRIVATE LIMITED (FORMERLY IPM INDIA WHOLESALE TRADING PVT. LTD.) | V43: 08EB_CIG_GURUG_0001 | W43: GSTIN | X43: 06AACCI0642K2ZQ | AA43: 209913 | AB43: 1 | AC43: 209913 | AD43: GST_India | AF43: 999792 | AG43: Being amount of cost of credit m/o feb-26 | AJ43: 0 | AK43: 0 | AL43: 209913 | AM43: Normal | AN43: 18 | AO43: 0 | AP43: 0 | AQ43: 37784.34 | AR43: 0 | AS43: 0 | AT43: 0 | AU43: 0 | AV43: 0 | AY43: 0 | AZ43: 247697.34 | BA43: Y | BB43: N | BC43: 11.7100.111.321912.2900.000000.0000.000000.000000.00000000 | BD43: GPI-HOC260300007 | BE43: HO_INTER-STATE_OTH_REC_18% | BF43: INPUT_SERVICE | BI43: 9397213257517241871f6c5dca7c4b2c5974c24da4e19df228f454630610056c | BJ43: 46133.801 | BK43: B2B
A44: Tax Invoice | B44: AR_INVOICE | C44: 107 | D44: Godfrey_Phillips_India_Limited_HO | E44: GPIL_HO_New_Delhi(Services) | F44: GPI-HOC260300010 | H44: HO New Friends Colony | I44: 07AABCG4768K1Z9 | J44: TRANSACTIONS | K44: Receivables | L44: INV_COMPLETE | O44: 46141 | P44: 11263000010 | Q44: 27208814 | R44: 46141 | S44: Customer | T44: 1242122 | U44: PHILIP MORRIS INDIA TRADING PRIVATE LIMITED (FORMERLY IPM INDIA WHOLESALE TRADING PVT. LTD.) | V44: 08EB_CIG_GURUG_0001 | W44: GSTIN | X44: 06AACCI0642K2ZQ | AA44: 13537544 | AB44: 1 | AC44: 13537544 | AD44: GST_India | AF44: 999792 | AG44: Being amount of reimbursement of cost of credit M/O April-26 | AJ44: 0 | AK44: 0 | AL44: 13537544 | AM44: Normal | AN44: 18 | AO44: 0 | AP44: 0 | AQ44: 2436757.9 | AR44: 0 | AS44: 0 | AT44: 0 | AU44: 0 | AV44: 0 | AY44: 0 | AZ44: 15974302 | BA44: Y | BB44: N | BC44: 11.7100.111.321912.2900.000000.0000.000000.000000.00000000 | BD44: GPI-HOC260300010 | BE44: HO_INTER-STATE_OTH_REC_18% | BF44: INPUT_SERVICE | BI44: f1f23a362dc5166de5a5c5399e4ec3f84f728480c1066368fe7558bfbc42582e | BJ44: 46147.51 | BK44: B2B
A45: Tax Invoice | B45: AR_INVOICE | C45: 107 | D45: Godfrey_Phillips_India_Limited_HO | E45: GPIL_HO_New_Delhi(Services) | F45: GPI-HOC260300026 | H45: HO New Friends Colony | I45: 07AABCG4768K1Z9 | J45: TRANSACTIONS | K45: Receivables | L45: INV_COMPLETE | O45: 46142 | P45: 11263000026 | Q45: 27210253 | R45: 46142 | S45: Customer | T45: 2886 | U45: Godfrey Phillips India Limited, Ahmedabad | V45: I111901 | W45: GSTIN | X45: 24AABCG4768K1ZD | AA45: 1933792 | AB45: 1 | AC45: 1933792 | AD45: GST_India | AF45: 998599 | AG45: BUSINESS SUPPORT SERVICES CROSS CHARGED FOR THE PERIOD MAR-26 | AJ45: 0 | AK45: 0 | AL45: 1933792 | AM45: Normal | AN45: 18 | AO45: 0 | AP45: 0 | AQ45: 348082.56 | AR45: 0 | AS45: 0 | AT45: 0 | AU45: 0 | AV45: 0 | AY45: 0 | AZ45: 2281874.6 | BA45: Y | BB45: N | BC45: 11.7100.111.512110.0000.000000.0000.000000.000000.00000000 | BD45: GPI-HOC260300026 | BE45: HO_INTER-STATE_OTH_REC_18% | BF45: INPUT_SERVICE | BI45: 9676d458cd4b6a7741a07c71e3761152179b1f6802ebe1f89f030f7f22947400 | BJ45: 46142.556 | BK45: B2B
A46: Tax Invoice | B46: AR_INVOICE | C46: 107 | D46: Godfrey_Phillips_India_Limited_HO | E46: GPIL_HO_New_Delhi(Services) | F46: GPI-HOC260300037 | H46: HO New Friends Colony | I46: 07AABCG4768K1Z9 | J46: TRANSACTIONS | K46: Receivables | L46: INV_COMPLETE | O46: 46142 | P46: 11263000037 | Q46: 27210293 | R46: 46142 | S46: Customer | T46: 436061 | U46: GODFREY PHILLIPS INDIA LIMITED | V46: GPI BANGLORE | W46: GSTIN | X46: 29AABCG4768K2Z2 | AA46: 601705 | AB46: 1 | AC46: 601705 | AD46: GST_India | AF46: 998599 | AG46: BUSINESS SUPPORT SERVICES CROSS CHARGED FOR THE PERIOD MAR-26 | AJ46: 0 | AK46: 0 | AL46: 601705 | AM46: Normal | AN46: 18 | AO46: 0 | AP46: 0 | AQ46: 108306.9 | AR46: 0 | AS46: 0 | AT46: 0 | AU46: 0 | AV46: 0 | AY46: 0 | AZ46: 710011.9 | BA46: Y | BB46: N | BC46: 11.7100.111.512110.0000.000000.0000.000000.000000.00000000 | BD46: GPI-HOC260300037 | BE46: HO_INTER-STATE_OTH_REC_18% | BF46: INPUT_SERVICE | BI46: 0c4a8c9290d108b1b25069c56bb6cdb6c971115061bb4c9a0dd797e8b4c84aed | BJ46: 46142.595 | BK46: B2B

Sheet Pivat
K1: GSTIN & INV | L1: PR | M1: 2B | N1: DIFF
K2: 06AACCL4494J1Z8LNC/25-26/5110 | L2: 10296.59 | M2: 10122.11 | N2: 174
A3: Row Labels | B3: Sum of IGST | C3: Sum of SGST | D3: Sum of CGST | E3: Sum of CESS1 | F3: Total | H3: YEAR | I3: Amount | K3: 27AACCN6194P1ZP272612BP05AFT995 | L3: 328.4 | M3: 289 | N3: 39
A4: RCM-Not Matched | B4: 20600.1 | C4: 165097.08 | D4: 165097.08 | E4: 0 | F4: =SUM(B4:E4) -> 350794.26 | H4: FY 2025-26 | I4: 531023.64 | K4: 07AACCN6194P2ZQ072612BP04ACB413 | L4: 412.76 | M4: 375 | N4: 38
A5: RCM Non Rec | B5: 12500.1 | C5: 18000 | D5: 18000 | E5: 0 | F5: =SUM(B5:E5) -> 48500.1 | H5: FY 2026-27 | I5: 1956379.4 | K5: 07AAACB2894G1ZPMF2707I000063444 | L5: 7790.66 | M5: 8534.42 | N5: -744
A6: RCM Rec | B6: 8100 | C6: 147097.08 | D6: 147097.08 | E6: 0 | F6: =SUM(B6:E6) -> 302294.16 | I6: =SUM(I4:I5) -> 2487403
A7: Fwd - Matched | B7: 165504.08 | C7: 1160702.4 | D7: 1160702.4 | E7: 0 | F7: =SUM(B7:E7) -> 2486908.8
A8: Fwd Rec | B8: 63923.6 | C8: 1044627.8 | D8: 1044627.8 | E8: 0 | F8: =SUM(B8:E8) -> 2153179.1
A9: Fwd Non Rec | B9: 101580.48 | C9: 116074.59 | D9: 116074.59 | E9: 0 | F9: =SUM(B9:E9) -> 333729.66
A10: Grand Total | B10: 186104.18 | C10: 1325799.4 | D10: 1325799.4 | E10: 0 | F10: =SUM(F4:F9) -> 5675406.1
K12: Total - Difference | L12: =SUM(L2:L10) -> 18828.41 | M12: =SUM(M2:M10) -> 19320.53 | N12: =SUM(N2:N10) -> -493
E17: As per Books | F17: =F7 -> 2486908.8
E18: As per 2B | F18: =I6 -> 2487403
E19: Diffrence | F19: =F17-F18 -> -494.21 | G19: Refer O12

Sheet Inward
AI1: =SUBTOTAL(9,AI3:AI312) -> 15828442 | AL1: =SUBTOTAL(9,AL3:AL312) -> 1325799.4 | AM1: =SUBTOTAL(9,AM3:AM312) -> 1325799.4 | AN1: =SUBTOTAL(9,AN3:AN312) -> 186104.18 | AP1: =SUBTOTAL(9,AP3:AP312) -> 0 | AR1: =SUBTOTAL(9,AR3:AR312) -> 0 | AT1: =SUBTOTAL(9,AT3:AT312) -> 0 | AX1: =SUBTOTAL(9,AX3:AX312) -> 19025684 | BL1: =SUBTOTAL(9,BL3:BL312) -> 2837703.1
A2: Document Type | B2: Trx Category | C2: Org Id | D2: Rec OU | E2: IO Name | F2: GST Inv No | G2: IO Location | H2: FP REGN | I2: ENTITY CODE | J2: EVENT TYPE CODE | K2: SOURCE | L2: TRX TYPE | M2: ACCOUNTING DATE | N2: TRX NUMBER | O2: TRX ID | P2: TRX DATE | Q2: PARTY TYPE | R2: PARTY NUMBER | S2: PARTY NAME | T2: PARTY SITE NAME | U2: TP REGNNO | V2: TRX UOM | W2: MRP | X2: UNIT PRICE | Y2: TRX QTY | Z2: LINE AMT | AA2: REGIME | AB2: SUPPLIER INVOICE NUM | AC2: SUPPLIER INVOICE DATE | AD2: ITEM CODE | AE2: HSN/SACCODE | AF2: ITEM DES | AG2: NCCD | AH2: BED/CVD | AI2: GST TAXABLE AMT | AJ2: TAX TYPE | AK2: GST TAX RATE | AL2: SGST | AM2: CGST | AN2: IGST | AO2: IGST IMPORT | AP2: UTGST | AQ2: CESS1 RATE | AR2: CESS1 | AS2: CESS2 RATE | AT2: CESS2 | AU2: TCS RATE/ADHOC | AV2: TCS AMOUNT | AW2: OTHER TAX | AX2: TOTAL INVOICE AMOUNT | AY2: TRX REC | AZ2: TRX SELF | BA2: EXPENSE | BB2: VOUCHARNO | BC2: TAX CATEGORY | BD2: ITC CATEGORY | BE2: Custom BOE No | BF2: Custom BOE Date | BG2: Port Code | BH2: IRN Status | BI2: State Code | BJ2: State Name | BK2: GSTIN & INV | BL2: Total Tax | BM2: V-Lookuop | BN2: Diff | BO2: Remark | BP2: TRX ID | BQ2: ITC Type | BR2: 2B Year
A3: Payable Invoice | B3: AP_INVOICE | C3: 107 | D3: Godfrey_Phillips_India_Limited_HO | E3: GPIL_HO_New_Delhi(Services) | G3: HO New Friends Colony | H3: 07AABCG4768K1Z9 | I3: AP_INVOICES | J3: STANDARD CREATED | K3: Manual Invoice Entry | L3: STANDARD | M3: 46127 | N3: DFSI2600000412 | O3: 9158398 | P3: 46090 | Q3: Supplier | R3: 35671 | S3: DEUTSCHE CARS PRIVATE LIMITED | T3: Faridabad-OFF | U3: 06AAGCD4246E1ZX | V3: NOS | X3: 275 | Y3: 44 | Z3: 12100 | AA3: GST_India | AB3: DFSI2600000412 | AC3: 46121 | AD3: BUDMINTIND | AE3: 996200 | AF3: INTERIOR BEAUTIFICATION AND ENRICHMENT | AI3: 12100 | AJ3: Normal | AK3: 18 | AL3: 0 | AM3: 0 | AN3: 2178 | AO3: 0 | AP3: 0 | AQ3: 0 | AR3: 0 | AS3: 0 | AT3: 0 | AW3: 0 | AX3: 14278 | AY3: N | AZ3: N | BA3: 11.7100.111.414301.1011.111636.0007.000000.000000.00000000 | BB3: 1126100105 | BC3: HO_INTER-STATE_OTH_NON_REC_18% | BD3: INPUT_TDS_194C | BF3: Fwd Non Rec | BG3: Fwd - Matched | BH3: Yes | BI3: 07 | BJ3: Delhi | BK3: 06AAGCD4246E1ZXDFSI2600000412 | BL3: 2178 | BM3: 38182.88 | BN3: -36005 | BO3: Matched | BP3: 9158398 | BQ3: Fwd Non Rec | BR3: FY 2026-27 | BS3: 37
A4: Payable Invoice | B4: AP_INVOICE | C4: 107 | D4: Godfrey_Phillips_India_Limited_HO | E4: GPIL_HO_New_Delhi(Services) | G4: HO New Friends Colony | H4: 07AABCG4768K1Z9 | I4: AP_INVOICES | J4: STANDARD CREATED | K4: Manual Invoice Entry | L4: STANDARD | M4: 46127 | N4: DFSI2600000412 | O4: 9158398 | P4: 46090 | Q4: Supplier | R4: 35671 | S4: DEUTSCHE CARS PRIVATE LIMITED | T4: Faridabad-OFF | U4: 06AAGCD4246E1ZX | V4: NOS | X4: 1031.36 | Y4: 8 | Z4: 8250.88 | AA4: GST_India | AB4: DFSI2600000412 | AC4: 46121 | AD4: BUDMINTIND | AE4: 34029099 | AF4: OZONIZER | AI4: 8250.88 | AJ4: Normal | AK4: 18 | AL4: 0 | AM4: 0 | AN4: 1485.16 | AO4: 0 | AP4: 0 | AQ4: 0 | AR4: 0 | AS4: 0 | AT4: 0 | AW4: 0 | AX4: 9736.04 | AY4: N | AZ4: N | BA4: 11.7100.111.414301.1011.111636.0007.000000.000000.00000000 | BB4: 1126100105 | BC4: HO_INTER-STATE_OTH_NON_REC_18% | BD4: INPUT_TDS_194C | BF4: Fwd Non Rec | BG4: Fwd - Matched | BH4: Yes | BI4: 07 | BJ4: Delhi | BK4: 06AAGCD4246E1ZXDFSI2600000412 | BL4: 1485.16 | BM4: 38182.88 | BN4: -36698 | BO4: Matched | BP4: 9158398 | BQ4: Fwd Non Rec | BR4: FY 2026-27 | BS4: 37
A5: Payable Invoice | B5: AP_INVOICE | C5: 107 | D5: Godfrey_Phillips_India_Limited_HO | E5: GPIL_HO_New_Delhi(Services) | G5: HO New Friends Colony | H5: 07AABCG4768K1Z9 | I5: AP_INVOICES | J5: STANDARD CREATED | K5: Manual Invoice Entry | L5: STANDARD | M5: 46140 | N5: DFSI2600000751 | O5: 9174963 | P5: 46129 | Q5: Supplier | R5: 35671 | S5: DEUTSCHE CARS PRIVATE LIMITED | T5: Faridabad-OFF | U5: 06AAGCD4246E1ZX | V5: NOS | X5: 275 | Y5: 64 | Z5: 17600 | AA5: GST_India | AB5: DFSI2600000751 | AC5: 46129 | AD5: BUDMINTIND | AE5: 998729 | AF5: MECH CARE | AI5: 17600 | AJ5: Normal | AK5: 18 | AL5: 0 | AM5: 0 | AN5: 3168 | AO5: 0 | AP5: 0 | AQ5: 0 | AR5: 0 | AS5: 0 | AT5: 0 | AW5: 0 | AX5: 20768 | AY5: N | AZ5: N | BA5: 11.7100.111.414301.1000.100007.0007.000000.000000.00000000 | BB5: 1126100446 | BC5: HO_INTER-STATE_OTH_NON_REC_18% | BD5: INPUT_TDS_194C | BF5: Fwd Non Rec | BG5: Fwd - Matched | BH5: Yes | BI5: 07 | BJ5: Delhi | BK5: 06AAGCD4246E1ZXDFSI2600000751 | BL5: 3168 | BM5: 36494.74 | BN5: -33327 | BO5: Matched | BP5: 9174963 | BQ5: Fwd Non Rec | BR5: FY 2026-27 | BS5: 36
A6: Payable Invoice | B6: AP_INVOICE | C6: 107 | D6: Godfrey_Phillips_India_Limited_HO | E6: GPIL_HO_New_Delhi(Services) | G6: HO New Friends Colony | H6: 07AABCG4768K1Z9 | I6: AP_INVOICES | J6: STANDARD CREATED | K6: Manual Invoice Entry | L6: STANDARD | M6: 46127 | N6: MF2707I00063444 | O6: 9156749 | P6: 46115 | Q6: Supplier | R6: 6262 | S6: BHARTI AIRTEL LIMITED | T6: HO | U6: 07AAACB2894G1ZP | V6: NOS | X6: 1 | Y6: 3199 | Z6: 3199 | AA6: GST_India | AB6: MF2707I000063444 | AC6: 46115 | AD6: MISCELLENS | AE6: 998413 | AF6: AIRTEL MOBILE BILLS FOR THE MONTH OF MAR 2026 | AI6: 3199 | AJ6: Normal | AK6: 18 | AL6: 287.91 | AM6: 287.91 | AN6: 0 | AO6: 0 | AP6: 0 | AQ6: 0 | AR6: 0 | AS6: 0 | AT6: 0 | AW6: 0 | AX6: 3774.82 | AY6: Y | AZ6: N | BA6: 11.7100.111.420803.1000.000000.0007.000000.000000.00000000 | BB6: 1126100078 | BC6: HO_INTRA-STATE_OTH_REC_18% | BD6: INPUT_SERVICE | BF6: Fwd Rec | BG6: Fwd - Matched | BH6: Yes | BI6: 07 | BJ6: Delhi | BK6: 07AAACB2894G1ZPMF2707I000063444 | BL6: 575.82 | BM6: 8534.42 | BN6: -7959 | BO6: Matched | BP6: 9156749 | BQ6: Fwd Rec | BR6: FY 2026-27 | BS6: 17
A7: Payable Invoice | B7: AP_INVOICE | C7: 107 | D7: Godfrey_Phillips_India_Limited_HO | E7: GPIL_HO_New_Delhi(Services) | H7: 07AABCG4768K1Z9 | I7: AP_INVOICES | J7: STANDARD VALIDATED TAX | K7: IA | L7: STANDARD | M7: 46126 | N7: DLS2627000000593 | O7: 9155613 | P7: 46114 | Q7: Supplier | R7: 2770 | S7: CANON INDIA PVT. LTD. | T7: OKHLA | U7: 07AAACC4175D1Z0 | V7: NOS | X7: 1 | Y7: 2.8 | Z7: 2.8 | AA7: GST_India | AB7: DLS2627000000593 | AC7: 46114 | AD7: MISCELLENS | AE7: 84439952 | AF7: Supply of Tonernnk Spares along with Support Services | AI7: 2.8 | AJ7: Normal | AK7: 18 | AL7: 0.25 | AM7: 0.25 | AN7: 0 | AO7: 0 | AP7: 0 | AQ7: 0 | AR7: 0 | AS7: 0 | AT7: 0 | AW7: 0 | AX7: 3.3 | AY7: Y | AZ7: N | BA7: 11.7100.111.234010.0000.000000.0007.000000.000000.00000000 | BB7: 1126100063 | BC7: HO_INTRA-STATE_OTH_REC_18% | BD7: INPUT_SERVICE | BF7: Fwd Rec | BG7: Fwd - Matched | BH7: Yes | BI7: 07 | BJ7: Delhi | BK7: 07AAACC4175D1Z0DLS2627000000593 | BL7: 0.5 | BM7: 5381.62 | BN7: -5381 | BO7: Matched | BP7: 9155613 | BQ7: Fwd Rec | BR7: FY 2026-27 | BS7: 4
A8: Payable Invoice | B8: AP_INVOICE | C8: 107 | D8: Godfrey_Phillips_India_Limited_HO | E8: GPIL_HO_New_Delhi(Services) | H8: 07AABCG4768K1Z9 | I8: AP_INVOICES | J8: STANDARD VALIDATED TAX | K8: IA | L8: STANDARD | M8: 46133 | N8: LKS01-2627-00147 | O8: 9164641 | P8: 46122 | Q8: Supplier | R8: 3539 | S8: LAKSHMI KUMARAN AND SRIDHARAN | T8: NEW DELHI | U8: 07AAAFL1585H1ZD | V8: NOS | X8: 40000 | Y8: 1 | Z8: 40000 | AA8: GST_India | AB8: LKS01-2627-00147 | AC8: 46122 | AE8: 998212 | AF8: Towards professional fee for legal advice on the applicability of BIS- and EPR-related compliances to imports of primary AA and AAA alkaline batteries. | AI8: 40000 | AJ8: Normal | AK8: 18 | AL8: 3600 | AM8: 3600 | AN8: 0 | AO8: 0 | AP8: 0 | AQ8: 0 | AR8: 0 | AS8: 0 | AT8: 0 | AW8: 0 | AX8: 47200 | AY8: Y | AZ8: Y | BA8: 11.7100.111.416001.1009.000000.0007.000000.000000.00000000 | BB8: 1126100302 | BC8: HO_REV_CHARGE_REC_18% | BD8: INPUT_SERVICE | BF8: RCM Rec | BG8: RCM-Not Matched | BH8: Yes | BI8: 07 | BJ8: Delhi | BK8: 07AAAFL1585H1ZDLKS01-2627-001470 | BL8: 7200 | BM8: #N/A | BN8: #N/A | BO8: RCM | BP8: 9164641 | BQ8: RCM Rec | BR8: FY 2026-27 | BS8: 1
A9: Payable Invoice | B9: AP_INVOICE | C9: 107 | D9: Godfrey_Phillips_India_Limited_HO | E9: GPIL_HO_New_Delhi(Services) | H9: 07AABCG4768K1Z9 | I9: AP_INVOICES | J9: STANDARD VALIDATED TAX | K9: IA | L9: STANDARD | M9: 46136 | N9: SME/26-27/98 | O9: 9168298 | P9: 46127 | Q9: Supplier | R9: 3484 | S9: SREE MAHAVIR ENTERPRISES | T9: NEW DELHI | U9: 07AAOFS6787Q1ZV | V9: NOS | X9: 5000 | Y9: 1 | Z9: 5000 | AA9: GST_India | AB9: SME/26-27/98 | AC9: 46127 | AD9: BUDMINTIND | AE9: 998716 | AF9: Annual Maintainance Contract No. NEC SL2100 (38) EPABX System 2 Nos. Key Phone Period 01.04.2026 to 31.03.2027 | AI9: 5000 | AJ9: Normal | AK9: 18 | AL9: 450 | AM9: 450 | AN9: 0 | AO9: 0 | AP9: 0 | AQ9: 0 | AR9: 0 | AS9: 0 | AT9: 0 | AW9: 0 | AX9: 5900 | AY9: Y | AZ9: N | BA9: 11.7100.111.414401.1010.000000.0007.000000.000000.00000000 | BB9: 1126100391 | BC9: HO_INTRA-STATE_OTH_REC_18% | BD9: INPUT_SERVICE | BF9: Fwd Rec | BG9: Fwd - Matched | BH9: Yes | BI9: 07 | BJ9: Delhi | BK9: 07AAOFS6787Q1ZVSME/26-27/98 | BL9: 900 | BM9: 900 | BN9: 0 | BO9: Matched | BP9: 9168298 | BQ9: Fwd Rec | BR9: FY 2026-27 | BS9: 1
A10: Payable Invoice | B10: AP_INVOICE | C10: 107 | D10: Godfrey_Phillips_India_Limited_HO | E10: GPIL_HO_New_Delhi(Services) | H10: 07AABCG4768K1Z9 | I10: AP_INVOICES | J10: STANDARD VALIDATED TAX | K10: Manual Invoice Entry | L10: STANDARD | M10: 46142 | N10: GLMS0000059723 | O10: 9178440 | P10: 46089 | Q10: Supplier | R10: 40270 | S10: TATA AIA LIFE INSURANCE COMPANY LIMITED | T10: Thane | U10: 27AABCT3784C1ZD | X10: 0 | Y10: 0 | Z10: 1964.52 | AA10: GST_India | AB10: GLMS000000059723 | AC10: 46089 | AE10: 9971 | AF10: GTIL Policy Deletion of Members for the m/o Feb 2026 | AI10: 1964.52 | AJ10: Normal | AK10: 18 | AL10: 0 | AM10: 0 | AN10: 353.61 | AO10: 0 | AP10: 0 | AQ10: 0 | AR10: 0 | AS10: 0 | AT10: 0 | AW10: 0 | AX10: 2318.13 | AY10: N | AZ10: N | BA10: 11.7100.111.234010.0000.000000.0007.000000.000000.00000000 | BB10: 1126100570 | BC10: HO_INTER-STATE_OTH_NON_REC_18% | BD10: INPUT_SERVICE | BF10: Fwd Non Rec | BG10: Fwd - Matched | BH10: No | BI10: 07 | BJ10: Delhi | BK10: 27AABCT3784C1ZDGLMS000000059723 | BL10: 353.61 | BM10: 353.61 | BN10: 0 | BO10: Matched | BP10: 9178440 | BQ10: Fwd Non Rec | BR10: FY 2025-26 | BS10: 1
A11: Payable Invoice | B11: AP_INVOICE | C11: 107 | D11: Godfrey_Phillips_India_Limited_HO | E11: GPIL_HO_New_Delhi(Services) | H11: 07AABCG4768K1Z9 | I11: AP_INVOICES | J11: STANDARD VALIDATED TAX | K11: IA | L11: STANDARD | M11: 46126 | N11: DLS2627000000653 | O11: 9155610 | P11: 46114 | Q11: Supplier | R11: 2770 | S11: CANON INDIA PVT. LTD. | T11: OKHLA | U11: 07AAACC4175D1Z0 | V11: NOS | X11: 1 | Y11: 275 | Z11: 275 | AA11: GST_India | AB11: DLS2627000000653 | AC11: 46114 | AD11: MISCELLENS | AE11: 84439952 | AF11: Supply of Toner ink and Spares along with Support Services | AI11: 275 | AJ11: Normal | AK11: 18 | AL11: 24.75 | AM11: 24.75 | AN11: 0 | AO11: 0 | AP11: 0 | AQ11: 0 | AR11: 0 | AS11: 0 | AT11: 0 | AW11: 0 | AX11: 324.5 | AY11: Y | AZ11: N | BA11: 11.7100.111.234010.0000.000000.0007.000000.000000.00000000 | BB11: 1126100060 | BC11: HO_INTRA-STATE_OTH_REC_18% | BD11: INPUT_SERVICE | BF11: Fwd Rec | BG11: Fwd - Matched | BH11: Yes | BI11: 07 | BJ11: Delhi | BK11: 07AAACC4175D1Z0DLS2627000000653 | BL11: 49.5 | BM11: 489.18 | BN11: -440 | BO11: Matched | BP11: 9155610 | BQ11: Fwd Rec | BR11: FY 2026-27 | BS11: 4
A12: Payable Invoice | B12: AP_INVOICE | C12: 107 | D12: Godfrey_Phillips_India_Limited_HO | E12: GPIL_HO_New_Delhi(Services) | G12: HO New Friends Colony | H12: 07AABCG4768K1Z9 | I12: AP_INVOICES | J12: STANDARD CREATED | K12: Manual Invoice Entry | L12: STANDARD | M12: 46140 | N12: DFSI2600000751 | O12: 9174963 | P12: 46129 | Q12: Supplier | R12: 35671 | S12: DEUTSCHE CARS PRIVATE LIMITED | T12: Faridabad-OFF | U12: 06AAGCD4246E1ZX | V12: NOS | X12: 275 | Y12: 24 | Z12: 6600 | AA12: GST_India | AB12: DFSI2600000751 | AC12: 46129 | AD12: BUDMINTIND | AE12: 996200 | AF12: SURFACE REFINEMENT | AI12: 6600 | AJ12: Normal | AK12: 18 | AL12: 0 | AM12: 0 | AN12: 1188 | AO12: 0 | AP12: 0 | AQ12: 0 | AR12: 0 | AS12: 0 | AT12: 0 | AW12: 0 | AX12: 7788 | AY12: N | AZ12: N | BA12: 11.7100.111.414301.1000.100007.0007.000000.000000.00000000 | BB12: 1126100446 | BC12: HO_INTER-STATE_OTH_NON_REC_18% | BD12: INPUT_TDS_194C | BF12: Fwd Non Rec | BG12: Fwd - Matched | BH12: Yes | BI12: 07 | BJ12: Delhi | BK12: 06AAGCD4246E1ZXDFSI2600000751 | BL12: 1188 | BM12: 36494.74 | BN12: -35307 | BO12: Matched | BP12: 9174963 | BQ12: Fwd Non Rec | BR12: FY 2026-27 | BS12: 36
A13: Payable Invoice | B13: AP_INVOICE | C13: 107 | D13: Godfrey_Phillips_India_Limited_HO | E13: GPIL_HO_New_Delhi(Services) | G13: HO New Friends Colony | H13: 07AABCG4768K1Z9 | I13: AP_INVOICES | J13: STANDARD CREATED | K13: Manual Invoice Entry | L13: STANDARD | M13: 46127 | N13: MF2707I00063444 | O13: 9156749 | P13: 46115 | Q13: Supplier | R13: 6262 | S13: BHARTI AIRTEL LIMITED | T13: HO | U13: 07AAACB2894G1ZP | V13: NOS | X13: 1 | Y13: 1297 | Z13: 1297 | AA13: GST_India | AB13: MF2707I000063444 | AC13: 46115 | AD13: MISCELLENS | AE13: 998413 | AF13: AIRTEL MOBILE BILLS FOR THE MONTH OF MAR 2026 | AI13: 1297 | AJ13: Normal | AK13: 18 | AL13: 116.73 | AM13: 116.73 | AN13: 0 | AO13: 0 | AP13: 0 | AQ13: 0 | AR13: 0 | AS13: 0 | AT13: 0 | AW13: 0 | AX13: 1530.46 | AY13: Y | AZ13: N | BA13: 11.7100.111.420803.1000.000000.0007.000000.000000.00000000 | BB13: 1126100078 | BC13: HO_INTRA-STATE_OTH_REC_18% | BD13: INPUT_SERVICE | BF13: Fwd Rec | BG13: Fwd - Matched | BH13: Yes | BI13: 07 | BJ13: Delhi | BK13: 07AAACB2894G1ZPMF2707I000063444 | BL13: 233.46 | BM13: 8534.42 | BN13: -8301 | BO13: Matched | BP13: 9156749 | BQ13: Fwd Rec | BR13: FY 2026-27 | BS13: 17
A14: Payable Invoice | B14: AP_INVOICE | C14: 107 | D14: Godfrey_Phillips_India_Limited_HO | E14: GPIL_HO_New_Delhi(Services) | G14: HO New Friends Colony | H14: 07AABCG4768K1Z9 | I14: AP_INVOICES | J14: STANDARD CREATED | K14: Manual Invoice Entry | L14: STANDARD | M14: 46127 | N14: MF2707I00063444 | O14: 9156749 | P14: 46115 | Q14: Supplier | R14: 6262 | S14: BHARTI AIRTEL LIMITED | T14: HO | U14: 07AAACB2894G1ZP | V14: NOS | X14: 1 | Y14: 399 | Z14: 399 | AA14: GST_India | AB14: MF2707I000063444 | AC14: 46115 | AD14: MISCELLENS | AE14: 998413 | AF14: AIRTEL MOBILE BILLS FOR THE MONTH OF MAR 2026 | AI14: 399 | AJ14: Normal | AK14: 18 | AL14: 35.91 | AM14: 35.91 | AN14: 0 | AO14: 0 | AP14: 0 | AQ14: 0 | AR14: 0 | AS14: 0 | AT14: 0 | AW14: 0 | AX14: 470.82 | AY14: Y | AZ14: N | BA14: 11.7100.111.420803.1000.000000.0007.000000.000000.00000000 | BB14: 1126100078 | BC14: HO_INTRA-STATE_OTH_REC_18% | BD14: INPUT_SERVICE | BF14: Fwd Rec | BG14: Fwd - Matched | BH14: Yes | BI14: 07 | BJ14: Delhi | BK14: 07AAACB2894G1ZPMF2707I000063444 | BL14: 71.82 | BM14: 8534.42 | BN14: -8463 | BO14: Matched | BP14: 9156749 | BQ14: Fwd Rec | BR14: FY 2026-27 | BS14: 17
A15: Payable Invoice | B15: AP_INVOICE | C15: 107 | D15: Godfrey_Phillips_India_Limited_HO | E15: GPIL_HO_New_Delhi(Services) | G15: HO New Friends Colony | H15: 07AABCG4768K1Z9 | I15: AP_INVOICES | J15: STANDARD CREATED | K15: Manual Invoice Entry | L15: STANDARD | M15: 46140 | N15: TXA26-00607 | O15: 9175014 | P15: 46129 | Q15: Supplier | R15: 15979 | S15: SPIRITED AUTO CARS (I) LTD. | T15: NEW DELHI | U15: 07AANCS0651B1ZM | V15: NOS | X15: 100 | Y15: 1 | Z15: 100 | AA15: GST_India | AB15: TXA26-00607 | AC15: 46129 | AD15: BUDMINTIND | AE15: 84212300 | AF15: FILTER ASSY OIL | AI15: 100 | AJ15: Normal | AK15: 18 | AL15: 9 | AM15: 9 | AN15: 0 | AO15: 0 | AP15: 0 | AQ15: 0 | AR15: 0 | AS15: 0 | AT15: 0 | AW15: 0 | AX15: 118 | AY15: N | AZ15: N | BA15: 11.7100.111.414301.1009.110908.0007.000000.000000.00000000 | BB15: 1126100447 | BC15: HO_INTRA-STATE_OTH_NON_REC_18% | BD15: INPUT_TDS_194C | BF15: Fwd Non Rec | BG15: Fwd - Matched | BH15: Yes | BI15: 07 | BJ15: Delhi | BK15: 07AANCS0651B1ZMTXA26-00607 | BL15: 18 | BM15: 2435.38 | BN15: -2417 | BO15: Matched | BP15: 9175014 | BQ15: Fwd Non Rec | BR15: FY 2026-27 | BS15: 18
A16: Payable Invoice | B16: AP_INVOICE | C16: 107 | D16: Godfrey_Phillips_India_Limited_HO | E16: GPIL_HO_New_Delhi(Services) | H16: 07AABCG4768K1Z9 | I16: AP_INVOICES | J16: STANDARD VALIDATED TAX | K16: IA | L16: STANDARD | M16: 46125 | N16: SQUA/27/T000001 | O16: 9151136 | P16: 46113 | Q16: Supplier | R16: 25119 | S16: SHANVI ESTATE MANAGEMENT SERVICES PRIVATE LIMITED | T16: NEW DELHI | U16: 07AAJCS4628Q1ZM | V16: NOS | X16: 792000 | Y16: 1 | Z16: 792000 | AA16: GST_India | AB16: SQUA/27/T000001 | AC16: 46113 | AD16: BUDMINTIND | AE16: 997221 | AF16: MAINTENANCE CHARGES | AI16: 792000 | AJ16: Normal | AK16: 18 | AL16: 71280 | AM16: 71280 | AN16: 0 | AO16: 0 | AP16: 0 | AQ16: 0 | AR16: 0 | AS16: 0 | AT16: 0 | AW16: 0 | AX16: 934560 | AY16: Y | AZ16: N | BA16: 11.7100.111.413703.1010.000000.0007.000000.000000.00000000 | BB16: 1126100026 | BC16: HO_INTRA-STATE_OTH_REC_18% | BD16: INPUT_SERVICE | BF16: Fwd Rec | BG16: Fwd - Matched | BH16: Yes | BI16: 07 | BJ16: Delhi | BK16: 07AAJCS4628Q1ZMSQUA/27/T000001 | BL16: 142560 | BM16: 142560 | BN16: 0 | BO16: Matched | BP16: 9151136 | BQ16: Fwd Rec | BR16: FY 2026-27 | BS16: 1
A17: Payable Invoice | B17: AP_INVOICE | C17: 107 | D17: Godfrey_Phillips_India_Limited_HO | E17: GPIL_HO_New_Delhi(Services) | G17: HO New Friends Colony | H17: 07AABCG4768K1Z9 | I17: AP_INVOICES | J17: STANDARD CREATED | K17: Manual Invoice Entry | L17: STANDARD | M17: 46127 | N17: DFSI2600000412 | O17: 9158398 | P17: 46090 | Q17: Supplier | R17: 35671 | S17: DEUTSCHE CARS PRIVATE LIMITED | T17: Faridabad-OFF | U17: 06AAGCD4246E1ZX | V17: NOS | X17: 275 | Y17: 38 | Z17: 10450 | AA17: GST_India | AB17: DFSI2600000412 | AC17: 46121 | AD17: BUDMINTIND | AE17: 998700 | AF17: COMBO 2 | AI17: 10450 | AJ17: Normal | AK17: 18 | AL17: 0 | AM17: 0 | AN17: 1881 | AO17: 0 | AP17: 0 | AQ17: 0 | AR17: 0 | AS17: 0 | AT17: 0 | AW17: 0 | AX17: 12331 | AY17: N | AZ17: N | BA17: 11.7100.111.414301.1011.111636.0007.000000.000000.00000000 | BB17: 1126100105 | BC17: HO_INTER-STATE_OTH_NON_REC_18% | BD17: INPUT_TDS_194C | BF17: Fwd Non Rec | BG17: Fwd - Matched | BH17: Yes | BI17: 07 | BJ17: Delhi | BK17: 06AAGCD4246E1ZXDFSI2600000412 | BL17: 1881 | BM17: 38182.88 | BN17: -36302 | BO17: Matched | BP17: 9158398 | BQ17: Fwd Non Rec | BR17: FY 2026-27 | BS17: 37
A18: Payable Invoice | B18: AP_INVOICE | C18: 107 | D18: Godfrey_Phillips_India_Limited_HO | E18: GPIL_HO_New_Delhi(Services) | H18: 07AABCG4768K1Z9 | I18: AP_INVOICES | J18: STANDARD VALIDATED TAX | K18: IA | L18: STANDARD | M18: 46126 | N18: DLS2627000000590 | O18: 9155609 | P18: 46114 | Q18: Supplier | R18: 2770 | S18: CANON INDIA PVT. LTD. | T18: OKHLA | U18: 07AAACC4175D1Z0 | V18: NOS | X18: 1 | Y18: 1.6 | Z18: 1.6 | AA18: GST_India | AB18: DLS2627000000590 | AC18: 46114 | AD18: MISCELLENS | AE18: 84439952 | AF18: Supply of Tonerink and Spares along with Support Services | AI18: 1.6 | AJ18: Normal | AK18: 18 | AL18: 0.14 | AM18: 0.14 | AN18: 0 | AO18: 0 | AP18: 0 | AQ18: 0 | AR18: 0 | AS18: 0 | AT18: 0 | AW18: 0 | AX18: 1.88 | AY18: Y | AZ18: N | BA18: 11.7100.111.234010.0000.000000.0007.000000.000000.00000000 | BB18: 1126100059 | BC18: HO_INTRA-STATE_OTH_REC_18% | BD18: INPUT_SERVICE | BF18: Fwd Rec | BG18: Fwd - Matched | BH18: Yes | BI18: 07 | BJ18: Delhi | BK18: 07AAACC4175D1Z0DLS2627000000590 | BL18: 0.28 | BM18: 1420.5 | BN18: -1420 | BO18: Matched | BP18: 9155609 | BQ18: Fwd Rec | BR18: FY 2026-27 | BS18: 4
A19: Payable Invoice | B19: AP_INVOICE | C19: 107 | D19: Godfrey_Phillips_India_Limited_HO | E19: GPIL_HO_New_Delhi(Services) | H19: 07AABCG4768K1Z9 | I19: AP_INVOICES | J19: STANDARD VALIDATED TAX | K19: IA | L19: STANDARD | M19: 46126 | N19: DLS2627000000593 | O19: 9155613 | P19: 46114 | Q19: Supplier | R19: 2770 | S19: CANON INDIA PVT. LTD. | T19: OKHLA | U19: 07AAACC4175D1Z0 | V19: NOS | X19: 1 | Y19: 10 | Z19: 10 | AA19: GST_India | AB19: DLS2627000000593 | AC19: 46114 | AD19: MISCELLENS | AE19: 84439952 | AF19: Supply of TonerInk Spares along Support Services | AI19: 10 | AJ19: Normal | AK19: 18 | AL19: 0.9 | AM19: 0.9 | AN19: 0 | AO19: 0 | AP19: 0 | AQ19: 0 | AR19: 0 | AS19: 0 | AT19: 0 | AW19: 0 | AX19: 11.8 | AY19: Y | AZ19: N | BA19: 11.7100.111.234010.0000.000000.0007.000000.000000.00000000 | BB19: 1126100063 | BC19: HO_INTRA-STATE_OTH_REC_18% | BD19: INPUT_SERVICE | BF19: Fwd Rec | BG19: Fwd - Matched | BH19: Yes | BI19: 07 | BJ19: Delhi | BK19: 07AAACC4175D1Z0DLS2627000000593 | BL19: 1.8 | BM19: 5381.62 | BN19: -5380 | BO19: Matched | BP19: 9155613 | BQ19: Fwd Rec | BR19: FY 2026-27 | BS19: 4
A20: Payable Invoice | B20: AP_INVOICE | C20: 107 | D20: Godfrey_Phillips_India_Limited_HO | E20: GPIL_HO_New_Delhi(Services) | H20: 07AABCG4768K1Z9 | I20: AP_INVOICES | J20: STANDARD VALIDATED TAX | K20: IA | L20: STANDARD | M20: 46126 | N20: DLS2627000000653 | O20: 9155610 | P20: 46114 | Q20: Supplier | R20: 2770 | S20: CANON INDIA PVT. LTD. | T20: OKHLA | U20: 07AAACC4175D1Z0 | V20: NOS | X20: 1 | Y20: 6 | Z20: 6 | AA20: GST_India | AB20: DLS2627000000653 | AC20: 46114 | AD20: MISCELLENS | AE20: 84439952 | AF20: Supply of TonerInk and Spares along with Support Services | AI20: 6 | AJ20: Normal | AK20: 18 | AL20: 0.54 | AM20: 0.54 | AN20: 0 | AO20: 0 | AP20: 0 | AQ20: 0 | AR20: 0 | AS20: 0 | AT20: 0 | AW20: 0 | AX20: 7.08 | AY20: Y | AZ20: N | BA20: 11.7100.111.234010.0000.000000.0007.000000.000000.00000000 | BB20: 1126100060 | BC20: HO_INTRA-STATE_OTH_REC_18% | BD20: INPUT_SERVICE | BF20: Fwd Rec | BG20: Fwd - Matched | BH20: Yes | BI20: 07 | BJ20: Delhi | BK20: 07AAACC4175D1Z0DLS2627000000653 | BL20: 1.08 | BM20: 489.18 | BN20: -488 | BO20: Matched | BP20: 9155610 | BQ20: Fwd Rec | BR20: FY 2026-27 | BS20: 4
A21: Payable Invoice | B21: AP_INVOICE | C21: 107 | D21: Godfrey_Phillips_India_Limited_HO | E21: GPIL_HO_New_Delhi(Services) | H21: 07AABCG4768K1Z9 | I21: AP_INVOICES | J21: STANDARD VALIDATED TAX | K21: IA | L21: STANDARD | M21: 46126 | N21: DLS2627000000660 | O21: 9155615 | P21: 46114 | Q21: Supplier | R21: 2770 | S21: CANON INDIA PVT. LTD. | T21: OKHLA | U21: 07AAACC4175D1Z0 | V21: NOS | X21: 1 | Y21: 4063.95 | Z21: 4063.95 | AA21: GST_India | AB21: DLS2627000000660 | AC21: 46114 | AD21: MISCELLENS | AE21: 84439952 | AF21: Supply of TonerInk Spares along Support Services | AI21: 4063.95 | AJ21: Normal | AK21: 18 | AL21: 365.76 | AM21: 365.76 | AN21: 0 | AO21: 0 | AP21: 0 | AQ21: 0 | AR21: 0 | AS21: 0 | AT21: 0 | AW21: 0 | AX21: 4795.47 | AY21: Y | AZ21: N | BA21: 11.7100.111.234010.0000.000000.0007.000000.000000.00000000 | BB21: 1126100065 | BC21: HO_INTRA-STATE_OTH_REC_18% | BD21: INPUT_SERVICE | BF21: Fwd Rec | BG21: Fwd - Matched | BH21: Yes | BI21: 07 | BJ21: Delhi | BK21: 07AAACC4175D1Z0DLS2627000000660 | BL21: 731.52 | BM21: 1123.84 | BN21: -392 | BO21: Matched | BP21: 9155615 | BQ21: Fwd Rec | BR21: FY 2026-27 | BS21: 4
A22: Payable Invoice | B22: AP_INVOICE | C22: 107 | D22: Godfrey_Phillips_India_Limited_HO | E22: GPIL_HO_New_Delhi(Services) | H22: 07AABCG4768K1Z9 | I22: AP_INVOICES | J22: STANDARD VALIDATED TAX | K22: IA | L22: STANDARD | M22: 46127 | N22: HRF2627000000683 | O22: 9156867 | P22: 46113 | Q22: Supplier | R22: 2770 | S22: CANON INDIA PVT. LTD. | T22: GURGAON-1A | U22: 06AAACC4175D1Z2 | V22: NOS | X22: 1 | Y22: 3956 | Z22: 3956 | AA22: GST_India | AB22: HRF2627000000683 | AC22: 46113 | AD22: BUDMINTIND | AE22: 997314 | AF22: Rental Charges For iR-ADV | AI22: 3956 | AJ22: Normal | AK22: 18 | AL22: 0 | AM22: 0 | AN22: 712.08 | AO22: 0 | AP22: 0 | AQ22: 0 | AR22: 0 | AS22: 0 | AT22: 0 | AW22: 0 | AX22: 4668.08 | AY22: Y | AZ22: N | BA22: 11.7100.111.414703.1000.000000.0007.000000.000000.00000000 | BB22: 1126100096 | BC22: HO_INTER-STATE_OTH_REC_18% | BD22: INPUT_SERVICE | BF22: Fwd Rec | BG22: Fwd - Matched | BH22: Yes | BI22: 07 | BJ22: Delhi | BK22: 06AAACC4175D1Z2HRF2627000000683 | BL22: 712.08 | BM22: 712.08 | BN22: 0 | BO22: Matched | BP22: 9156867 | BQ22: Fwd Rec | BR22: FY 2026-27 | BS22: 1
A23: Payable Invoice | B23: AP_INVOICE | C23: 107 | D23: Godfrey_Phillips_India_Limited_HO | E23: GPIL_HO_New_Delhi(Services) | G23: HO New Friends Colony | H23: 07AABCG4768K1Z9 | I23: AP_INVOICES | J23: STANDARD CREATED | K23: Manual Invoice Entry | L23: STANDARD | M23: 46127 | N23: DFSI2600000412 | O23: 9158398 | P23: 46090 | Q23: Supplier | R23: 35671 | S23: DEUTSCHE CARS PRIVATE LIMITED | T23: Faridabad-OFF | U23: 06AAGCD4246E1ZX | V23: NOS | X23: 275 | Y23: 38 | Z23: 10450 | AA23: GST_India | AB23: DFSI2600000412 | AC23: 46121 | AD23: BUDMINTIND | AE23: 998700 | AF23: COMBO 1 | AI23: 10450 | AJ23: Normal | AK23: 18 | AL23: 0 | AM23: 0 | AN23: 1881 | AO23: 0 | AP23: 0 | AQ23: 0 | AR23: 0 | AS23: 0 | AT23: 0 | AW23: 0 | AX23: 12331 | AY23: N | AZ23: N | BA23: 11.7100.111.414301.1011.111636.0007.000000.000000.00000000 | BB23: 1126100105 | BC23: HO_INTER-STATE_OTH_NON_REC_18% | BD23: INPUT_TDS_194C | BF23: Fwd Non Rec | BG23: Fwd - Matched | BH23: Yes | BI23: 07 | BJ23: Delhi | BK23: 06AAGCD4246E1ZXDFSI2600000412 | BL23: 1881 | BM23: 38182.88 | BN23: -36302 | BO23: Matched | BP23: 9158398 | BQ23: Fwd Non Rec | BR23: FY 2026-27 | BS23: 37
A24: Payable Invoice | B24: AP_INVOICE | C24: 107 | D24: Godfrey_Phillips_India_Limited_HO | E24: GPIL_HO_New_Delhi(Services) | G24: HO New Friends Colony | H24: 07AABCG4768K1Z9 | I24: AP_INVOICES | J24: STANDARD CREATED | K24: Manual Invoice Entry | L24: STANDARD | M24: 46140 | N24: DFSI2600000751 | O24: 9174963 | P24: 46129 | Q24: Supplier | R24: 35671 | S24: DEUTSCHE CARS PRIVATE LIMITED | T24: Faridabad-OFF | U24: 06AAGCD4246E1ZX | V24: NOS | X24: 1188.14 | Y24: 1 | Z24: 1188.14 | AA24: GST_India | AB24: DFSI2600000751 | AC24: 46129 | AD24: BUDMINTIND | AE24: 3820000 | AF24: RADIATOR ANT | AI24: 1188.14 | AJ24: Normal | AK24: 18 | AL24: 0 | AM24: 0 | AN24: 213.87 | AO24: 0 | AP24: 0 | AQ24: 0 | AR24: 0 | AS24: 0 | AT24: 0 | AW24: 0 | AX24: 1402.01 | AY24: N | AZ24: N | BA24: 11.7100.111.414301.1000.100007.0007.000000.000000.00000000 | BB24: 1126100446 | BC24: HO_INTER-STATE_OTH_NON_REC_18% | BD24: INPUT_TDS_194C | BF24: Fwd Non Rec | BG24: Fwd - Matched | BH24: Yes | BI24: 07 | BJ24: Delhi | BK24: 06AAGCD4246E1ZXDFSI2600000751 | BL24: 213.87 | BM24: 36494.74 | BN24: -36281 | BO24: Matched | BP24: 9174963 | BQ24: Fwd Non Rec | BR24: FY 2026-27 | BS24: 36
A25: Payable Invoice | B25: AP_INVOICE | C25: 107 | D25: Godfrey_Phillips_India_Limited_HO | E25: GPIL_HO_New_Delhi(Services) | G25: HO New Friends Colony | H25: 07AABCG4768K1Z9 | I25: AP_INVOICES | J25: STANDARD CREATED | K25: Manual Invoice Entry | L25: STANDARD | M25: 46140 | N25: DFSI2600000751 | O25: 9174963 | P25: 46129 | Q25: Supplier | R25: 35671 | S25: DEUTSCHE CARS PRIVATE LIMITED | T25: Faridabad-OFF | U25: 06AAGCD4246E1ZX | V25: NOS | X25: 275 | Y25: 14 | Z25: 3850 | AA25: GST_India | AB25: DFSI2600000751 | AC25: 46129 | AD25: BUDMINTIND | AE25: 998729 | AF25: VEHICLE CHECK FOR EXTENDED CAR | AI25: 3850 | AJ25: Normal | AK25: 18 | AL25: 0 | AM25: 0 | AN25: 693 | AO25: 0 | AP25: 0 | AQ25: 0 | AR25: 0 | AS25: 0 | AT25: 0 | AW25: 0 | AX25: 4543 | AY25: N | AZ25: N | BA25: 11.7100.111.414301.1000.100007.0007.000000.000000.00000000 | BB25: 1126100446 | BC25: HO_INTER-STATE_OTH_NON_REC_18% | BD25: INPUT_TDS_194C | BF25: Fwd Non Rec | BG25: Fwd - Matched | BH25: Yes | BI25: 07 | BJ25: Delhi | BK25: 06AAGCD4246E1ZXDFSI2600000751 | BL25: 693 | BM25: 36494.74 | BN25: -35802 | BO25: Matched | BP25: 9174963 | BQ25: Fwd Non Rec | BR25: FY 2026-27 | BS25: 36
A26: Payable Invoice | B26: AP_INVOICE | C26: 107 | D26: Godfrey_Phillips_India_Limited_HO | E26: GPIL_HO_New_Delhi(Services) | H26: 07AABCG4768K1Z9 | I26: AP_INVOICES | J26: STANDARD VALIDATED TAX | K26: IA | L26: STANDARD | M26: 46133 | N26: 1/GPI/2026-27 | O26: 9167056 | P26: 46123 | Q26: Supplier | R26: 42255 | S26: SHATANSHU PANDA | T26: KOLKATA-OFF | V26: NOS | X26: 15000 | Y26: 1 | Z26: 15000 | AA26: GST_India | AB26: GPI-HOC260400005 | AC26: 46123 | AE26: 998216 | AF26: Conference held with Ms. Jaishree Tolani and Mr. Anshuman Vikram Singh 08.04.2026 to discuss | AI26: 15000 | AJ26: Normal | AK26: 18 | AL26: 0 | AM26: 0 | AN26: 2700 | AO26: 0 | AP26: 0 | AQ26: 0 | AR26: 0 | AS26: 0 | AT26: 0 | AW26: 0 | AX26: 17700 | AY26: Y | AZ26: Y | BA26: 11.7100.111.416001.1009.000000.0007.000000.000000.00000000 | BB26: 1126100300 | BC26: HO_INTER-STATE_REV_REC_18% | BD26: INPUT_SERVICE | BF26: RCM Rec | BG26: RCM-Not Matched | BH26: No | BI26: 07 | BJ26: Delhi | BK26: GPI-HOC260400005 | BL26: 2700 | BM26: #N/A | BN26: #N/A | BO26: RCM | BP26: 9167056 | BQ26: RCM Rec | BR26: RCM | BS26: 3
A27: Payable Invoice | B27: AP_INVOICE | C27: 107 | D27: Godfrey_Phillips_India_Limited_HO | E27: GPIL_HO_New_Delhi(Services) | H27: 07AABCG4768K1Z9 | I27: AP_INVOICES | J27: STANDARD VALIDATED TAX | K27: IA | L27: STANDARD | M27: 46142 | N27: GST/DL/2627/021 | O27: 9178273 | P27: 46129 | Q27: Supplier | R27: 38296 | S27: LGA TECHNOLOGY PRIVATE LIMITED | T27: NEW DELHI | U27: 07AADCL9190Q1ZO | V27: NOS | X27: 1 | Y27: 2237.28 | Z27: 2237.28 | AA27: GST_India | AB27: GST/DL/2627/021 | AC27: 46129 | AD27: BUDITMINTIND | AE27: 84733099 | AF27: HP KB CL KM260 KM260251243052 | AI27: 2237.28 | AJ27: Normal | AK27: 18 | AL27: 201.36 | AM27: 201.36 | AN27: 0 | AO27: 0 | AP27: 0 | AQ27: 0 | AR27: 0 | AS27: 0 | AT27: 0 | AW27: 0 | AX27: 2640 | AY27: Y | AZ27: N | BA27: 11.7100.111.414701.1013.000000.0007.000000.000000.00000000 | BB27: 1126100490 | BC27: HO_INTRA-STATE_OTH_REC_18% | BD27: INPUT | BF27: Fwd Rec | BG27: Fwd - Matched | BH27: No | BI27: 07 | BJ27: Delhi | BK27: 07AADCL9190Q1ZOGST/DL/2627/021 | BL27: 402.72 | BM27: 665.86 | BN27: -263 | BO27: Matched | BP27: 9178273 | BQ27: Fwd Rec | BR27: FY 2026-27 | BS27: 2
A28: Payable Invoice | B28: AP_INVOICE | C28: 107 | D28: Godfrey_Phillips_India_Limited_HO | E28: GPIL_HO_New_Delhi(Services) | G28: HO New Friends Colony | H28: 07AABCG4768K1Z9 | I28: AP_INVOICES | J28: STANDARD CREATED | K28: Manual Invoice Entry | L28: STANDARD | M28: 46126 | N28: 612 | O28: 9151235 | P28: 46116 | Q28: Supplier | R28: 40631 | S28: ARSHAD KHAN ENTERPRISES | T28: NEW DELHI | U28: 07AVQPK8011N2Z1 | V28: NOS | X28: 1200 | Y28: 9 | Z28: 10800 | AA28: GST_India | AB28: 612 | AC28: 46116 | AD28: BUDMINTIND | AE28: 995400 | AF28: Gazebo Ceiling Cane Light | AI28: 10800 | AJ28: Normal | AK28: 18 | AL28: 972 | AM28: 972 | AN28: 0 | AO28: 0 | AP28: 0 | AQ28: 0 | AR28: 0 | AS28: 0 | AT28: 0 | AW28: 0 | AX28: 12744 | AY28: N | AZ28: N | BA28: 11.7100.111.424156.1000.100007.0007.000000.000000.00000000 | BB28: 1126100056 | BC28: HO_INTRA-STATE_OTH_NON_REC_18% | BD28: INPUT_SERVICE | BF28: Fwd Non Rec | BG28: Fwd - Matched | BH28: No | BI28: 07 | BJ28: Delhi | BK28: 07AVQPK8011N2Z1612 | BL28: 1944 | BM28: 4734 | BN28: -2790 | BO28: Matched | BP28: 9151235 | BQ28: Fwd Non Rec | BR28: FY 2026-27 | BS28: 3
A29: Payable Invoice | B29: AP_INVOICE | C29: 107 | D29: Godfrey_Phillips_India_Limited_HO | E29: GPIL_HO_New_Delhi(Services) | G29: HO New Friends Colony | H29: 07AABCG4768K1Z9 | I29: AP_INVOICES | J29: STANDARD CREATED | K29: Manual Invoice Entry | L29: STANDARD | M29: 46127 | N29: DFSI2600000412 | O29: 9158398 | P29: 46090 | Q29: Supplier | R29: 35671 | S29: DEUTSCHE CARS PRIVATE LIMITED | T29: Faridabad-OFF | U29: 06AAGCD4246E1ZX | V29: NOS | X29: 7755.51 | Y29: 1 | Z29: 7755.51 | AA29: GST_India | AB29: DFSI2600000412 | AC29: 46121 | AD29: BUDMINTIND | AE29: 85129000 | AF29: SET OF WIPER | AI29: 7755.51 | AJ29: Normal | AK29: 18 | AL29: 0 | AM29: 0 | AN29: 1395.99 | AO29: 0 | AP29: 0 | AQ29: 0 | AR29: 0 | AS29: 0 | AT29: 0 | AW29: 0 | AX29: 9151.5 | AY29: N | AZ29: N | BA29: 11.7100.111.414301.1011.111636.0007.000000.000000.00000000 | BB29: 1126100105 | BC29: HO_INTER-STATE_OTH_NON_REC_18% | BD29: INPUT_TDS_194C | BF29: Fwd Non Rec | BG29: Fwd - Matched | BH29: Yes | BI29: 07 | BJ29: Delhi | BK29: 06AAGCD4246E1ZXDFSI2600000412 | BL29: 1395.99 | BM29: 38182.88 | BN29: -36787 | BO29: Matched | BP29: 9158398 | BQ29: Fwd Non Rec | BR29: FY 2026-27 | BS29: 37
A30: Payable Invoice | B30: AP_INVOICE | C30: 107 | D30: Godfrey_Phillips_India_Limited_HO | E30: GPIL_HO_New_Delhi(Services) | G30: HO New Friends Colony | H30: 07AABCG4768K1Z9 | I30: AP_INVOICES | J30: STANDARD CREATED | K30: Manual Invoice Entry | L30: STANDARD | M30: 46140 | N30: DFSI2600000751 | O30: 9174963 | P30: 46129 | Q30: Supplier | R30: 35671 | S30: DEUTSCHE CARS PRIVATE LIMITED | T30: Faridabad-OFF | U30: 06AAGCD4246E1ZX | V30: NOS | X30: 9315.94 | Y30: 1 | Z30: 9315.94 | AA30: GST_India | AB30: DFSI2600000751 | AC30: 46129 | AD30: BUDMINTIND | AE30: 84219900 | AF30: SET MICROFI | AI30: 9315.94 | AJ30: Normal | AK30: 18 | AL30: 0 | AM30: 0 | AN30: 1676.87 | AO30: 0 | AP30: 0 | AQ30: 0 | AR30: 0 | AS30: 0 | AT30: 0 | AW30: 0 | AX30: 10992.81 | AY30: N | AZ30: N | BA30: 11.7100.111.414301.1000.100007.0007.000000.000000.00000000 | BB30: 1126100446 | BC30: HO_INTER-STATE_OTH_NON_REC_18% | BD30: INPUT_TDS_194C | BF30: Fwd Non Rec | BG30: Fwd - Matched | BH30: Yes | BI30: 07 | BJ30: Delhi | BK30: 06AAGCD4246E1ZXDFSI2600000751 | BL30: 1676.87 | BM30: 36494.74 | BN30: -34818 | BO30: Matched | BP30: 9174963 | BQ30: Fwd Non Rec | BR30: FY 2026-27 | BS30: 36
A31: Payable Invoice | B31: AP_INVOICE | C31: 107 | D31: Godfrey_Phillips_India_Limited_HO | E31: GPIL_HO_New_Delhi(Services) | G31: HO New Friends Colony | H31: 07AABCG4768K1Z9 | I31: AP_INVOICES | J31: STANDARD CREATED | K31: Manual Invoice Entry | L31: STANDARD | M31: 46127 | N31: C07E262700010044 | O31: 9156758 | P31: 46113 | Q31: Supplier | R31: 33841 | S31: RELIANCE JIO INFOCOMM LIMITED | T31: NEW DELHI | U31: 07AABCI6363G1ZL | V31: NOS | X31: 1 | Y31: 509 | Z31: 509 | AA31: GST_India | AB31: C07E262700010044 | AC31: 46113 | AD31: MISCELLENS | AE31: 998400 | AF31: RELIANCE JIO MOBILE BILL FOR THE MONTH OF MAR 2026 | AI31: 509 | AJ31: Normal | AK31: 18 | AL31: 45.81 | AM31: 45.81 | AN31: 0 | AO31: 0 | AP31: 0 | AQ31: 0 | AR31: 0 | AS31: 0 | AT31: 0 | AW31: 0 | AX31: 600.62 | AY31: Y | AZ31: N | BA31: 11.7100.111.420803.1000.000000.0007.000000.000000.00000000 | BB31: 1126100082 | BC31: HO_INTRA-STATE_OTH_REC_18% | BD31: INPUT_SERVICE | BF31: Fwd Rec | BG31: Fwd - Matched | BH31: Yes | BI31: 07 | BJ31: Delhi | BK31: 07AABCI6363G1ZLC07E262700010044 | BL31: 91.62 | BM31: 369.72 | BN31: -278 | BO31: Matched | BP31: 9156758 | BQ31: Fwd Rec | BR31: FY 2026-27 | BS31: 2
A32: Payable Invoice | B32: AP_INVOICE | C32: 107 | D32: Godfrey_Phillips_India_Limited_HO | E32: GPIL_HO_New_Delhi(Services) | G32: HO New Friends Colony | H32: 07AABCG4768K1Z9 | I32: AP_INVOICES | J32: STANDARD CREATED | K32: Manual Invoice Entry | L32: STANDARD | M32: 46135 | N32: 3473457367 | O32: 9167995 | P32: 46127 | Q32: Supplier | R32: 39705 | S32: TATA TELESERVICES LIMITED | T32: NEW DELHI | U32: 07AAACT2438A1ZV | V32: NOS | X32: 1 | Y32: 7500 | Z32: 7500 | AA32: GST_India | AB32: 3473457367 | AC32: 46127 | AD32: BUDMINTIND | AE32: 998412 | AF32: TATA PRI bill for the period of 13-03-2026 to 12.04.2026– Jasola Office | AI32: 7500 | AJ32: Normal | AK32: 18 | AL32: 675 | AM32: 675 | AN32: 0 | AO32: 0 | AP32: 0 | AQ32: 0 | AR32: 0 | AS32: 0 | AT32: 0 | AW32: 0 | AX32: 8850 | AY32: Y | AZ32: N | BA32: 11.7100.111.420801.1010.000000.0007.000000.000000.00000000 | BB32: 1126100348 | BC32: HO_INTRA-STATE_OTH_REC_18% | BD32: INPUT_SERVICE | BF32: Fwd Rec | BG32: Fwd - Matched | BH32: Yes | BI32: 07 | BJ32: Delhi | BK32: 07AAACT2438A1ZV3473457367 | BL32: 1350 | BM32: 1350 | BN32: 0 | BO32: Matched | BP32: 9167995 | BQ32: Fwd Rec | BR32: FY 2026-27 | BS32: 1
A33: Payable Invoice | B33: AP_INVOICE | C33: 107 | D33: Godfrey_Phillips_India_Limited_HO | E33: GPIL_HO_New_Delhi(Services) | G33: HO New Friends Colony | H33: 07AABCG4768K1Z9 | I33: AP_INVOICES | J33: STANDARD CREATED | K33: Manual Invoice Entry | L33: STANDARD | M33: 46127 | N33: DFSI2600000412 | O33: 9158398 | P33: 46090 | Q33: Supplier | R33: 35671 | S33: DEUTSCHE CARS PRIVATE LIMITED | T33: Faridabad-OFF | U33: 06AAGCD4246E1ZX | V33: NOS | X33: 163.14 | Y33: 2 | Z33: 326.28 | AA33: GST_India | AB33: DFSI2600000412 | AC33: 46121 | AD33: BUDMINTIND | AE33: 34029099 | AF33: BMW GROUP GL | AI33: 326.28 | AJ33: Normal | AK33: 18 | AL33: 0 | AM33: 0 | AN33: 58.73 | AO33: 0 | AP33: 0 | AQ33: 0 | AR33: 0 | AS33: 0 | AT33: 0 | AW33: 0 | AX33: 385.01 | AY33: N | AZ33: N | BA33: 11.7100.111.414301.1011.111636.0007.000000.000000.00000000 | BB33: 1126100105 | BC33: HO_INTER-STATE_OTH_NON_REC_18% | BD33: INPUT_TDS_194C | BF33: Fwd Non Rec | BG33: Fwd - Matched | BH33: Yes | BI33: 07 | BJ33: Delhi | BK33: 06AAGCD4246E1ZXDFSI2600000412 | BL33: 58.73 | BM33: 38182.88 | BN33: -38124 | BO33: Matched | BP33: 9158398 | BQ33: Fwd Non Rec | BR33: FY 2026-27 | BS33: 37
A34: Payable Invoice | B34: AP_INVOICE | C34: 107 | D34: Godfrey_Phillips_India_Limited_HO | E34: GPIL_HO_New_Delhi(Services) | G34: HO New Friends Colony | H34: 07AABCG4768K1Z9 | I34: AP_INVOICES | J34: STANDARD CREATED | K34: Manual Invoice Entry | L34: STANDARD | M34: 46127 | N34: DFSI2600000412 | O34: 9158398 | P34: 46090 | Q34: Supplier | R34: 35671 | S34: DEUTSCHE CARS PRIVATE LIMITED | T34: Faridabad-OFF | U34: 06AAGCD4246E1ZX | V34: NOS | X34: 2155.51 | Y34: 4 | Z34: 8622.04 | AA34: GST_India | AB34: DFSI2600000412 | AC34: 46121 | AD34: BUDMINTIND | AE34: 85111000 | AF34: SPARK PLUG | AI34: 8622.04 | AJ34: Normal | AK34: 18 | AL34: 0 | AM34: 0 | AN34: 1551.97 | AO34: 0 | AP34: 0 | AQ34: 0 | AR34: 0 | AS34: 0 | AT34: 0 | AW34: 0 | AX34: 10174.01 | AY34: N | AZ34: N | BA34: 11.7100.111.414301.1011.111636.0007.000000.000000.00000000 | BB34: 1126100105 | BC34: HO_INTER-STATE_OTH_NON_REC_18% | BD34: INPUT_TDS_194C | BF34: Fwd Non Rec | BG34: Fwd - Matched | BH34: Yes | BI34: 07 | BJ34: Delhi | BK34: 06AAGCD4246E1ZXDFSI2600000412 | BL34: 1551.97 | BM34: 38182.88 | BN34: -36631 | BO34: Matched | BP34: 9158398 | BQ34: Fwd Non Rec | BR34: FY 2026-27 | BS34: 37
A35: Payable Invoice | B35: AP_INVOICE | C35: 107 | D35: Godfrey_Phillips_India_Limited_HO | E35: GPIL_HO_New_Delhi(Services) | G35: HO New Friends Colony | H35: 07AABCG4768K1Z9 | I35: AP_INVOICES | J35: STANDARD CREATED | K35: Manual Invoice Entry | L35: STANDARD | M35: 46140 | N35: DFSI2600000751 | O35: 9174963 | P35: 46129 | Q35: Supplier | R35: 35671 | S35: DEUTSCHE CARS PRIVATE LIMITED | T35: Faridabad-OFF | U35: 06AAGCD4246E1ZX | V35: NOS | X35: 275 | Y35: 0.001 | Z35: 0.28 | AA35: GST_India | AB35: DFSI2600000751 | AC35: 46129 | AD35: BUDMINTIND | AE35: 998729 | AF35: JOB TIME WITHOUT ALLOWANCE FOR / ELECTRICAL SYSTEM | AI35: 0.28 | AJ35: Normal | AK35: 18 | AL35: 0 | AM35: 0 | AN35: 0.05 | AO35: 0 | AP35: 0 | AQ35: 0 | AR35: 0 | AS35: 0 | AT35: 0 | AW35: 0 | AX35: 0.33 | AY35: N | AZ35: N | BA35: 11.7100.111.414301.1000.100007.0007.000000.000000.00000000 | BB35: 1126100446 | BC35: HO_INTER-STATE_OTH_NON_REC_18% | BD35: INPUT_TDS_194C | BF35: Fwd Non Rec | BG35: Fwd - Matched | BH35: Yes | BI35: 07 | BJ35: Delhi | BK35: 06AAGCD4246E1ZXDFSI2600000751 | BL35: 0.05 | BM35: 36494.74 | BN35: -36495 | BO35: Matched | BP35: 9174963 | BQ35: Fwd Non Rec | BR35: FY 2026-27 | BS35: 36
A36: Payable Invoice | B36: AP_INVOICE | C36: 107 | D36: Godfrey_Phillips_India_Limited_HO | E36: GPIL_HO_New_Delhi(Services) | H36: 07AABCG4768K1Z9 | I36: AP_INVOICES | J36: STANDARD VALIDATED TAX | K36: IA | L36: STANDARD | M36: 46141 | N36: 46082 | O36: 9178114 | P36: 46127 | Q36: Supplier | R36: 5093 | S36: ANS COMPUTERS AND PERIPHERALS | T36: DELHI | U36: 07ACBPV7574P1ZN | V36: NOS | X36: 1 | Y36: 450 | Z36: 450 | AA36: GST_India | AB36: 3 | AC36: 46127 | AD36: BUDITMINTIND | AE36: 8536 | AF36: RJ-45 CONNECTORS DLINK | AI36: 450 | AJ36: Normal | AK36: 18 | AL36: 40.5 | AM36: 40.5 | AN36: 0 | AO36: 0 | AP36: 0 | AQ36: 0 | AR36: 0 | AS36: 0 | AT36: 0 | AW36: 0 | AX36: 531 | AY36: Y | AZ36: N | BA36: 11.7100.111.414701.1013.000000.0007.000000.000000.00000000 | BB36: 1126100466 | BC36: HO_INTRA-STATE_OTH_REC_18% | BD36: INPUT | BF36: Fwd Rec | BG36: Fwd - Matched | BH36: No | BI36: 07 | BJ36: Delhi | BK36: 07ACBPV7574P1ZN3 | BL36: 81 | BM36: 1584 | BN36: -1503 | BO36: Matched | BP36: 9178114 | BQ36: Fwd Rec | BR36: FY 2026-27 | BS36: 3
A37: Payable Invoice | B37: AP_INVOICE | C37: 107 | D37: Godfrey_Phillips_India_Limited_HO | E37: GPIL_HO_New_Delhi(Services) | H37: 07AABCG4768K1Z9 | I37: AP_INVOICES | J37: STANDARD VALIDATED TAX | K37: IA | L37: STANDARD | M37: 46133 | N37: 738/2025-2026 | O37: 9164022 | P37: 46108 | Q37: Supplier | R37: 45456 | S37: SAGA LEGAL | T37: HEAD OFFICE | X37: 15000 | Y37: 1 | Z37: 15000 | AA37: GST_India | AB37: 738/2025-2026 | AC37: 46108 | AE37: 998216 | AF37: Professional fees towards appearance on 12.03.2026. | AI37: 15000 | AJ37: Normal | AK37: 18 | AL37: 1350 | AM37: 1350 | AN37: 0 | AO37: 0 | AP37: 0 | AQ37: 0 | AR37: 0 | AS37: 0 | AT37: 0 | AW37: 0 | AX37: 17700 | AY37: Y | AZ37: Y | BA37: 11.7100.111.234010.0000.000000.0007.000000.000000.00000000 | BB37: 1125113945 | BC37: HO_REV_CHARGE_REC_18% | BD37: INPUT_SERVICE | BF37: RCM Rec | BG37: RCM-Not Matched | BH37: No | BI37: 07 | BJ37: Delhi | BK37: 738/2025-2026 | BL37: 2700 | BM37: #N/A | BN37: #N/A | BO37: RCM | BP37: 9164022 | BQ37: RCM Rec | BR37: RCM | BS37: 3
A38: Payable Invoice | B38: AP_INVOICE | C38: 107 | D38: Godfrey_Phillips_India_Limited_HO | E38: GPIL_HO_New_Delhi(Services) | G38: HO New Friends Colony | H38: 07AABCG4768K1Z9 | I38: AP_INVOICES | J38: STANDARD CREATED | K38: Manual Invoice Entry | L38: STANDARD | M38: 46127 | N38: DFSI2600000412 | O38: 9158398 | P38: 46090 | Q38: Supplier | R38: 35671 | S38: DEUTSCHE CARS PRIVATE LIMITED | T38: Faridabad-OFF | U38: 06AAGCD4246E1ZX | V38: NOS | X38: 3507.2 | Y38: 1 | Z38: 3507.2 | AA38: GST_India | AB38: DFSI2600000412 | AC38: 46121 | AD38: BUDMINTIND | AE38: 84213100 | AF38: AIR FILTER E | AI38: 3507.2 | AJ38: Normal | AK38: 18 | AL38: 0 | AM38: 0 | AN38: 631.3 | AO38: 0 | AP38: 0 | AQ38: 0 | AR38: 0 | AS38: 0 | AT38: 0 | AW38: 0 | AX38: 4138.5 | AY38: N | AZ38: N | BA38: 11.7100.111.414301.1011.111636.0007.000000.000000.00000000 | BB38: 1126100105 | BC38: HO_INTER-STATE_OTH_NON_REC_18% | BD38: INPUT_TDS_194C | BF38: Fwd Non Rec | BG38: Fwd - Matched | BH38: Yes | BI38: 07 | BJ38: Delhi | BK38: 06AAGCD4246E1ZXDFSI2600000412 | BL38: 631.3 | BM38: 38182.88 | BN38: -37552 | BO38: Matched | BP38: 9158398 | BQ38: Fwd Non Rec | BR38: FY 2026-27 | BS38: 37
A39: Payable Invoice | B39: AP_INVOICE | C39: 107 | D39: Godfrey_Phillips_India_Limited_HO | E39: GPIL_HO_New_Delhi(Services) | G39: HO New Friends Colony | H39: 07AABCG4768K1Z9 | I39: AP_INVOICES | J39: STANDARD CREATED | K39: Manual Invoice Entry | L39: STANDARD | M39: 46127 | N39: MF2707I00063444 | O39: 9156749 | P39: 46115 | Q39: Supplier | R39: 6262 | S39: BHARTI AIRTEL LIMITED | T39: HO | U39: 07AAACB2894G1ZP | V39: NOS | X39: 1 | Y39: 1570 | Z39: 1570 | AA39: GST_India | AB39: MF2707I000063444 | AC39: 46115 | AD39: MISCELLENS | AE39: 998413 | AF39: AIRTEL MOBILE BILLS FOR THE MONTH OF MAR 2026 | AI39: 1570 | AJ39: Normal | AK39: 18 | AL39: 141.3 | AM39: 141.3 | AN39: 0 | AO39: 0 | AP39: 0 | AQ39: 0 | AR39: 0 | AS39: 0 | AT39: 0 | AW39: 0 | AX39: 1852.6 | AY39: Y | AZ39: N | BA39: 11.7100.111.420803.1000.000000.0007.000000.000000.00000000 | BB39: 1126100078 | BC39: HO_INTRA-STATE_OTH_REC_18% | BD39: INPUT_SERVICE | BF39: Fwd Rec | BG39: Fwd - Matched | BH39: Yes | BI39: 07 | BJ39: Delhi | BK39: 07AAACB2894G1ZPMF2707I000063444 | BL39: 282.6 | BM39: 8534.42 | BN39: -8252 | BO39: Matched | BP39: 9156749 | BQ39: Fwd Rec | BR39: FY 2026-27 | BS39: 17
A40: Payable Invoice | B40: AP_INVOICE | C40: 107 | D40: Godfrey_Phillips_India_Limited_HO | E40: GPIL_HO_New_Delhi(Services) | G40: HO New Friends Colony | H40: 07AABCG4768K1Z9 | I40: AP_INVOICES | J40: STANDARD CREATED | K40: Manual Invoice Entry | L40: STANDARD | M40: 46140 | N40: TXA26-00607 | O40: 9175014 | P40: 46129 | Q40: Supplier | R40: 15979 | S40: SPIRITED AUTO CARS (I) LTD. | T40: NEW DELHI | U40: 07AANCS0651B1ZM | V40: NOS | X40: 42 | Y40: 3 | Z40: 126 | AA40: GST_India | AB40: TXA26-00607 | AC40: 46129 | AD40: BUDMINTIND | AE40: 34029099 | AF40: WINDSHIELD WASHER FLUID | AI40: 126 | AJ40: Normal | AK40: 18 | AL40: 11.34 | AM40: 11.34 | AN40: 0 | AO40: 0 | AP40: 0 | AQ40: 0 | AR40: 0 | AS40: 0 | AT40: 0 | AW40: 0 | AX40: 148.68 | AY40: N | AZ40: N | BA40: 11.7100.111.414301.1009.110908.0007.000000.000000.00000000 | BB40: 1126100447 | BC40: HO_INTRA-STATE_OTH_NON_REC_18% | BD40: INPUT_TDS_194C | BF40: Fwd Non Rec | BG40: Fwd - Matched | BH40: Yes | BI40: 07 | BJ40: Delhi | BK40: 07AANCS0651B1ZMTXA26-00607 | BL40: 22.68 | BM40: 2435.38 | BN40: -2413 | BO40: Matched | BP40: 9175014 | BQ40: Fwd Non Rec | BR40: FY 2026-27 | BS40: 18
A41: Payable Invoice | B41: AP_INVOICE | C41: 107 | D41: Godfrey_Phillips_India_Limited_HO | E41: GPIL_HO_New_Delhi(Services) | H41: 07AABCG4768K1Z9 | I41: AP_INVOICES | J41: STANDARD VALIDATED TAX | K41: CONVERSION | L41: STANDARD | M41: 46133 | N41: HF2707I000137674 | O41: 9164386 | P41: 46115 | Q41: Supplier | R41: 6262 | S41: BHARTI AIRTEL LIMITED | T41: HO | U41: 07AAACB2894G1ZP | V41: NOS | X41: 1 | Y41: 399 | Z41: 399 | AA41: GST_India | AB41: HF2707I000137674 | AC41: 46115 | AD41: MISCELLENS | AE41: 998412 | AF41: GPI JASOLA OFFICE AIRTEL - LANDLINE TELEPHONE EXPENSES FOR THE MONTH OF March-2026 - - ADMN | AI41: 399 | AJ41: Normal | AK41: 18 | AL41: 35.91 | AM41: 35.91 | AN41: 0 | AO41: 0 | AP41: 0 | AQ41: 0 | AR41: 0 | AS41: 0 | AT41: 0 | AW41: 0 | AX41: 470.82 | AY41: Y | AZ41: N | BA41: 11.7100.111.420801.1010.000000.0007.000000.000000.00000000 | BB41: 1126100282 | BC41: HO_INTRA-STATE_OTH_REC_18% | BD41: INPUT_SERVICE | BF41: Fwd Rec | BG41: Fwd - Matched | BH41: Yes | BI41: 07 | BJ41: Delhi | BK41: 07AAACB2894G1ZPHF2707I000137674 | BL41: 71.82 | BM41: 71.82 | BN41: 0 | BO41: Matched | BP41: 9164386 | BQ41: Fwd Rec | BR41: FY 2026-27 | BS41: 1
A42: Payable Invoice | B42: AP_INVOICE | C42: 107 | D42: Godfrey_Phillips_India_Limited_HO | E42: GPIL_HO_New_Delhi(Services) | H42: 07AABCG4768K1Z9 | I42: AP_INVOICES | J42: STANDARD VALIDATED TAX | K42: IA | L42: STANDARD | M42: 46134 | N42: 130/26-27 | O42: 9164740 | P42: 46121 | Q42: Supplier | R42: 3615 | S42: NIYOGI OFFSET PVT.LTD. | T42: NEW DELHI | U42: 07AAACN0474C1ZX | V42: NOS | X42: 30 | Y42: 400 | Z42: 12000 | AA42: GST_India | AB42: 130/26-27 | AC42: 46121 | AD42: MISCELLENS | AE42: 998900 | AF42: Envelope (HSN 49090010 Womens Dday Appreciation Card | AI42: 12000 | AJ42: Normal | AK42: 18 | AL42: 1080 | AM42: 1080 | AN42: 0 | AO42: 0 | AP42: 0 | AQ42: 0 | AR42: 0 | AS42: 0 | AT42: 0 | AW42: 0 | AX42: 14160 | AY42: N | AZ42: N | BA42: 11.7100.111.420602.1011.000000.0007.000000.000000.00000000 | BB42: 1126100334 | BC42: HO_INTRA-STATE_OTH_NON_REC_18% | BD42: INPUT_SERVICE | BF42: Fwd Non Rec | BG42: Fwd - Matched | BH42: Yes | BI42: 07 | BJ42: Delhi | BK42: 07AAACN0474C1ZX130/26-27 | BL42: 2160 | BM42: 6014.7 | BN42: -3855 | BO42: Matched | BP42: 9164740 | BQ42: Fwd Non Rec | BR42: FY 2026-27 | BS42: 6
A43: Payable Invoice | B43: AP_INVOICE | C43: 107 | D43: Godfrey_Phillips_India_Limited_HO | E43: GPIL_HO_New_Delhi(Services) | H43: 07AABCG4768K1Z9 | I43: AP_INVOICES | J43: STANDARD VALIDATED TAX | K43: IA | L43: STANDARD | M43: 46133 | N43: 76 | O43: 9164654 | P43: 46120 | Q43: Supplier | R43: 43295 | S43: STELLAR ENTERPRISES | T43: DELHI-OFF | U43: 07AFGFS5626D1Z0 | V43: NOS | X43: 1 | Y43: 6000 | Z43: 6000 | AA43: GST_India | AB43: 76 | AC43: 46120 | AD43: MISCELLENS | AE43: 998719 | AF43: Machine Service Rental Charges Month of April OODG trtin 1500 CST per month Machine 4 Machines the | AI43: 6000 | AJ43: Normal | AK43: 18 | AL43: 540 | AM43: 540 | AN43: 0 | AO43: 0 | AP43: 0 | AQ43: 0 | AR43: 0 | AS43: 0 | AT43: 0 | AW43: 0 | AX43: 7080 | AY43: N | AZ43: N | BA43: 11.7100.111.412401.1010.000000.0007.000000.000000.00000000 | BB43: 1126100309 | BC43: HO_INTRA-STATE_OTH_NON_REC_18% | BD43: INPUT_SERVICE | BF43: Fwd Non Rec | BG43: Fwd - Matched | BH43: No | BI43: 07 | BJ43: Delhi | BK43: 07AFGFS5626D1Z076 | BL43: 1080 | BM43: 1080 | BN43: 0 | BO43: Matched | BP43: 9164654 | BQ43: Fwd Non Rec | BR43: FY 2026-27 | BS43: 1
A44: Payable Invoice | B44: AP_INVOICE | C44: 107 | D44: Godfrey_Phillips_India_Limited_HO | E44: GPIL_HO_New_Delhi(Services) | H44: 07AABCG4768K1Z9 | I44: AP_INVOICES | J44: STANDARD VALIDATED TAX | K44: Manual Invoice Entry | L44: STANDARD | M44: 46136 | N44: CI1001100320 | O44: 9171115 | P44: 46113 | Q44: Supplier | R44: 3734 | S44: THE OBEROI | T44: NEW DELHI | U44: 07AAACE6898B4ZH | X44: 0 | Y44: 0 | Z44: 125000 | AA44: GST_India | AB44: CI1001100320 | AC44: 46113 | AE44: 998599 | AF44: BELVEDERE MEM RENEWAL FEES APRIL 2026 TO MARCH 2027 DR BINA MODI | AI44: 125000 | AJ44: Normal | AK44: 18 | AL44: 11250 | AM44: 11250 | AN44: 0 | AO44: 0 | AP44: 0 | AQ44: 0 | AR44: 0 | AS44: 0 | AT44: 0 | AW44: 0 | AX44: 147500 | AY44: N | AZ44: N | BA44: 11.7100.111.420501.1000.100005.0007.000000.000000.00000000 | BB44: 1126100388 | BC44: HO_INTRA-STATE_OTH_NON_REC_18% | BD44: INPUT_SERVICE | BF44: Fwd Non Rec | BG44: Fwd - Matched | BH44: Yes | BI44: 07 | BJ44: Delhi | BK44: 07AAACE6898B4ZHCI1001100320 | BL44: 22500 | BM44: 22500 | BN44: 0 | BO44: Matched | BP44: 9171115 | BQ44: Fwd Non Rec | BR44: FY 2026-27 | BS44: 1
A45: Payable Invoice | B45: AP_INVOICE | C45: 107 | D45: Godfrey_Phillips_India_Limited_HO | E45: GPIL_HO_New_Delhi(Services) | G45: HO New Friends Colony | H45: 07AABCG4768K1Z9 | I45: AP_INVOICES | J45: STANDARD CREATED | K45: Manual Invoice Entry | L45: STANDARD | M45: 46127 | N45: MF2707I000130888 | O45: 9156752 | P45: 46115 | Q45: Supplier | R45: 6262 | S45: BHARTI AIRTEL LIMITED | T45: HO | U45: 07AAACB2894G1ZP | V45: NOS | X45: 1 | Y45: 399 | Z45: 399 | AA45: GST_India | AB45: MF2707I000130888 | AC45: 46115 | AD45: MISCELLENS | AE45: 998413 | AF45: AIRTEL MOBILE BILLS FOR THE MONTH OF MAR 2026-SHABAD KALRA | AI45: 399 | AJ45: Normal | AK45: 18 | AL45: 35.91 | AM45: 35.91 | AN45: 0 | AO45: 0 | AP45: 0 | AQ45: 0 | AR45: 0 | AS45: 0 | AT45: 0 | AW45: 0 | AX45: 470.82 | AY45: Y | AZ45: N | BA45: 11.7100.111.420803.1013.000000.0007.000000.000000.00000000 | BB45: 1126100080 | BC45: HO_INTRA-STATE_OTH_REC_18% | BD45: INPUT_SERVICE | BF45: Fwd Rec | BG45: Fwd - Matched | BH45: Yes | BI45: 07 | BJ45: Delhi | BK45: 07AAACB2894G1ZPMF2707I000130888 | BL45: 71.82 | BM45: 385.92 | BN45: -314 | BO45: Matched | BP45: 9156752 | BQ45: Fwd Rec | BR45: FY 2026-27 | BS45: 2
A46: Payable Invoice | B46: AP_INVOICE | C46: 107 | D46: Godfrey_Phillips_India_Limited_HO | E46: GPIL_HO_New_Delhi(Services) | G46: HO New Friends Colony | H46: 07AABCG4768K1Z9 | I46: AP_INVOICES | J46: STANDARD CREATED | K46: Manual Invoice Entry | L46: STANDARD | M46: 46140 | N46: TXA26-00607 | O46: 9175014 | P46: 46129 | Q46: Supplier | R46: 15979 | S46: SPIRITED AUTO CARS (I) LTD. | T46: NEW DELHI | U46: 07AANCS0651B1ZM | V46: NOS | X46: 1249 | Y46: 1 | Z46: 1249 | AA46: GST_India | AB46: TXA26-00607 | AC46: 46129 | AD46: BUDMINTIND | AE46: 38119000 | AF46: CLEANER INJECTOR | AI46: 1249 | AJ46: Normal | AK46: 18 | AL46: 112.41 | AM46: 112.41 | AN46: 0 | AO46: 0 | AP46: 0 | AQ46: 0 | AR46: 0 | AS46: 0 | AT46: 0 | AW46: 0 | AX46: 1473.82 | AY46: N | AZ46: N | BA46: 11.7100.111.414301.1009.110908.0007.000000.000000.00000000 | BB46: 1126100447 | BC46: HO_INTRA-STATE_OTH_NON_REC_18% | BD46: INPUT_TDS_194C | BF46: Fwd Non Rec | BG46: Fwd - Matched | BH46: Yes | BI46: 07 | BJ46: Delhi | BK46: 07AANCS0651B1ZMTXA26-00607 | BL46: 224.82 | BM46: 2435.38 | BN46: -2211 | BO46: Matched | BP46: 9175014 | BQ46: Fwd Non Rec | BR46: FY 2026-27 | BS46: 18
A47: Payable Invoice | B47: AP_INVOICE | C47: 107 | D47: Godfrey_Phillips_India_Limited_HO | E47: GPIL_HO_New_Delhi(Services) | H47: 07AABCG4768K1Z9 | I47: AP_INVOICES | J47: STANDARD VALIDATED TAX | K47: CONVERSION | L47: STANDARD | M47: 46133 | N47: HF2707I000101334 | O47: 9164393 | P47: 46115 | Q47: Supplier | R47: 6262 | S47: BHARTI AIRTEL LIMITED | T47: HO | U47: 07AAACB2894G1ZP | V47: NOS | X47: 1 | Y47: 999 | Z47: 999 | AA47: GST_India | AB47: HF2707I000101334 | AC47: 46115 | AD47: MISCELLENS | AE47: 998412 | AF47: PRESIDENT OFF.( A-1) AIRTEL - LANDLINE TELEPHONE EXPENSES FOR THE MONTH OF March-2026 - - CM | AI47: 999 | AJ47: Normal | AK47: 18 | AL47: 89.91 | AM47: 89.91 | AN47: 0 | AO47: 0 | AP47: 0 | AQ47: 0 | AR47: 0 | AS47: 0 | AT47: 0 | AW47: 0 | AX47: 1178.82 | AY47: N | AZ47: N | BA47: 11.7100.111.420801.1000.000000.0007.000000.000000.00000000 | BB47: 1126100289 | BC47: HO_INTRA-STATE_OTH_NON_REC_18% | BD47: INPUT_SERVICE | BF47: Fwd Non Rec | BG47: Fwd - Matched | BH47: Yes | BI47: 07 | BJ47: Delhi | BK47: 07AAACB2894G1ZPHF2707I000101334 | BL47: 179.82 | BM47: 179.82 | BN47: 0 | BO47: Matched | BP47: 9164393 | BQ47: Fwd Non Rec | BR47: FY 2026-27 | BS47: 1
A48: Payable Invoice | B48: AP_INVOICE | C48: 107 | D48: Godfrey_Phillips_India_Limited_HO | E48: GPIL_HO_New_Delhi(Services) | H48: 07AABCG4768K1Z9 | I48: AP_INVOICES | J48: STANDARD VALIDATED TAX | K48: IA | L48: STANDARD | M48: 46126 | N48: DLS2627000000643 | O48: 9155607 | P48: 46114 | Q48: Supplier | R48: 2770 | S48: CANON INDIA PVT. LTD. | T48: OKHLA | U48: 07AAACC4175D1Z0 | V48: NOS | X48: 1 | Y48: 1.6 | Z48: 1.6 | AA48: GST_India | AB48: DLS2627000000643 | AC48: 46114 | AD48: MISCELLENS | AE48: 84439952 | AF48: Supply of Tonerilnk Spares along With Support Services | AI48: 1.6 | AJ48: Normal | AK48: 18 | AL48: 0.14 | AM48: 0.14 | AN48: 0 | AO48: 0 | AP48: 0 | AQ48: 0 | AR48: 0 | AS48: 0 | AT48: 0 | AW48: 0 | AX48: 1.88 | AY48: Y | AZ48: N | BA48: 11.7100.111.234010.0000.000000.0007.000000.000000.00000000 | BB48: 1126100057 | BC48: HO_INTRA-STATE_OTH_REC_18% | BD48: INPUT_SERVICE | BF48: Fwd Rec | BG48: Fwd - Matched | BH48: Yes | BI48: 07 | BJ48: Delhi | BK48: 07AAACC4175D1Z0DLS2627000000643 | BL48: 0.28 | BM48: 2568.6 | BN48: -2568 | BO48: Matched | BP48: 9155607 | BQ48: Fwd Rec | BR48: FY 2026-27 | BS48: 4
A49: Payable Invoice | B49: AP_INVOICE | C49: 107 | D49: Godfrey_Phillips_India_Limited_HO | E49: GPIL_HO_New_Delhi(Services) | H49: 07AABCG4768K1Z9 | I49: AP_INVOICES | J49: STANDARD VALIDATED TAX | K49: IA | L49: STANDARD | M49: 46141 | N49: 4 | O49: 9177498 | P49: 46129 | Q49: Supplier | R49: 5093 | S49: ANS COMPUTERS AND PERIPHERALS | T49: DELHI | U49: 07ACBPV7574P1ZN | V49: NOS | X49: 1 | Y49: 14740 | Z49: 14740 | AA49: GST_India | AB49: 4 | AC49: 46129 | AD49: BUDITMINTIND | AE49: 8544 | AF49: HDD-1 TB WD EXTERNAL USB | AI49: 14740 | AJ49: Normal | AK49: 18 | AL49: 1326.6 | AM49: 1326.6 | AN49: 0 | AO49: 0 | AP49: 0 | AQ49: 0 | AR49: 0 | AS49: 0 | AT49: 0 | AW49: 0 | AX49: 17393.2 | AY49: Y | AZ49: N | BA49: 11.7100.111.414701.1013.000000.0007.000000.000000.00000000 | BB49: 1126100464 | BC49: HO_INTRA-STATE_OTH_REC_18% | BD49: INPUT | BF49: Fwd Rec | BG49: Fwd - Matched | BH49: No | BI49: 07 | BJ49: Delhi | BK49: 07ACBPV7574P1ZN4 | BL49: 2653.2 | BM49: 6033.6 | BN49: -3380 | BO49: Matched | BP49: 9177498 | BQ49: Fwd Rec | BR49: FY 2026-27 | BS49: 3
A50: Payable Invoice | B50: AP_INVOICE | C50: 107 | D50: Godfrey_Phillips_India_Limited_HO | E50: GPIL_HO_New_Delhi(Services) | H50: 07AABCG4768K1Z9 | I50: AP_INVOICES | J50: STANDARD VALIDATED TAX | K50: IA | L50: STANDARD | M50: 46125 | N50: AVZ/274/2025-26 | O50: 9151134 | P50: 46112 | Q50: Supplier | R50: 7826 | S50: A AND V ZIPPERS PVT.LTD. | T50: NEW DELHI | U50: 07AADCA3655R1Z7 | V50: NOS | X50: 1 | Y50: 697701 | Z50: 697701 | AA50: GST_India | AB50: AVZ/274/2025-26 | AC50: 46112 | AD50: MISCELLENS | AE50: 998515 | AF50: PAYROLL STAFFING SERVICE | AI50: 697701 | AJ50: Normal | AK50: 18 | AL50: 62793.09 | AM50: 62793.09 | AN50: 0 | AO50: 0 | AP50: 0 | AQ50: 0 | AR50: 0 | AS50: 0 | AT50: 0 | AW50: 0 | AX50: 823287.18 | AY50: Y | AZ50: N | BA50: 11.7100.111.420301.1010.100007.0007.000000.000000.00000000 | BB50: 1126100024 | BC50: HO_INTRA-STATE_OTH_REC_18% | BD50: INPUT_SERVICE | BF50: Fwd Rec | BG50: Fwd - Matched | BH50: Yes | BI50: 07 | BJ50: Delhi | BK50: 07AADCA3655R1Z7AVZ/274/2025-26 | BL50: 125586.18 | BM50: 125586.18 | BN50: 0 | BO50: Matched | BP50: 9151134 | BQ50: Fwd Rec | BR50: FY 2025-26 | BS50: 1
A51: Payable Invoice | B51: AP_INVOICE | C51: 107 | D51: Godfrey_Phillips_India_Limited_HO | E51: GPIL_HO_New_Delhi(Services) | H51: 07AABCG4768K1Z9 | I51: AP_INVOICES | J51: STANDARD VALIDATED TAX | K51: IA | L51: STANDARD | M51: 46126 | N51: DLS2627000000660 | O51: 9155615 | P51: 46114 | Q51: Supplier | R51: 2770 | S51: CANON INDIA PVT. LTD. | T51: OKHLA | U51: 07AAACC4175D1Z0 | V51: NOS | X51: 1 | Y51: 2137.98 | Z51: 2137.98 | AA51: GST_India | AB51: DLS2627000000660 | AC51: 46114 | AD51: MISCELLENS | AE51: 84439952 | AF51: Supply of TonerInk Spares along with Support Services | AI51: 2137.98 | AJ51: Normal | AK51: 18 | AL51: 192.42 | AM51: 192.42 | AN51: 0 | AO51: 0 | AP51: 0 | AQ51: 0 | AR51: 0 | AS51: 0 | AT51: 0 | AW51: 0 | AX51: 2522.82 | AY51: Y | AZ51: N | BA51: 11.7100.111.234010.0000.000000.0007.000000.000000.00000000 | BB51: 1126100065 | BC51: HO_INTRA-STATE_OTH_REC_18% | BD51: INPUT_SERVICE | BF51: Fwd Rec | BG51: Fwd - Matched | BH51: Yes | BI51: 07 | BJ51: Delhi | BK51: 07AAACC4175D1Z0DLS2627000000660 | BL51: 384.84 | BM51: 1123.84 | BN51: -739 | BO51: Matched | BP51: 9155615 | BQ51: Fwd Rec | BR51: FY 2026-27 | BS51: 4
A52: Payable Invoice | B52: AP_INVOICE | C52: 107 | D52: Godfrey_Phillips_India_Limited_HO | E52: GPIL_HO_New_Delhi(Services) | H52: 07AABCG4768K1Z9 | I52: AP_INVOICES | J52: STANDARD VALIDATED TAX | K52: Manual Invoice Entry | L52: STANDARD | M52: 46142 | N52: MH25I00004429548 | O52: 9178796 | P52: 46090 | Q52: Supplier | R52: 11570 | S52: TATA AIG GENERAL INSURANCE COMPANY LIMITED | T52: MUMBAI | U52: 27AABCT3518Q1ZW | X52: 0 | Y52: 0 | Z52: 9270 | AA52: GST_India | AB52: MH25I00004429548 | AC52: 46090 | AE52: 9971 | AF52: Motor Car Renewal DL7CW4741 Maruti xl-6 User ED Office | AI52: 9270 | AJ52: Normal | AK52: 18 | AL52: 0 | AM52: 0 | AN52: 1668.6 | AO52: 0 | AP52: 0 | AQ52: 0 | AR52: 0 | AS52: 0 | AT52: 0 | AW52: 0 | AX52: 10938.6 | AY52: N | AZ52: N | BA52: 11.7100.111.234010.0000.000000.0007.000000.000000.00000000 | BB52: 1126100478 | BC52: HO_INTER-STATE_OTH_NON_REC_18% | BD52: INPUT_SERVICE | BF52: Fwd Non Rec | BG52: Fwd - Matched | BH52: Yes | BI52: 07 | BJ52: Delhi | BK52: 27AABCT3518Q1ZWMH25I00004429548 | BL52: 1668.6 | BM52: 1669 | BN52: 0 | BO52: Matched | BP52: 9178796 | BQ52: Fwd Non Rec | BR52: FY 2025-26 | BS52: 1
A53: Payable Invoice | B53: AP_INVOICE | C53: 107 | D53: Godfrey_Phillips_India_Limited_HO | E53: GPIL_HO_New_Delhi(Services) | G53: HO New Friends Colony | H53: 07AABCG4768K1Z9 | I53: AP_INVOICES | J53: STANDARD CREATED | K53: Manual Invoice Entry | L53: STANDARD | M53: 46127 | N53: DFSI2600000412 | O53: 9158398 | P53: 46090 | Q53: Supplier | R53: 35671 | S53: DEUTSCHE CARS PRIVATE LIMITED | T53: Faridabad-OFF | U53: 06AAGCD4246E1ZX | V53: NOS | X53: 275 | Y53: 24 | Z53: 6600 | AA53: GST_India | AB53: DFSI2600000412 | AC53: 46121 | AD53: BUDMINTIND | AE53: 998729 | AF53: VEHICLE CARE SET 1 VEHICLE | AI53: 6600 | AJ53: Normal | AK53: 18 | AL53: 0 | AM53: 0 | AN53: 1188 | AO53: 0 | AP53: 0 | AQ53: 0 | AR53: 0 | AS53: 0 | AT53: 0 | AW53: 0 | AX53: 7788 | AY53: N | AZ53: N | BA53: 11.7100.111.414301.1011.111636.0007.000000.000000.00000000 | BB53: 1126100105 | BC53: HO_INTER-STATE_OTH_NON_REC_18% | BD53: INPUT_TDS_194C | BF53: Fwd Non Rec | BG53: Fwd - Matched | BH53: Yes | BI53: 07 | BJ53: Delhi | BK53: 06AAGCD4246E1ZXDFSI2600000412 | BL53: 1188 | BM53: 38182.88 | BN53: -36995 | BO53: Matched | BP53: 9158398 | BQ53: Fwd Non Rec | BR53: FY 2026-27 | BS53: 37
A54: Payable Invoice | B54: AP_INVOICE | C54: 107 | D54: Godfrey_Phillips_India_Limited_HO | E54: GPIL_HO_New_Delhi(Services) | G54: HO New Friends Colony | H54: 07AABCG4768K1Z9 | I54: AP_INVOICES | J54: STANDARD CREATED | K54: Manual Invoice Entry | L54: STANDARD | M54: 46140 | N54: DFSI2600000751 | O54: 9174963 | P54: 46129 | Q54: Supplier | R54: 35671 | S54: DEUTSCHE CARS PRIVATE LIMITED | T54: Faridabad-OFF | U54: 06AAGCD4246E1ZX | V54: NOS | X54: 7839.83 | Y54: 2 | Z54: 15679.66 | AA54: GST_India | AB54: DFSI2600000751 | AC54: 46129 | AD54: BUDMINTIND | AE54: 34053000 | AF54: CERAMIC COAT | AI54: 15679.66 | AJ54: Normal | AK54: 18 | AL54: 0 | AM54: 0 | AN54: 2822.34 | AO54: 0 | AP54: 0 | AQ54: 0 | AR54: 0 | AS54: 0 | AT54: 0 | AW54: 0 | AX54: 18502 | AY54: N | AZ54: N | BA54: 11.7100.111.414301.1000.100007.0007.000000.000000.00000000 | BB54: 1126100446 | BC54: HO_INTER-STATE_OTH_NON_REC_18% | BD54: INPUT_TDS_194C | BF54: Fwd Non Rec | BG54: Fwd - Matched | BH54: Yes | BI54: 07 | BJ54: Delhi | BK54: 06AAGCD4246E1ZXDFSI2600000751 | BL54: 2822.34 | BM54: 36494.74 | BN54: -33672 | BO54: Matched | BP54: 9174963 | BQ54: Fwd Non Rec | BR54: FY 2026-27 | BS54: 36
A55: Payable Invoice | B55: AP_INVOICE | C55: 107 | D55: Godfrey_Phillips_India_Limited_HO | E55: GPIL_HO_New_Delhi(Services) | G55: HO New Friends Colony | H55: 07AABCG4768K1Z9 | I55: AP_INVOICES | J55: STANDARD CREATED | K55: Manual Invoice Entry | L55: STANDARD | M55: 46140 | N55: DFSI2600000751 | O55: 9174963 | P55: 46129 | Q55: Supplier | R55: 35671 | S55: DEUTSCHE CARS PRIVATE LIMITED | T55: Faridabad-OFF | U55: 06AAGCD4246E1ZX | V55: NOS | X55: 220 | Y55: 3 | Z55: 660 | AA55: GST_India | AB55: DFSI2600000751 | AC55: 46129 | AD55: BUDMINTIND | AE55: 998729 | AF55: ENGINE OIL SERVICE | AI55: 660 | AJ55: Normal | AK55: 18 | AL55: 0 | AM55: 0 | AN55: 118.8 | AO55: 0 | AP55: 0 | AQ55: 0 | AR55: 0 | AS55: 0 | AT55: 0 | AW55: 0 | AX55: 778.8 | AY55: N | AZ55: N | BA55: 11.7100.111.414301.1000.100007.0007.000000.000000.00000000 | BB55: 1126100446 | BC55: HO_INTER-STATE_OTH_NON_REC_18% | BD55: INPUT_TDS_194C | BF55: Fwd Non Rec | BG55: Fwd - Matched | BH55: Yes | BI55: 07 | BJ55: Delhi | BK55: 06AAGCD4246E1ZXDFSI2600000751 | BL55: 118.8 | BM55: 36494.74 | BN55: -36376 | BO55: Matched | BP55: 9174963 | BQ55: Fwd Non Rec | BR55: FY 2026-27 | BS55: 36
A56: Payable Invoice | B56: AP_INVOICE | C56: 107 | D56: Godfrey_Phillips_India_Limited_HO | E56: GPIL_HO_New_Delhi(Services) | G56: HO New Friends Colony | H56: 07AABCG4768K1Z9 | I56: AP_INVOICES | J56: STANDARD CREATED | K56: Manual Invoice Entry | L56: STANDARD | M56: 46127 | N56: MF2707I000063997 | O56: 9156751 | P56: 46115 | Q56: Supplier | R56: 6262 | S56: BHARTI AIRTEL LIMITED | T56: HO | U56: 07AAACB2894G1ZP | V56: NOS | X56: 1 | Y56: 565 | Z56: 565 | AA56: GST_India | AB56: MF2707I000063997 | AC56: 46115 | AD56: MISCELLENS | AE56: 998413 | AF56: AIRTEL MOBILE BILLS FOR THE MONTH OF MAR 2026-CHANDRA SHEKHAR SHARMA | AI56: 565 | AJ56: Normal | AK56: 18 | AL56: 50.85 | AM56: 50.85 | AN56: 0 | AO56: 0 | AP56: 0 | AQ56: 0 | AR56: 0 | AS56: 0 | AT56: 0 | AW56: 0 | AX56: 666.7 | AY56: Y | AZ56: N | BA56: 11.7100.111.420803.1009.110908.0007.000000.000000.00000000 | BB56: 1126100079 | BC56: HO_INTRA-STATE_OTH_REC_18% | BD56: INPUT_SERVICE | BF56: Fwd Rec | BG56: Fwd - Matched | BH56: Yes | BI56: 07 | BJ56: Delhi | BK56: 07AAACB2894G1ZPMF2707I000063997 | BL56: 101.7 | BM56: 101.7 | BN56: 0 | BO56: Matched | BP56: 9156751 | BQ56: Fwd Rec | BR56: FY 2026-27 | BS56: 1
A57: Payable Invoice | B57: AP_INVOICE | C57: 107 | D57: Godfrey_Phillips_India_Limited_HO | E57: GPIL_HO_New_Delhi(Services) | G57: HO New Friends Colony | H57: 07AABCG4768K1Z9 | I57: AP_INVOICES | J57: STANDARD CREATED | K57: Manual Invoice Entry | L57: STANDARD | M57: 46127 | N57: MF2707I00063444 | O57: 9156749 | P57: 46115 | Q57: Supplier | R57: 6262 | S57: BHARTI AIRTEL LIMITED | T57: HO | U57: 07AAACB2894G1ZP | V57: NOS | X57: 1 | Y57: 2431 | Z57: 2431 | AA57: GST_India | AB57: MF2707I000063444 | AC57: 46115 | AD57: MISCELLENS | AE57: 998413 | AF57: AIRTEL MOBILE BILLS FOR THE MONTH OF MAR 2026 | AI57: 2431 | AJ57: Normal | AK57: 18 | AL57: 218.79 | AM57: 218.79 | AN57: 0 | AO57: 0 | AP57: 0 | AQ57: 0 | AR57: 0 | AS57: 0 | AT57: 0 | AW57: 0 | AX57: 2868.58 | AY57: Y | AZ57: N | BA57: 11.7100.111.420803.1000.000000.0007.000000.000000.00000000 | BB57: 1126100078 | BC57: HO_INTRA-STATE_OTH_REC_18% | BD57: INPUT_SERVICE | BF57: Fwd Rec | BG57: Fwd - Matched | BH57: Yes | BI57: 07 | BJ57: Delhi | BK57: 07AAACB2894G1ZPMF2707I000063444 | BL57: 437.58 | BM57: 8534.42 | BN57: -8097 | BO57: Matched | BP57: 9156749 | BQ57: Fwd Rec | BR57: FY 2026-27 | BS57: 17
A58: Payable Invoice | B58: AP_INVOICE | C58: 107 | D58: Godfrey_Phillips_India_Limited_HO | E58: GPIL_HO_New_Delhi(Services) | G58: HO New Friends Colony | H58: 07AABCG4768K1Z9 | I58: AP_INVOICES | J58: STANDARD CREATED | K58: Manual Invoice Entry | L58: STANDARD | M58: 46140 | N58: TXA26-00607 | O58: 9175014 | P58: 46129 | Q58: Supplier | R58: 15979 | S58: SPIRITED AUTO CARS (I) LTD. | T58: NEW DELHI | U58: 07AANCS0651B1ZM | V58: NOS | X58: 1074.6 | Y58: 1 | Z58: 1074.6 | AA58: GST_India | AB58: TXA26-00607 | AC58: 46129 | AD58: BUDMINTIND | AE58: 998729 | AF58: WHEEL ALIGNMENT INSP | AI58: 1074.6 | AJ58: Normal | AK58: 18 | AL58: 96.71 | AM58: 96.71 | AN58: 0 | AO58: 0 | AP58: 0 | AQ58: 0 | AR58: 0 | AS58: 0 | AT58: 0 | AW58: 0 | AX58: 1268.02 | AY58: N | AZ58: N | BA58: 11.7100.111.414301.1009.110908.0007.000000.000000.00000000 | BB58: 1126100447 | BC58: HO_INTRA-STATE_OTH_NON_REC_18% | BD58: INPUT_TDS_194C | BF58: Fwd Non Rec | BG58: Fwd - Matched | BH58: Yes | BI58: 07 | BJ58: Delhi | BK58: 07AANCS0651B1ZMTXA26-00607 | BL58: 193.42 | BM58: 2435.38 | BN58: -2242 | BO58: Matched | BP58: 9175014 | BQ58: Fwd Non Rec | BR58: FY 2026-27 | BS58: 18
A59: Payable Invoice | B59: AP_INVOICE | C59: 107 | D59: Godfrey_Phillips_India_Limited_HO | E59: GPIL_HO_New_Delhi(Services) | G59: HO New Friends Colony | H59: 07AABCG4768K1Z9 | I59: AP_INVOICES | J59: STANDARD CREATED | K59: Manual Invoice Entry | L59: STANDARD | M59: 46140 | N59: DFSI2600000751 | O59: 9174963 | P59: 46129 | Q59: Supplier | R59: 35671 | S59: DEUTSCHE CARS PRIVATE LIMITED | T59: Faridabad-OFF | U59: 06AAGCD4246E1ZX | V59: NOS | X59: 275 | Y59: 10 | Z59: 2750 | AA59: GST_India | AB59: DFSI2600000751 | AC59: 46129 | AD59: BUDMINTIND | AE59: 998729 | AF59: KINEMATICS DIAGNOSIS SYSTEM WHEEL ALIGNMENT WITH RIDE HEIGHT MEASUREMENT WITHOUT LOADING THE VEHICLE | AI59: 2750 | AJ59: Normal | AK59: 18 | AL59: 0 | AM59: 0 | AN59: 495 | AO59: 0 | AP59: 0 | AQ59: 0 | AR59: 0 | AS59: 0 | AT59: 0 | AW59: 0 | AX59: 3245 | AY59: N | AZ59: N | BA59: 11.7100.111.414301.1000.100007.0007.000000.000000.00000000 | BB59: 1126100446 | BC59: HO_INTER-STATE_OTH_NON_REC_18% | BD59: INPUT_TDS_194C | BF59: Fwd Non Rec | BG59: Fwd - Matched | BH59: Yes | BI59: 07 | BJ59: Delhi | BK59: 06AAGCD4246E1ZXDFSI2600000751 | BL59: 495 | BM59: 36494.74 | BN59: -36000 | BO59: Matched | BP59: 9174963 | BQ59: Fwd Non Rec | BR59: FY 2026-27 | BS59: 36
A60: Payable Invoice | B60: AP_INVOICE | C60: 107 | D60: Godfrey_Phillips_India_Limited_HO | E60: GPIL_HO_New_Delhi(Services) | G60: HO New Friends Colony | H60: 07AABCG4768K1Z9 | I60: AP_INVOICES | J60: STANDARD CREATED | K60: Manual Invoice Entry | L60: STANDARD | M60: 46127 | N60: MF2707I00063444 | O60: 9156749 | P60: 46115 | Q60: Supplier | R60: 6262 | S60: BHARTI AIRTEL LIMITED | T60: HO | U60: 07AAACB2894G1ZP | V60: NOS | X60: 1 | Y60: 400 | Z60: 400 | AA60: GST_India | AB60: MF2707I000063444 | AC60: 46115 | AD60: MISCELLENS | AE60: 998413 | AF60: AIRTEL MOBILE BILLS FOR THE MONTH OF MAR 2026 | AI60: 400 | AJ60: Normal | AK60: 18 | AL60: 36 | AM60: 36 | AN60: 0 | AO60: 0 | AP60: 0 | AQ60: 0 | AR60: 0 | AS60: 0 | AT60: 0 | AW60: 0 | AX60: 472 | AY60: Y | AZ60: N | BA60: 11.7100.111.420803.1000.000000.0007.000000.000000.00000000 | BB60: 1126100078 | BC60: HO_INTRA-STATE_OTH_REC_18% | BD60: INPUT_SERVICE | BF60: Fwd Rec | BG60: Fwd - Matched | BH60: Yes | BI60: 07 | BJ60: Delhi | BK60: 07AAACB2894G1ZPMF2707I000063444 | BL60: 72 | BM60: 8534.42 | BN60: -8462 | BO60: Matched | BP60: 9156749 | BQ60: Fwd Rec | BR60: FY 2026-27 | BS60: 17
A61: Payable Invoice | B61: AP_INVOICE | C61: 107 | D61: Godfrey_Phillips_India_Limited_HO | E61: GPIL_HO_New_Delhi(Services) | H61: 07AABCG4768K1Z9 | I61: AP_INVOICES | J61: STANDARD VALIDATED TAX | K61: IA | L61: STANDARD | M61: 46126 | N61: DLS2627000000355 | O61: 9155612 | P61: 45749 | Q61: Supplier | R61: 2770 | S61: CANON INDIA PVT. LTD. | T61: OKHLA | U61: 07AAACC4175D1Z0 | V61: NOS | X61: 1 | Y61: 1937.42 | Z61: 1937.42 | AA61: GST_India | AB61: DLS2627000000355 | AC61: 45749 | AD61: MISCELLENS | AE61: 84439952 | AF61: Supply of TonerInk and Spares along with Support Services | AI61: 1937.42 | AJ61: Normal | AK61: 18 | AL61: 174.37 | AM61: 174.37 | AN61: 0 | AO61: 0 | AP61: 0 | AQ61: 0 | AR61: 0 | AS61: 0 | AT61: 0 | AW61: 0 | AX61: 2286.16 | AY61: Y | AZ61: N | BA61: 11.7100.111.234010.0000.000000.0007.000000.000000.00000000 | BB61: 1126100062 | BC61: HO_INTRA-STATE_OTH_REC_18% | BD61: INPUT_SERVICE | BF61: Fwd Rec | BG61: Fwd - Matched | BH61: Yes | BI61: 07 | BJ61: Delhi | BK61: 07AAACC4175D1Z0DLS2627000000355 | BL61: 348.74 | BM61: 348.74 | BN61: 0 | BO61: Matched | BP61: 9155612 | BQ61: Fwd Rec | BR61: FY 2026-27 | BS61: 1
A62: Payable Invoice | B62: AP_INVOICE | C62: 107 | D62: Godfrey_Phillips_India_Limited_HO | E62: GPIL_HO_New_Delhi(Services) | H62: 07AABCG4768K1Z9 | I62: AP_INVOICES | J62: STANDARD VALIDATED TAX | K62: IA | L62: STANDARD | M62: 46126 | N62: DLS2627000000642 | O62: 9155618 | P62: 46114 | Q62: Supplier | R62: 2770 | S62: CANON INDIA PVT. LTD. | T62: OKHLA | U62: 07AAACC4175D1Z0 | V62: NOS | X62: 1 | Y62: 40 | Z62: 40 | AA62: GST_India | AB62: DLS2627000000642 | AC62: 46114 | AD62: MISCELLENS | AE62: 84439952 | AF62: Supply of TonerInk and Spares along with Support Services | AI62: 40 | AJ62: Normal | AK62: 18 | AL62: 3.6 | AM62: 3.6 | AN62: 0 | AO62: 0 | AP62: 0 | AQ62: 0 | AR62: 0 | AS62: 0 | AT62: 0 | AW62: 0 | AX62: 47.2 | AY62: Y | AZ62: N | BA62: 11.7100.111.234010.0000.000000.0007.000000.000000.00000000 | BB62: 1126100068 | BC62: HO_INTRA-STATE_OTH_REC_18% | BD62: INPUT_SERVICE | BF62: Fwd Rec | BG62: Fwd - Matched | BH62: Yes | BI62: 07 | BJ62: Delhi | BK62: 07AAACC4175D1Z0DLS2627000000642 | BL62: 7.2 | BM62: 840.1 | BN62: -833 | BO62: Matched | BP62: 9155618 | BQ62: Fwd Rec | BR62: FY 2026-27 | BS62: 3
A63: Payable Invoice | B63: AP_INVOICE | C63: 107 | D63: Godfrey_Phillips_India_Limited_HO | E63: GPIL_HO_New_Delhi(Services) | H63: 07AABCG4768K1Z9 | I63: AP_INVOICES | J63: STANDARD VALIDATED TAX | K63: IA | L63: STANDARD | M63: 46126 | N63: DLS2627000000644 | O63: 9155608 | P63: 46114 | Q63: Supplier | R63: 2770 | S63: CANON INDIA PVT. LTD. | T63: OKHLA | U63: 07AAACC4175D1Z0 | V63: NOS | X63: 1 | Y63: 10 | Z63: 10 | AA63: GST_India | AB63: DLS2627000000644 | AC63: 46114 | AD63: MISCELLENS | AE63: 84439952 | AF63: Supply of TonerInk Spares along Support Services | AI63: 10 | AJ63: Normal | AK63: 18 | AL63: 0.9 | AM63: 0.9 | AN63: 0 | AO63: 0 | AP63: 0 | AQ63: 0 | AR63: 0 | AS63: 0 | AT63: 0 | AW63: 0 | AX63: 11.8 | AY63: Y | AZ63: N | BA63: 11.7100.111.234010.0000.000000.0007.000000.000000.00000000 | BB63: 1126100058 | BC63: HO_INTRA-STATE_OTH_REC_18% | BD63: INPUT_SERVICE | BF63: Fwd Rec | BG63: Fwd - Matched | BH63: Yes | BI63: 07 | BJ63: Delhi | BK63: 07AAACC4175D1Z0DLS2627000000644 | BL63: 1.8 | BM63: 1873.72 | BN63: -1872 | BO63: Matched | BP63: 9155608 | BQ63: Fwd Rec | BR63: FY 2026-27 | BS63: 4
A64: Payable Invoice | B64: AP_INVOICE | C64: 107 | D64: Godfrey_Phillips_India_Limited_HO | E64: GPIL_HO_New_Delhi(Services) | H64: 07AABCG4768K1Z9 | I64: AP_INVOICES | J64: STANDARD VALIDATED TAX | K64: IA | L64: STANDARD | M64: 46127 | N64: HRF2627000000686 | O64: 9156860 | P64: 46113 | Q64: Supplier | R64: 2770 | S64: CANON INDIA PVT. LTD. | T64: GURGAON-1A | U64: 06AAACC4175D1Z2 | V64: NOS | X64: 1 | Y64: 4365 | Z64: 4365 | AA64: GST_India | AB64: HRF2627000000686 | AC64: 46113 | AD64: BUDMINTIND | AE64: 997314 | AF64: Rental Charges For iR-ADV DX C | AI64: 4365 | AJ64: Normal | AK64: 18 | AL64: 0 | AM64: 0 | AN64: 785.7 | AO64: 0 | AP64: 0 | AQ64: 0 | AR64: 0 | AS64: 0 | AT64: 0 | AW64: 0 | AX64: 5150.7 | AY64: Y | AZ64: N | BA64: 11.7100.111.414703.2700.000000.0007.000000.000000.00000000 | BB64: 1126100089 | BC64: HO_INTER-STATE_OTH_REC_18% | BD64: INPUT_SERVICE | BF64: Fwd Rec | BG64: Fwd - Matched | BH64: Yes | BI64: 07 | BJ64: Delhi | BK64: 06AAACC4175D1Z2HRF2627000000686 | BL64: 785.7 | BM64: 785.7 | BN64: 0 | BO64: Matched | BP64: 9156860 | BQ64: Fwd Rec | BR64: FY 2026-27 | BS64: 1
A65: Payable Invoice | B65: AP_INVOICE | C65: 107 | D65: Godfrey_Phillips_India_Limited_HO | E65: GPIL_HO_New_Delhi(Services) | G65: HO New Friends Colony | H65: 07AABCG4768K1Z9 | I65: AP_INVOICES | J65: STANDARD CREATED | K65: Manual Invoice Entry | L65: STANDARD | M65: 46135 | N65: 3473455437 | O65: 9167997 | P65: 46127 | Q65: Supplier | R65: 39705 | S65: TATA TELESERVICES LIMITED | T65: NEW DELHI | U65: 07AAACT2438A1ZV | V65: NOS | X65: 1 | Y65: 31750 | Z65: 31750 | AA65: GST_India | AB65: 3473455437 | AC65: 46127 | AD65: BUDMINTIND | AE65: 998412 | AF65: TATA PRI bill for the period of 13-03-2026 to 12.04.2026– Jasola Office | AI65: 31750 | AJ65: Normal | AK65: 18 | AL65: 2857.5 | AM65: 2857.5 | AN65: 0 | AO65: 0 | AP65: 0 | AQ65: 0 | AR65: 0 | AS65: 0 | AT65: 0 | AW65: 0 | AX65: 37465 | AY65: Y | AZ65: N | BA65: 11.7100.111.420801.1010.000000.0007.000000.000000.00000000 | BB65: 1126100350 | BC65: HO_INTRA-STATE_OTH_REC_18% | BD65: INPUT_SERVICE | BF65: Fwd Rec | BG65: Fwd - Matched | BH65: Yes | BI65: 07 | BJ65: Delhi | BK65: 07AAACT2438A1ZV3473455437 | BL65: 5715 | BM65: 5715 | BN65: 0 | BO65: Matched | BP65: 9167997 | BQ65: Fwd Rec | BR65: FY 2026-27 | BS65: 1
A66: Payable Invoice | B66: AP_INVOICE | C66: 107 | D66: Godfrey_Phillips_India_Limited_HO | E66: GPIL_HO_New_Delhi(Services) | G66: HO New Friends Colony | H66: 07AABCG4768K1Z9 | I66: AP_INVOICES | J66: STANDARD CREATED | K66: Manual Invoice Entry | L66: STANDARD | M66: 46140 | N66: DFSI2600000751 | O66: 9174963 | P66: 46129 | Q66: Supplier | R66: 35671 | S66: DEUTSCHE CARS PRIVATE LIMITED | T66: Faridabad-OFF | U66: 06AAGCD4246E1ZX | V66: NOS | X66: 2717.37 | Y66: 1 | Z66: 2717.37 | AA66: GST_India | AB66: DFSI2600000751 | AC66: 46129 | AD66: BUDMINTIND | AE66: 34029099 | AF66: AIR CONDITIO | AI66: 2717.37 | AJ66: Normal | AK66: 18 | AL66: 0 | AM66: 0 | AN66: 489.13 | AO66: 0 | AP66: 0 | AQ66: 0 | AR66: 0 | AS66: 0 | AT66: 0 | AW66: 0 | AX66: 3206.5 | AY66: N | AZ66: N | BA66: 11.7100.111.414301.1000.100007.0007.000000.000000.00000000 | BB66: 1126100446 | BC66: HO_INTER-STATE_OTH_NON_REC_18% | BD66: INPUT_TDS_194C | BF66: Fwd Non Rec | BG66: Fwd - Matched | BH66: Yes | BI66: 07 | BJ66: Delhi | BK66: 06AAGCD4246E1ZXDFSI2600000751 | BL66: 489.13 | BM66: 36494.74 | BN66: -36006 | BO66: Matched | BP66: 9174963 | BQ66: Fwd Non Rec | BR66: FY 2026-27 | BS66: 36
A67: Payable Invoice | B67: AP_INVOICE | C67: 107 | D67: Godfrey_Phillips_India_Limited_HO | E67: GPIL_HO_New_Delhi(Services) | G67: HO New Friends Colony | H67: 07AABCG4768K1Z9 | I67: AP_INVOICES | J67: STANDARD CREATED | K67: Manual Invoice Entry | L67: STANDARD | M67: 46140 | N67: DFSI2600000751 | O67: 9174963 | P67: 46129 | Q67: Supplier | R67: 35671 | S67: DEUTSCHE CARS PRIVATE LIMITED | T67: Faridabad-OFF | U67: 06AAGCD4246E1ZX | V67: NOS | X67: 275 | Y67: 0.001 | Z67: 0.28 | AA67: GST_India | AB67: DFSI2600000751 | AC67: 46129 | AD67: BUDMINTIND | AE67: 998729 | AF67: JOB TIME WITHOUT ALLOWANCE FOR WHEELS | AI67: 0.28 | AJ67: Normal | AK67: 18 | AL67: 0 | AM67: 0 | AN67: 0.05 | AO67: 0 | AP67: 0 | AQ67: 0 | AR67: 0 | AS67: 0 | AT67: 0 | AW67: 0 | AX67: 0.33 | AY67: N | AZ67: N | BA67: 11.7100.111.414301.1000.100007.0007.000000.000000.00000000 | BB67: 1126100446 | BC67: HO_INTER-STATE_OTH_NON_REC_18% | BD67: INPUT_TDS_194C | BF67: Fwd Non Rec | BG67: Fwd - Matched | BH67: Yes | BI67: 07 | BJ67: Delhi | BK67: 06AAGCD4246E1ZXDFSI2600000751 | BL67: 0.05 | BM67: 36494.74 | BN67: -36495 | BO67: Matched | BP67: 9174963 | BQ67: Fwd Non Rec | BR67: FY 2026-27 | BS67: 36
A68: Payable Invoice | B68: AP_INVOICE | C68: 107 | D68: Godfrey_Phillips_India_Limited_HO | E68: GPIL_HO_New_Delhi(Services) | G68: HO New Friends Colony | H68: 07AABCG4768K1Z9 | I68: AP_INVOICES | J68: STANDARD CREATED | K68: Manual Invoice Entry | L68: STANDARD | M68: 46140 | N68: DFSI2600000751 | O68: 9174963 | P68: 46129 | Q68: Supplier | R68: 35671 | S68: DEUTSCHE CARS PRIVATE LIMITED | T68: Faridabad-OFF | U68: 06AAGCD4246E1ZX | V68: NOS | X68: 275 | Y68: 35 | Z68: 9625 | AA68: GST_India | AB68: DFSI2600000751 | AC68: 46129 | AD68: BUDMINTIND | AE68: 998729 | AF68: REMOVING AND INSTALLING INTAKE MANIFOLD | AI68: 9625 | AJ68: Normal | AK68: 18 | AL68: 0 | AM68: 0 | AN68: 1732.5 | AO68: 0 | AP68: 0 | AQ68: 0 | AR68: 0 | AS68: 0 | AT68: 0 | AW68: 0 | AX68: 11357.5 | AY68: N | AZ68: N | BA68: 11.7100.111.414301.1000.100007.0007.000000.000000.00000000 | BB68: 1126100446 | BC68: HO_INTER-STATE_OTH_NON_REC_18% | BD68: INPUT_TDS_194C | BF68: Fwd Non Rec | BG68: Fwd - Matched | BH68: Yes | BI68: 07 | BJ68: Delhi | BK68: 06AAGCD4246E1ZXDFSI2600000751 | BL68: 1732.5 | BM68: 36494.74 | BN68: -34762 | BO68: Matched | BP68: 9174963 | BQ68: Fwd Non Rec | BR68: FY 2026-27 | BS68: 36
A69: Payable Invoice | B69: AP_INVOICE | C69: 107 | D69: Godfrey_Phillips_India_Limited_HO | E69: GPIL_HO_New_Delhi(Services) | H69: 07AABCG4768K1Z9 | I69: AP_INVOICES | J69: STANDARD VALIDATED TAX | K69: IA | L69: STANDARD | M69: 46141 | N69: 104577/LIT | O69: 9177454 | P69: 45990 | Q69: Supplier | R69: 36105 | S69: RAHUL CHAUDHARY AND PARTNERS | T69: NEW DELHI | V69: NOS | X69: 3280 | Y69: 1 | Z69: 3280 | AA69: GST_India | AB69: GPI-HOC250400365 | AC69: 45990 | AE69: 998213 | AF69: Printing photocopying and other miscellaneous out of pocket expenses | AI69: 3280 | AJ69: Normal | AK69: 18 | AL69: 295.2 | AM69: 295.2 | AN69: 0 | AO69: 0 | AP69: 0 | AQ69: 0 | AR69: 0 | AS69: 0 | AT69: 0 | AW69: 0 | AX69: 3870.4 | AY69: Y | AZ69: Y | BA69: 11.7100.111.234010.0000.000000.0007.000000.000000.00000000 | BB69: 1126100459 | BC69: HO_REV_CHARGE_REC_18% | BD69: INPUT_SERVICE | BF69: RCM Rec | BG69: RCM-Not Matched | BH69: No | BI69: 07 | BJ69: Delhi | BK69: GPI-HOC250400365 | BL69: 590.4 | BM69: #N/A | BN69: #N/A | BO69: RCM | BP69: 9177454 | BQ69: RCM Rec | BR69: RCM | BS69: 6
A70: Payable Invoice | B70: AP_INVOICE | C70: 107 | D70: Godfrey_Phillips_India_Limited_HO | E70: GPIL_HO_New_Delhi(Services) | H70: 07AABCG4768K1Z9 | I70: AP_INVOICES | J70: STANDARD VALIDATED TAX | K70: IA | L70: STANDARD | M70: 46133 | N70: 741/2025-2026 | O70: 9164023 | P70: 46108 | Q70: Supplier | R70: 45456 | S70: SAGA LEGAL | T70: HEAD OFFICE | X70: 650 | Y70: 1 | Z70: 650 | AA70: GST_India | AB70: 741/2025-2026 | AC70: 46108 | AE70: 998216 | AF70: Printing Photocopying Scanning Expense. | AI70: 650 | AJ70: Normal | AK70: 18 | AL70: 58.5 | AM70: 58.5 | AN70: 0 | AO70: 0 | AP70: 0 | AQ70: 0 | AR70: 0 | AS70: 0 | AT70: 0 | AW70: 0 | AX70: 767 | AY70: Y | AZ70: Y | BA70: 11.7100.111.234010.0000.000000.0007.000000.000000.00000000 | BB70: 1125113946 | BC70: HO_REV_CHARGE_REC_18% | BD70: INPUT_SERVICE | BF70: RCM Rec | BG70: RCM-Not Matched | BH70: No | BI70: 07 | BJ70: Delhi | BK70: 741/2025-2026 | BL70: 117 | BM70: #N/A | BN70: #N/A | BO70: RCM | BP70: 9164023 | BQ70: RCM Rec | BR70: RCM | BS70: 2
A71: Payable Invoice | B71: AP_INVOICE | C71: 107 | D71: Godfrey_Phillips_India_Limited_HO | E71: GPIL_HO_New_Delhi(Services) | H71: 07AABCG4768K1Z9 | I71: AP_INVOICES | J71: STANDARD VALIDATED TAX | K71: IA | L71: STANDARD | M71: 46126 | N71: DLS2627000000354 | O71: 9155614 | P71: 46114 | Q71: Supplier | R71: 2770 | S71: CANON INDIA PVT. LTD. | T71: OKHLA | U71: 07AAACC4175D1Z0 | V71: NOS | X71: 1 | Y71: 1476.96 | Z71: 1476.96 | AA71: GST_India | AB71: DLS2627000000354 | AC71: 46114 | AD71: MISCELLENS | AE71: 84439952 | AF71: Supply of TonerInk and Spares along with Support Services | AI71: 1476.96 | AJ71: Normal | AK71: 18 | AL71: 132.93 | AM71: 132.93 | AN71: 0 | AO71: 0 | AP71: 0 | AQ71: 0 | AR71: 0 | AS71: 0 | AT71: 0 | AW71: 0 | AX71: 1742.82 | AY71: Y | AZ71: N | BA71: 11.7100.111.234010.0000.000000.0007.000000.000000.00000000 | BB71: 1126100064 | BC71: HO_INTRA-STATE_OTH_REC_18% | BD71: INPUT_SERVICE | BF71: Fwd Rec | BG71: Fwd - Matched | BH71: Yes | BI71: 07 | BJ71: Delhi | BK71: 07AAACC4175D1Z0DLS2627000000354 | BL71: 265.86 | BM71: 265.86 | BN71: 0 | BO71: Matched | BP71: 9155614 | BQ71: Fwd Rec | BR71: FY 2026-27 | BS71: 1
A72: Payable Invoice | B72: AP_INVOICE | C72: 107 | D72: Godfrey_Phillips_India_Limited_HO | E72: GPIL_HO_New_Delhi(Services) | H72: 07AABCG4768K1Z9 | I72: AP_INVOICES | J72: STANDARD VALIDATED TAX | K72: IA | L72: STANDARD | M72: 46126 | N72: DLS2627000000593 | O72: 9155613 | P72: 46114 | Q72: Supplier | R72: 2770 | S72: CANON INDIA PVT. LTD. | T72: OKHLA | U72: 07AAACC4175D1Z0 | V72: NOS | X72: 1 | Y72: 27437.85 | Z72: 27437.85 | AA72: GST_India | AB72: DLS2627000000593 | AC72: 46114 | AD72: MISCELLENS | AE72: 84439952 | AF72: Supply at-Tonerink and Spares along with Support Services | AI72: 27437.85 | AJ72: Normal | AK72: 18 | AL72: 2469.41 | AM72: 2469.41 | AN72: 0 | AO72: 0 | AP72: 0 | AQ72: 0 | AR72: 0 | AS72: 0 | AT72: 0 | AW72: 0 | AX72: 32376.67 | AY72: Y | AZ72: N | BA72: 11.7100.111.234010.0000.000000.0007.000000.000000.00000000 | BB72: 1126100063 | BC72: HO_INTRA-STATE_OTH_REC_18% | BD72: INPUT_SERVICE | BF72: Fwd Rec | BG72: Fwd - Matched | BH72: Yes | BI72: 07 | BJ72: Delhi | BK72: 07AAACC4175D1Z0DLS2627000000593 | BL72: 4938.82 | BM72: 5381.62 | BN72: -443 | BO72: Matched | BP72: 9155613 | BQ72: Fwd Rec | BR72: FY 2026-27 | BS72: 4
A73: Payable Invoice | B73: AP_INVOICE | C73: 107 | D73: Godfrey_Phillips_India_Limited_HO | E73: GPIL_HO_New_Delhi(Services) | H73: 07AABCG4768K1Z9 | I73: AP_INVOICES | J73: STANDARD VALIDATED TAX | K73: IA | L73: STANDARD | M73: 46126 | N73: DLS2627000000644 | O73: 9155608 | P73: 46114 | Q73: Supplier | R73: 2770 | S73: CANON INDIA PVT. LTD. | T73: OKHLA | U73: 07AAACC4175D1Z0 | V73: NOS | X73: 1 | Y73: 6910.2 | Z73: 6910.2 | AA73: GST_India | AB73: DLS2627000000644 | AC73: 46114 | AD73: MISCELLENS | AE73: 84439952 | AF73: Supply ofTonerAnk and Spares along with Support Services | AI73: 6910.2 | AJ73: Normal | AK73: 18 | AL73: 621.92 | AM73: 621.92 | AN73: 0 | AO73: 0 | AP73: 0 | AQ73: 0 | AR73: 0 | AS73: 0 | AT73: 0 | AW73: 0 | AX73: 8154.04 | AY73: Y | AZ73: N | BA73: 11.7100.111.234010.0000.000000.0007.000000.000000.00000000 | BB73: 1126100058 | BC73: HO_INTRA-STATE_OTH_REC_18% | BD73: INPUT_SERVICE | BF73: Fwd Rec | BG73: Fwd - Matched | BH73: Yes | BI73: 07 | BJ73: Delhi | BK73: 07AAACC4175D1Z0DLS2627000000644 | BL73: 1243.84 | BM73: 1873.72 | BN73: -630 | BO73: Matched | BP73: 9155608 | BQ73: Fwd Rec | BR73: FY 2026-27 | BS73: 4
A74: Payable Invoice | B74: AP_INVOICE | C74: 107 | D74: Godfrey_Phillips_India_Limited_HO | E74: GPIL_HO_New_Delhi(Services) | G74: HO New Friends Colony | H74: 07AABCG4768K1Z9 | I74: AP_INVOICES | J74: STANDARD CREATED | K74: IA | L74: STANDARD | M74: 46139 | N74: BDLI000511/26-27 | O74: 9173789 | P74: 46125 | Q74: Supplier | R74: 35005 | S74: SHYAM SPECTRA PVT. LTD. | T74: 9018866A | U74: 07AADCC3694E1ZP | V74: NOS | X74: 4 | Y74: 5625 | Z74: 22500 | AA74: GST_India | AB74: BDLI000511/26-27 | AC74: 46125 | AD74: BUDITMINTIND | AE74: 998422 | AF74: ARC charges for NFC 15 Mb Internet link Circuit Id 9018866 from 01-Apr-26 to 30-Jun-26 | AI74: 22500 | AJ74: Normal | AK74: 18 | AL74: 2025 | AM74: 2025 | AN74: 0 | AO74: 0 | AP74: 0 | AQ74: 0 | AR74: 0 | AS74: 0 | AT74: 0 | AW74: 0 | AX74: 26550 | AY74: Y | AZ74: N | BA74: 11.7100.111.421415.1013.000000.0007.000000.000000.00000000 | BB74: 1126100440 | BC74: HO_INTRA-STATE_OTH_REC_18% | BD74: INPUT_SERVICE | BF74: Fwd Rec | BG74: Fwd - Matched | BH74: Yes | BI74: 07 | BJ74: Delhi | BK74: 07AADCC3694E1ZPBDLI000511/26-27 | BL74: 4050 | BM74: 4050 | BN74: 0 | BO74: Matched | BP74: 9173789 | BQ74: Fwd Rec | BR74: FY 2026-27 | BS74: 1
A75: Payable Invoice | B75: AP_INVOICE | C75: 107 | D75: Godfrey_Phillips_India_Limited_HO | E75: GPIL_HO_New_Delhi(Services) | G75: HO New Friends Colony | H75: 07AABCG4768K1Z9 | I75: AP_INVOICES | J75: STANDARD CREATED | K75: Manual Invoice Entry | L75: STANDARD | M75: 46140 | N75: DFSI2600000751 | O75: 9174963 | P75: 46129 | Q75: Supplier | R75: 35671 | S75: DEUTSCHE CARS PRIVATE LIMITED | T75: Faridabad-OFF | U75: 06AAGCD4246E1ZX | V75: NOS | X75: 2721.7 | Y75: 1 | Z75: 2721.7 | AA75: GST_India | AB75: DFSI2600000751 | AC75: 46129 | AD75: BUDMINTIND | AE75: 84213100 | AF75: AIR FILTER E | AI75: 2721.7 | AJ75: Normal | AK75: 18 | AL75: 0 | AM75: 0 | AN75: 489.91 | AO75: 0 | AP75: 0 | AQ75: 0 | AR75: 0 | AS75: 0 | AT75: 0 | AW75: 0 | AX75: 3211.61 | AY75: N | AZ75: N | BA75: 11.7100.111.414301.1000.100007.0007.000000.000000.00000000 | BB75: 1126100446 | BC75: HO_INTER-STATE_OTH_NON_REC_18% | BD75: INPUT_TDS_194C | BF75: Fwd Non Rec | BG75: Fwd - Matched | BH75: Yes | BI75: 07 | BJ75: Delhi | BK75: 06AAGCD4246E1ZXDFSI2600000751 | BL75: 489.91 | BM75: 36494.74 | BN75: -36005 | BO75: Matched | BP75: 9174963 | BQ75: Fwd Non Rec | BR75: FY 2026-27 | BS75: 36
A76: Payable Invoice | B76: AP_INVOICE | C76: 107 | D76: Godfrey_Phillips_India_Limited_HO | E76: GPIL_HO_New_Delhi(Services) | G76: HO New Friends Colony | H76: 07AABCG4768K1Z9 | I76: AP_INVOICES | J76: STANDARD CREATED | K76: Manual Invoice Entry | L76: STANDARD | M76: 46140 | N76: DFSI2600000751 | O76: 9174963 | P76: 46129 | Q76: Supplier | R76: 35671 | S76: DEUTSCHE CARS PRIVATE LIMITED | T76: Faridabad-OFF | U76: 06AAGCD4246E1ZX | V76: NOS | X76: 1409.49 | Y76: 1 | Z76: 1409.49 | AA76: GST_India | AB76: DFSI2600000751 | AC76: 46129 | AD76: BUDMINTIND | AE76: 84212300 | AF76: SET OIL FILT | AI76: 1409.49 | AJ76: Normal | AK76: 18 | AL76: 0 | AM76: 0 | AN76: 253.71 | AO76: 0 | AP76: 0 | AQ76: 0 | AR76: 0 | AS76: 0 | AT76: 0 | AW76: 0 | AX76: 1663.2 | AY76: N | AZ76: N | BA76: 11.7100.111.414301.1000.100007.0007.000000.000000.00000000 | BB76: 1126100446 | BC76: HO_INTER-STATE_OTH_NON_REC_18% | BD76: INPUT_TDS_194C | BF76: Fwd Non Rec | BG76: Fwd - Matched | BH76: Yes | BI76: 07 | BJ76: Delhi | BK76: 06AAGCD4246E1ZXDFSI2600000751 | BL76: 253.71 | BM76: 36494.74 | BN76: -36241 | BO76: Matched | BP76: 9174963 | BQ76: Fwd Non Rec | BR76: FY 2026-27 | BS76: 36
A77: Payable Invoice | B77: AP_INVOICE | C77: 107 | D77: Godfrey_Phillips_India_Limited_HO | E77: GPIL_HO_New_Delhi(Services) | G77: HO New Friends Colony | H77: 07AABCG4768K1Z9 | I77: AP_INVOICES | J77: STANDARD CREATED | K77: Manual Invoice Entry | L77: STANDARD | M77: 46140 | N77: TXA26-00607 | O77: 9175014 | P77: 46129 | Q77: Supplier | R77: 15979 | S77: SPIRITED AUTO CARS (I) LTD. | T77: NEW DELHI | U77: 07AANCS0651B1ZM | V77: NOS | X77: 30.6 | Y77: 15 | Z77: 459 | AA77: GST_India | AB77: TXA26-00607 | AC77: 46129 | AD77: BUDMINTIND | AE77: 38190010 | AF77: BRAKE FLUID | AI77: 459 | AJ77: Normal | AK77: 18 | AL77: 41.31 | AM77: 41.31 | AN77: 0 | AO77: 0 | AP77: 0 | AQ77: 0 | AR77: 0 | AS77: 0 | AT77: 0 | AW77: 0 | AX77: 541.62 | AY77: N | AZ77: N | BA77: 11.7100.111.414301.1009.110908.0007.000000.000000.00000000 | BB77: 1126100447 | BC77: HO_INTRA-STATE_OTH_NON_REC_18% | BD77: INPUT_TDS_194C | BF77: Fwd Non Rec | BG77: Fwd - Matched | BH77: Yes | BI77: 07 | BJ77: Delhi | BK77: 07AANCS0651B1ZMTXA26-00607 | BL77: 82.62 | BM77: 2435.38 | BN77: -2353 | BO77: Matched | BP77: 9175014 | BQ77: Fwd Non Rec | BR77: FY 2026-27 | BS77: 18
A78: Payable Invoice | B78: AP_INVOICE | C78: 107 | D78: Godfrey_Phillips_India_Limited_HO | E78: GPIL_HO_New_Delhi(Services) | G78: HO New Friends Colony | H78: 07AABCG4768K1Z9 | I78: AP_INVOICES | J78: STANDARD VALIDATED TAX | K78: Manual Invoice Entry | L78: STANDARD | M78: 46140 | N78: 446 | O78: 9175031 | P78: 46129 | Q78: Supplier | R78: 18837 | S78: RNT ENTERPRISES | T78: BADARPUR | U78: 07AELPT6048J2ZV | V78: JOB | X78: 11000 | Y78: 1 | Z78: 11000 | AA78: GST_India | AB78: 446 | AC78: 46129 | AD78: BUDMINTIND | AE78: 995400 | AF78: Misc Civil Work at Jasola Office (3rd Floor, 4th Floor, 5th Floor & Basement 2) | AI78: 11000 | AJ78: Normal | AK78: 18 | AL78: 990 | AM78: 990 | AN78: 0 | AO78: 0 | AP78: 0 | AQ78: 0 | AR78: 0 | AS78: 0 | AT78: 0 | AW78: 0 | AX78: 12980 | AY78: Y | AZ78: N | BA78: 11.7100.111.413701.1010.000000.0007.000000.000000.00000000 | BB78: 1126100448 | BC78: HO_INTRA-STATE_OTH_REC_18% | BD78: INPUT_SERVICE | BF78: Fwd Rec | BG78: Fwd - Matched | BH78: No | BI78: 07 | BJ78: Delhi | BK78: 07AELPT6048J2ZV446 | BL78: 1980 | BM78: 1980 | BN78: 0 | BO78: Matched | BP78: 9175031 | BQ78: Fwd Rec | BR78: FY 2026-27 | BS78: 1
A79: Payable Invoice | B79: AP_INVOICE | C79: 107 | D79: Godfrey_Phillips_India_Limited_HO | E79: GPIL_HO_New_Delhi(Services) | H79: 07AABCG4768K1Z9 | I79: AP_INVOICES | J79: STANDARD VALIDATED TAX | K79: IA | L79: STANDARD | M79: 46133 | N79: 107/2026-27 | O79: 9164653 | P79: 46127 | Q79: Supplier | R79: 39845 | S79: GOEL ENTERPRISES BHANGEL | T79: NEW DELHI-OFF | U79: 09ACTPG0935H1ZE | V79: NOS | X79: 1 | Y79: 4457.16 | Z79: 4457.16 | AA79: GST_India | AB79: 107/2026-27 | AC79: 46127 | AD79: BUDMINTIND | AE79: 17049090 | AF79: FUNDA PAAN(675GM) | AI79: 4457.16 | AJ79: Normal | AK79: 5 | AL79: 0 | AM79: 0 | AN79: 222.86 | AO79: 0 | AP79: 0 | AQ79: 0 | AR79: 0 | AS79: 0 | AT79: 0 | AW79: 0 | AX79: 4680.02 | AY79: N | AZ79: N | BA79: 11.7100.111.412401.1010.000000.0007.000000.000000.00000000 | BB79: 1126100308 | BC79: HO_INTER-STATE_OTH_NON_REC_5% | BD79: INPUT | BF79: Fwd Non Rec | BG79: Fwd - Matched | BH79: Yes | BI79: 07 | BJ79: Delhi | BK79: 09ACTPG0935H1ZE107/2026-27 | BL79: 222.86 | BM79: 1632.71 | BN79: -1410 | BO79: Matched | BP79: 9164653 | BQ79: Fwd Non Rec | BR79: FY 2026-27 | BS79: 3
A80: Payable Invoice | B80: AP_INVOICE | C80: 107 | D80: Godfrey_Phillips_India_Limited_HO | E80: GPIL_HO_New_Delhi(Services) | G80: HO New Friends Colony | H80: 07AABCG4768K1Z9 | I80: AP_INVOICES | J80: STANDARD CREATED | K80: Manual Invoice Entry | L80: STANDARD | M80: 46127 | N80: DFSI2600000412 | O80: 9158398 | P80: 46090 | Q80: Supplier | R80: 35671 | S80: DEUTSCHE CARS PRIVATE LIMITED | T80: Faridabad-OFF | U80: 06AAGCD4246E1ZX | V80: NOS | X80: 275 | Y80: 14 | Z80: 3850 | AA80: GST_India | AB80: DFSI2600000412 | AC80: 46121 | AD80: BUDMINTIND | AE80: 998729 | AF80: HEADLIGHT RESTORATION | AI80: 3850 | AJ80: Normal | AK80: 18 | AL80: 0 | AM80: 0 | AN80: 693 | AO80: 0 | AP80: 0 | AQ80: 0 | AR80: 0 | AS80: 0 | AT80: 0 | AW80: 0 | AX80: 4543 | AY80: N | AZ80: N | BA80: 11.7100.111.414301.1011.111636.0007.000000.000000.00000000 | BB80: 1126100105 | BC80: HO_INTER-STATE_OTH_NON_REC_18% | BD80: INPUT_TDS_194C | BF80: Fwd Non Rec | BG80: Fwd - Matched | BH80: Yes | BI80: 07 | BJ80: Delhi | BK80: 06AAGCD4246E1ZXDFSI2600000412 | BL80: 693 | BM80: 38182.88 | BN80: -37490 | BO80: Matched | BP80: 9158398 | BQ80: Fwd Non Rec | BR80: FY 2026-27 | BS80: 37
A81: Payable Invoice | B81: AP_INVOICE | C81: 107 | D81: Godfrey_Phillips_India_Limited_HO | E81: GPIL_HO_New_Delhi(Services) | G81: HO New Friends Colony | H81: 07AABCG4768K1Z9 | I81: AP_INVOICES | J81: STANDARD CREATED | K81: Manual Invoice Entry | L81: STANDARD | M81: 46127 | N81: DFSI2600000412 | O81: 9158398 | P81: 46090 | Q81: Supplier | R81: 35671 | S81: DEUTSCHE CARS PRIVATE LIMITED | T81: Faridabad-OFF | U81: 06AAGCD4246E1ZX | V81: NOS | X81: 275 | Y81: 2 | Z81: 550 | AA81: GST_India | AB81: DFSI2600000412 | AC81: 46121 | AD81: BUDMINTIND | AE81: 998729 | AF81: SERVICE AIR FILTER ELEMENT | AI81: 550 | AJ81: Normal | AK81: 18 | AL81: 0 | AM81: 0 | AN81: 99 | AO81: 0 | AP81: 0 | AQ81: 0 | AR81: 0 | AS81: 0 | AT81: 0 | AW81: 0 | AX81: 649 | AY81: N | AZ81: N | BA81: 11.7100.111.414301.1011.111636.0007.000000.000000.00000000 | BB81: 1126100105 | BC81: HO_INTER-STATE_OTH_NON_REC_18% | BD81: INPUT_TDS_194C | BF81: Fwd Non Rec | BG81: Fwd - Matched | BH81: Yes | BI81: 07 | BJ81: Delhi | BK81: 06AAGCD4246E1ZXDFSI2600000412 | BL81: 99 | BM81: 38182.88 | BN81: -38084 | BO81: Matched | BP81: 9158398 | BQ81: Fwd Non Rec | BR81: FY 2026-27 | BS81: 37
A82: Payable Invoice | B82: AP_INVOICE | C82: 107 | D82: Godfrey_Phillips_India_Limited_HO | E82: GPIL_HO_New_Delhi(Services) | G82: HO New Friends Colony | H82: 07AABCG4768K1Z9 | I82: AP_INVOICES | J82: STANDARD CREATED | K82: Manual Invoice Entry | L82: STANDARD | M82: 46140 | N82: DFSI2600000751 | O82: 9174963 | P82: 46129 | Q82: Supplier | R82: 35671 | S82: DEUTSCHE CARS PRIVATE LIMITED | T82: Faridabad-OFF | U82: 06AAGCD4246E1ZX | V82: NOS | X82: 275 | Y82: 24 | Z82: 6600 | AA82: GST_India | AB82: DFSI2600000751 | AC82: 46129 | AD82: BUDMINTIND | AE82: 998729 | AF82: AIR CONDITIONING | AI82: 6600 | AJ82: Normal | AK82: 18 | AL82: 0 | AM82: 0 | AN82: 1188 | AO82: 0 | AP82: 0 | AQ82: 0 | AR82: 0 | AS82: 0 | AT82: 0 | AW82: 0 | AX82: 7788 | AY82: N | AZ82: N | BA82: 11.7100.111.414301.1000.100007.0007.000000.000000.00000000 | BB82: 1126100446 | BC82: HO_INTER-STATE_OTH_NON_REC_18% | BD82: INPUT_TDS_194C | BF82: Fwd Non Rec | BG82: Fwd - Matched | BH82: Yes | BI82: 07 | BJ82: Delhi | BK82: 06AAGCD4246E1ZXDFSI2600000751 | BL82: 1188 | BM82: 36494.74 | BN82: -35307 | BO82: Matched | BP82: 9174963 | BQ82: Fwd Non Rec | BR82: FY 2026-27 | BS82: 36
A83: Payable Invoice | B83: AP_INVOICE | C83: 107 | D83: Godfrey_Phillips_India_Limited_HO | E83: GPIL_HO_New_Delhi(Services) | G83: HO New Friends Colony | H83: 07AABCG4768K1Z9 | I83: AP_INVOICES | J83: STANDARD CREATED | K83: Manual Invoice Entry | L83: STANDARD | M83: 46140 | N83: DFSI2600000751 | O83: 9174963 | P83: 46129 | Q83: Supplier | R83: 35671 | S83: DEUTSCHE CARS PRIVATE LIMITED | T83: Faridabad-OFF | U83: 06AAGCD4246E1ZX | V83: NOS | X83: 7231.78 | Y83: 2 | Z83: 14463.56 | AA83: GST_India | AB83: DFSI2600000751 | AC83: 46129 | AD83: BUDMINTIND | AE83: 34053000 | AF83: BMW CAR CARE | AI83: 14463.56 | AJ83: Normal | AK83: 18 | AL83: 0 | AM83: 0 | AN83: 2603.44 | AO83: 0 | AP83: 0 | AQ83: 0 | AR83: 0 | AS83: 0 | AT83: 0 | AW83: 0 | AX83: 17067 | AY83: N | AZ83: N | BA83: 11.7100.111.414301.1000.100007.0007.000000.000000.00000000 | BB83: 1126100446 | BC83: HO_INTER-STATE_OTH_NON_REC_18% | BD83: INPUT_TDS_194C | BF83: Fwd Non Rec | BG83: Fwd - Matched | BH83: Yes | BI83: 07 | BJ83: Delhi | BK83: 06AAGCD4246E1ZXDFSI2600000751 | BL83: 2603.44 | BM83: 36494.74 | BN83: -33891 | BO83: Matched | BP83: 9174963 | BQ83: Fwd Non Rec | BR83: FY 2026-27 | BS83: 36
A84: Payable Invoice | B84: AP_INVOICE | C84: 107 | D84: Godfrey_Phillips_India_Limited_HO | E84: GPIL_HO_New_Delhi(Services) | G84: HO New Friends Colony | H84: 07AABCG4768K1Z9 | I84: AP_INVOICES | J84: STANDARD CREATED | K84: Manual Invoice Entry | L84: STANDARD | M84: 46140 | N84: TXA26-00607 | O84: 9175014 | P84: 46129 | Q84: Supplier | R84: 15979 | S84: SPIRITED AUTO CARS (I) LTD. | T84: NEW DELHI | U84: 07AANCS0651B1ZM | V84: NOS | X84: 561.6 | Y84: 1 | Z84: 561.6 | AA84: GST_India | AB84: TXA26-00607 | AC84: 46129 | AD84: BUDMINTIND | AE84: 998729 | AF84: TGLOSS PLASTIC CARE | AI84: 561.6 | AJ84: Normal | AK84: 18 | AL84: 50.54 | AM84: 50.54 | AN84: 0 | AO84: 0 | AP84: 0 | AQ84: 0 | AR84: 0 | AS84: 0 | AT84: 0 | AW84: 0 | AX84: 662.68 | AY84: N | AZ84: N | BA84: 11.7100.111.414301.1009.110908.0007.000000.000000.00000000 | BB84: 1126100447 | BC84: HO_INTRA-STATE_OTH_NON_REC_18% | BD84: INPUT_TDS_194C | BF84: Fwd Non Rec | BG84: Fwd - Matched | BH84: Yes | BI84: 07 | BJ84: Delhi | BK84: 07AANCS0651B1ZMTXA26-00607 | BL84: 101.08 | BM84: 2435.38 | BN84: -2334 | BO84: Matched | BP84: 9175014 | BQ84: Fwd Non Rec | BR84: FY 2026-27 | BS84: 18
A85: Payable Invoice | B85: AP_INVOICE | C85: 107 | D85: Godfrey_Phillips_India_Limited_HO | E85: GPIL_HO_New_Delhi(Services) | H85: 07AABCG4768K1Z9 | I85: AP_INVOICES | J85: STANDARD VALIDATED TAX | K85: IA | L85: STANDARD | M85: 46141 | N85: 104577/LIT | O85: 9177454 | P85: 45990 | Q85: Supplier | R85: 36105 | S85: RAHUL CHAUDHARY AND PARTNERS | T85: NEW DELHI | V85: NOS | X85: 12500 | Y85: 1 | Z85: 12500 | AA85: GST_India | AB85: GPI-HOC250400365 | AC85: 45990 | AE85: 998213 | AF85: for providing a short opinion on the Order passed in Pelican Tobacco case vide our email dated November 28 2025 | AI85: 12500 | AJ85: Normal | AK85: 18 | AL85: 1125 | AM85: 1125 | AN85: 0 | AO85: 0 | AP85: 0 | AQ85: 0 | AR85: 0 | AS85: 0 | AT85: 0 | AW85: 0 | AX85: 14750 | AY85: Y | AZ85: Y | BA85: 11.7100.111.234010.0000.000000.0007.000000.000000.00000000 | BB85: 1126100459 | BC85: HO_REV_CHARGE_REC_18% | BD85: INPUT_SERVICE | BF85: RCM Rec | BG85: RCM-Not Matched | BH85: No | BI85: 07 | BJ85: Delhi | BK85: GPI-HOC250400365 | BL85: 2250 | BM85: #N/A | BN85: #N/A | BO85: RCM | BP85: 9177454 | BQ85: RCM Rec | BR85: RCM | BS85: 6
A86: Payable Invoice | B86: AP_INVOICE | C86: 107 | D86: Godfrey_Phillips_India_Limited_HO | E86: GPIL_HO_New_Delhi(Services) | H86: 07AABCG4768K1Z9 | I86: AP_INVOICES | J86: STANDARD VALIDATED TAX | K86: IA | L86: STANDARD | M86: 46127 | N86: HRF2627000000687 | O86: 9156862 | P86: 46113 | Q86: Supplier | R86: 2770 | S86: CANON INDIA PVT. LTD. | T86: GURGAON-1A | U86: 06AAACC4175D1Z2 | V86: NOS | X86: 1 | Y86: 4365 | Z86: 4365 | AA86: GST_India | AB86: HRF2627000000687 | AC86: 46113 | AD86: BUDMINTIND | AE86: 997314 | AF86: Rental Charges For iR-ADV C | AI86: 4365 | AJ86: Normal | AK86: 18 | AL86: 0 | AM86: 0 | AN86: 785.7 | AO86: 0 | AP86: 0 | AQ86: 0 | AR86: 0 | AS86: 0 | AT86: 0 | AW86: 0 | AX86: 5150.7 | AY86: Y | AZ86: N | BA86: 11.7100.111.414703.1006.000000.0007.000000.000000.00000000 | BB86: 1126100091 | BC86: HO_INTER-STATE_OTH_REC_18% | BD86: INPUT_SERVICE | BF86: Fwd Rec | BG86: Fwd - Matched | BH86: Yes | BI86: 07 | BJ86: Delhi | BK86: 06AAACC4175D1Z2HRF2627000000687 | BL86: 785.7 | BM86: 785.7 | BN86: 0 | BO86: Matched | BP86: 9156862 | BQ86: Fwd Rec | BR86: FY 2026-27 | BS86: 1
A87: Payable Invoice | B87: AP_INVOICE | C87: 107 | D87: Godfrey_Phillips_India_Limited_HO | E87: GPIL_HO_New_Delhi(Services) | H87: 07AABCG4768K1Z9 | I87: AP_INVOICES | J87: STANDARD VALIDATED TAX | K87: Manual Invoice Entry | L87: DEBIT | M87: 46142 | N87: DE25C00000031991 | O87: 9178799 | P87: 46095 | Q87: Supplier | R87: 11570 | S87: TATA AIG GENERAL INSURANCE COMPANY LIMITED | T87: DELHI | U87: 07AABCT3518Q1ZY | X87: 0 | Y87: 0 | Z87: -262.9 | AA87: GST_India | AB87: DE25C00000031991 | AC87: 46095 | AE87: 9971 | AF87: GPA Policy Deletion of members M/O Mar 2026 | AI87: -262.9 | AJ87: Normal | AK87: 18 | AL87: -23.66 | AM87: -23.66 | AN87: 0 | AO87: 0 | AP87: 0 | AQ87: 0 | AR87: 0 | AS87: 0 | AT87: 0 | AW87: 0 | AX87: -310.22 | AY87: N | AZ87: N | BA87: 11.7100.111.415802.1008.000000.0007.000000.000000.00000000 | BB87: 1126100480 | BC87: HO_INTRA-STATE_OTH_NON_REC_18% | BD87: INPUT_SERVICE | BF87: Fwd Non Rec | BG87: Fwd - Matched | BH87: No | BI87: 07 | BJ87: Delhi | BK87: 07AABCT3518Q1ZYDE25C00000031991 | BL87: -47.32 | BM87: -47.32 | BN87: 0 | BO87: Matched | BP87: 9178799 | BQ87: Fwd Non Rec | BR87: FY 2025-26 | BS87: 1
A88: Payable Invoice | B88: AP_INVOICE | C88: 107 | D88: Godfrey_Phillips_India_Limited_HO | E88: GPIL_HO_New_Delhi(Services) | H88: 07AABCG4768K1Z9 | I88: AP_INVOICES | J88: STANDARD VALIDATED TAX | K88: Manual Invoice Entry | L88: STANDARD | M88: 46141 | N88: CI1001100173 | O88: 9177547 | P88: 46121 | Q88: Supplier | R88: 3734 | S88: THE OBEROI | T88: NEW DELHI | U88: 07AAACE6898B4ZH | X88: 0 | Y88: 0 | Z88: 0 | AA88: GST_India | AB88: CI1001100173 | AC88: 46121 | AE88: 998599 | AF88: BUSINESS MEAL CHARU MODI | AI88: 0 | AJ88: Normal | AK88: 18 | AL88: 1540.8 | AM88: 1540.8 | AN88: 0 | AO88: 0 | AP88: 0 | AQ88: 0 | AR88: 0 | AS88: 0 | AT88: 0 | AW88: 0 | AX88: 3081.6 | AY88: N | AZ88: N | BA88: 11.7100.111.420201.1000.100007.0007.000000.000000.00000000 | BB88: 1126100467 | BC88: HO_INTRA-STATE_OTH_NON_REC_18% | BD88: INPUT_SERVICE | BF88: Fwd Non Rec | BG88: Fwd - Matched | BH88: Yes | BI88: 07 | BJ88: Delhi | BK88: 07AAACE6898B4ZHCI1001100173 | BL88: 3081.6 | BM88: 3081.6 | BN88: 0 | BO88: Matched | BP88: 9177547 | BQ88: Fwd Non Rec | BR88: FY 2026-27 | BS88: 1
A89: Payable Invoice | B89: AP_INVOICE | C89: 107 | D89: Godfrey_Phillips_India_Limited_HO | E89: GPIL_HO_New_Delhi(Services) | H89: 07AABCG4768K1Z9 | I89: AP_INVOICES | J89: STANDARD VALIDATED TAX | K89: Manual Invoice Entry | L89: STANDARD | M89: 46126 | N89: RENT-APR26 | O89: 9151216 | P89: 46113 | Q89: Supplier | R89: 29291 | S89: SHRI AMRIT LAL CHOPRA | T89: DELHI | X89: 0 | Y89: 0 | Z89: 169312 | AA89: GST_India | AB89: GPI-HOC260400001 | AC89: 46113 | AE89: 997211 | AF89: NFC, DELHI GUEST HOUSE RENT FOR APRIL 2026 | AI89: 169312 | AJ89: Normal | AK89: 18 | AL89: 15238.08 | AM89: 15238.08 | AN89: 0 | AO89: 0 | AP89: 0 | AQ89: 0 | AR89: 0 | AS89: 0 | AT89: 0 | AW89: 0 | AX89: 199788.16 | AY89: Y | AZ89: Y | BA89: 11.7100.111.423705.1010.000000.0007.000000.000000.00000000 | BB89: 1126100053 | BC89: HO_REV_CHARGE_REC_18% | BD89: INPUT_SERVICE | BF89: RCM Rec | BG89: RCM-Not Matched | BH89: No | BI89: 07 | BJ89: Delhi | BK89: GPI-HOC260400001 | BL89: 30476.16 | BM89: #N/A | BN89: #N/A | BO89: RCM | BP89: 9151216 | BQ89: RCM Rec | BR89: RCM | BS89: 1
A90: Payable Invoice | B90: AP_INVOICE | C90: 107 | D90: Godfrey_Phillips_India_Limited_HO | E90: GPIL_HO_New_Delhi(Services) | G90: HO New Friends Colony | H90: 07AABCG4768K1Z9 | I90: AP_INVOICES | J90: STANDARD CREATED | K90: Manual Invoice Entry | L90: STANDARD | M90: 46127 | N90: DFSI2600000412 | O90: 9158398 | P90: 46090 | Q90: Supplier | R90: 35671 | S90: DEUTSCHE CARS PRIVATE LIMITED | T90: Faridabad-OFF | U90: 06AAGCD4246E1ZX | V90: NOS | X90: 253.81 | Y90: 2 | Z90: 507.62 | AA90: GST_India | AB90: DFSI2600000412 | AC90: 46121 | AD90: BUDMINTIND | AE90: 28539010 | AF90: DESTILLED WA | AI90: 507.62 | AJ90: Normal | AK90: 18 | AL90: 0 | AM90: 0 | AN90: 91.37 | AO90: 0 | AP90: 0 | AQ90: 0 | AR90: 0 | AS90: 0 | AT90: 0 | AW90: 0 | AX90: 598.99 | AY90: N | AZ90: N | BA90: 11.7100.111.414301.1011.111636.0007.000000.000000.00000000 | BB90: 1126100105 | BC90: HO_INTER-STATE_OTH_NON_REC_18% | BD90: INPUT_TDS_194C | BF90: Fwd Non Rec | BG90: Fwd - Matched | BH90: Yes | BI90: 07 | BJ90: Delhi | BK90: 06AAGCD4246E1ZXDFSI2600000412 | BL90: 91.37 | BM90: 38182.88 | BN90: -38092 | BO90: Matched | BP90: 9158398 | BQ90: Fwd Non Rec | BR90: FY 2026-27 | BS90: 37
A91: Payable Invoice | B91: AP_INVOICE | C91: 107 | D91: Godfrey_Phillips_India_Limited_HO | E91: GPIL_HO_New_Delhi(Services) | H91: 07AABCG4768K1Z9 | I91: AP_INVOICES | J91: STANDARD VALIDATED TAX | K91: CONVERSION | L91: STANDARD | M91: 46133 | N91: HF2707I000134626 | O91: 9164380 | P91: 46115 | Q91: Supplier | R91: 6262 | S91: BHARTI AIRTEL LIMITED | T91: HO | U91: 07AAACB2894G1ZP | V91: NOS | X91: 1 | Y91: 399 | Z91: 399 | AA91: GST_India | AB91: HF2707I000134626 | AC91: 46115 | AD91: MISCELLENS | AE91: 998412 | AF91: GPI JASOLA OFFICE AIRTEL - LANDLINE TELEPHONE EXPENSES FOR THE MONTH OF March-2026 - - ADMN | AI91: 399 | AJ91: Normal | AK91: 18 | AL91: 35.91 | AM91: 35.91 | AN91: 0 | AO91: 0 | AP91: 0 | AQ91: 0 | AR91: 0 | AS91: 0 | AT91: 0 | AW91: 0 | AX91: 470.82 | AY91: Y | AZ91: N | BA91: 11.7100.111.420801.1010.000000.0007.000000.000000.00000000 | BB91: 1126100276 | BC91: HO_INTRA-STATE_OTH_REC_18% | BD91: INPUT_SERVICE | BF91: Fwd Rec | BG91: Fwd - Matched | BH91: Yes | BI91: 07 | BJ91: Delhi | BK91: 07AAACB2894G1ZPHF2707I000134626 | BL91: 71.82 | BM91: 71.82 | BN91: 0 | BO91: Matched | BP91: 9164380 | BQ91: Fwd Rec | BR91: FY 2026-27 | BS91: 1
A92: Payable Invoice | B92: AP_INVOICE | C92: 107 | D92: Godfrey_Phillips_India_Limited_HO | E92: GPIL_HO_New_Delhi(Services) | H92: 07AABCG4768K1Z9 | I92: AP_INVOICES | J92: STANDARD VALIDATED TAX | K92: IA | L92: STANDARD | M92: 46141 | N92: 46082 | O92: 9178114 | P92: 46127 | Q92: Supplier | R92: 5093 | S92: ANS COMPUTERS AND PERIPHERALS | T92: DELHI | U92: 07ACBPV7574P1ZN | V92: NOS | X92: 1 | Y92: 4750 | Z92: 4750 | AA92: GST_India | AB92: 3 | AC92: 46127 | AD92: BUDITMINTIND | AE92: 8536 | AF92: HEADPHONE HP USB H120 | AI92: 4750 | AJ92: Normal | AK92: 18 | AL92: 427.5 | AM92: 427.5 | AN92: 0 | AO92: 0 | AP92: 0 | AQ92: 0 | AR92: 0 | AS92: 0 | AT92: 0 | AW92: 0 | AX92: 5605 | AY92: Y | AZ92: N | BA92: 11.7100.111.414701.1013.000000.0007.000000.000000.00000000 | BB92: 1126100466 | BC92: HO_INTRA-STATE_OTH_REC_18% | BD92: INPUT | BF92: Fwd Rec | BG92: Fwd - Matched | BH92: No | BI92: 07 | BJ92: Delhi | BK92: 07ACBPV7574P1ZN3 | BL92: 855 | BM92: 1584 | BN92: -729 | BO92: Matched | BP92: 9178114 | BQ92: Fwd Rec | BR92: FY 2026-27 | BS92: 3
A93: Payable Invoice | B93: AP_INVOICE | C93: 107 | D93: Godfrey_Phillips_India_Limited_HO | E93: GPIL_HO_New_Delhi(Services) | H93: 07AABCG4768K1Z9 | I93: AP_INVOICES | J93: STANDARD VALIDATED TAX | K93: IA | L93: STANDARD | M93: 46133 | N93: 737/2025-2026 | O93: 9164021 | P93: 46108 | Q93: Supplier | R93: 45456 | S93: SAGA LEGAL | T93: HEAD OFFICE | X93: 0 | Y93: 0 | Z93: 180 | AA93: GST_India | AB93: 737/2025-2026 | AC93: 46108 | AE93: 998216 | AF93: Girish Sharma Vs. GPIL -CS DJ No. 11912-2016- Saket District Courts New Delhi - Professional fee towards drafting and filing of restoration application for Counter Claim drafting and filing of restoration application for condonation of de | AI93: 180 | AJ93: Normal | AK93: 18 | AL93: 16.2 | AM93: 16.2 | AN93: 0 | AO93: 0 | AP93: 0 | AQ93: 0 | AR93: 0 | AS93: 0 | AT93: 0 | AW93: 0 | AX93: 212.4 | AY93: Y | AZ93: Y | BA93: 11.7100.111.234010.0000.000000.0007.000000.000000.00000000 | BB93: 1125113944 | BC93: HO_REV_CHARGE_REC_18% | BD93: INPUT_SERVICE | BF93: RCM Rec | BG93: RCM-Not Matched | BH93: No | BI93: 07 | BJ93: Delhi | BK93: 737/2025-2026 | BL93: 32.4 | BM93: #N/A | BN93: #N/A | BO93: RCM | BP93: 9164021 | BQ93: RCM Rec | BR93: RCM | BS93: 5
A94: Payable Invoice | B94: AP_INVOICE | C94: 107 | D94: Godfrey_Phillips_India_Limited_HO | E94: GPIL_HO_New_Delhi(Services) | H94: 07AABCG4768K1Z9 | I94: AP_INVOICES | J94: STANDARD VALIDATED TAX | K94: IA | L94: STANDARD | M94: 46133 | N94: 738/2025-2026 | O94: 9164022 | P94: 46108 | Q94: Supplier | R94: 45456 | S94: SAGA LEGAL | T94: HEAD OFFICE | X94: 1500 | Y94: 1 | Z94: 1500 | AA94: GST_India | AB94: 738/2025-2026 | AC94: 46108 | AE94: 998216 | AF94: 10 Clerkage | AI94: 1500 | AJ94: Normal | AK94: 18 | AL94: 135 | AM94: 135 | AN94: 0 | AO94: 0 | AP94: 0 | AQ94: 0 | AR94: 0 | AS94: 0 | AT94: 0 | AW94: 0 | AX94: 1770 | AY94: Y | AZ94: Y | BA94: 11.7100.111.234010.0000.000000.0007.000000.000000.00000000 | BB94: 1125113945 | BC94: HO_REV_CHARGE_REC_18% | BD94: INPUT_SERVICE | BF94: RCM Rec | BG94: RCM-Not Matched | BH94: No | BI94: 07 | BJ94: Delhi | BK94: 738/2025-2026 | BL94: 270 | BM94: #N/A | BN94: #N/A | BO94: RCM | BP94: 9164022 | BQ94: RCM Rec | BR94: RCM | BS94: 3
A95: Payable Invoice | B95: AP_INVOICE | C95: 107 | D95: Godfrey_Phillips_India_Limited_HO | E95: GPIL_HO_New_Delhi(Services) | H95: 07AABCG4768K1Z9 | I95: AP_INVOICES | J95: STANDARD VALIDATED TAX | K95: IA | L95: STANDARD | M95: 46125 | N95: AVZ/272/2025-26 | O95: 9151135 | P95: 46112 | Q95: Supplier | R95: 7826 | S95: A AND V ZIPPERS PVT.LTD. | T95: NEW DELHI | U95: 07AADCA3655R1Z7 | V95: NOS | X95: 1 | Y95: 328728 | Z95: 328728 | AA95: GST_India | AB95: AVZ/272/2025-26 | AC95: 46112 | AD95: MISCELLENS | AE95: 998515 | AF95: PAYROLL STAFFING SERVICE | AI95: 328728 | AJ95: Normal | AK95: 18 | AL95: 29585.52 | AM95: 29585.52 | AN95: 0 | AO95: 0 | AP95: 0 | AQ95: 0 | AR95: 0 | AS95: 0 | AT95: 0 | AW95: 0 | AX95: 387899.04 | AY95: Y | AZ95: N | BA95: 11.7100.111.420301.1010.100007.0007.000000.000000.00000000 | BB95: 1126100025 | BC95: HO_INTRA-STATE_OTH_REC_18% | BD95: INPUT_SERVICE | BF95: Fwd Rec | BG95: Fwd - Matched | BH95: Yes | BI95: 07 | BJ95: Delhi | BK95: 07AADCA3655R1Z7AVZ/272/2025-26 | BL95: 59171.04 | BM95: 59171.04 | BN95: 0 | BO95: Matched | BP95: 9151135 | BQ95: Fwd Rec | BR95: FY 2025-26 | BS95: 1
A96: Payable Invoice | B96: AP_INVOICE | C96: 107 | D96: Godfrey_Phillips_India_Limited_HO | E96: GPIL_HO_New_Delhi(Services) | H96: 07AABCG4768K1Z9 | I96: AP_INVOICES | J96: STANDARD VALIDATED TAX | K96: IA | L96: STANDARD | M96: 46126 | N96: DLS2627000000120 | O96: 9155611 | P96: 46114 | Q96: Supplier | R96: 2770 | S96: CANON INDIA PVT. LTD. | T96: OKHLA | U96: 07AAACC4175D1Z0 | V96: NOS | X96: 1 | Y96: 1817 | Z96: 1817 | AA96: GST_India | AB96: DLS2627000000120 | AC96: 46114 | AD96: MISCELLENS | AE96: 84439952 | AF96: Supply of TonerInK and Spares along with Support Services | AI96: 1817 | AJ96: Normal | AK96: 18 | AL96: 163.53 | AM96: 163.53 | AN96: 0 | AO96: 0 | AP96: 0 | AQ96: 0 | AR96: 0 | AS96: 0 | AT96: 0 | AW96: 0 | AX96: 2144.06 | AY96: Y | AZ96: N | BA96: 11.7100.111.234010.0000.000000.0007.000000.000000.00000000 | BB96: 1126100061 | BC96: HO_INTRA-STATE_OTH_REC_18% | BD96: INPUT_SERVICE | BF96: Fwd Rec | BG96: Fwd - Matched | BH96: Yes | BI96: 07 | BJ96: Delhi | BK96: 07AAACC4175D1Z0DLS2627000000120 | BL96: 327.06 | BM96: 327.06 | BN96: 0 | BO96: Matched | BP96: 9155611 | BQ96: Fwd Rec | BR96: FY 2026-27 | BS96: 1
A97: Payable Invoice | B97: AP_INVOICE | C97: 107 | D97: Godfrey_Phillips_India_Limited_HO | E97: GPIL_HO_New_Delhi(Services) | H97: 07AABCG4768K1Z9 | I97: AP_INVOICES | J97: STANDARD VALIDATED TAX | K97: IA | L97: STANDARD | M97: 46142 | N97: GST/DL/2627/021 | O97: 9178273 | P97: 46129 | Q97: Supplier | R97: 38296 | S97: LGA TECHNOLOGY PRIVATE LIMITED | T97: NEW DELHI | U97: 07AADCL9190Q1ZO | V97: NOS | X97: 1 | Y97: 1461.87 | Z97: 1461.87 | AA97: GST_India | AB97: GST/DL/2627/021 | AC97: 46129 | AD97: BUDITMINTIND | AE97: 84733099 | AF97: LCARE CHILLMATE LAPTOP STAND ( LOSPCM6130 ) LB38862135 LB3886234 LB690842500 | AI97: 1461.87 | AJ97: Normal | AK97: 18 | AL97: 131.57 | AM97: 131.57 | AN97: 0 | AO97: 0 | AP97: 0 | AQ97: 0 | AR97: 0 | AS97: 0 | AT97: 0 | AW97: 0 | AX97: 1725.01 | AY97: Y | AZ97: N | BA97: 11.7100.111.414701.1013.000000.0007.000000.000000.00000000 | BB97: 1126100490 | BC97: HO_INTRA-STATE_OTH_REC_18% | BD97: INPUT | BF97: Fwd Rec | BG97: Fwd - Matched | BH97: No | BI97: 07 | BJ97: Delhi | BK97: 07AADCL9190Q1ZOGST/DL/2627/021 | BL97: 263.14 | BM97: 665.86 | BN97: -403 | BO97: Matched | BP97: 9178273 | BQ97: Fwd Rec | BR97: FY 2026-27 | BS97: 2
A98: Payable Invoice | B98: AP_INVOICE | C98: 107 | D98: Godfrey_Phillips_India_Limited_HO | E98: GPIL_HO_New_Delhi(Services) | H98: 07AABCG4768K1Z9 | I98: AP_INVOICES | J98: STANDARD VALIDATED TAX | K98: IA | L98: STANDARD | M98: 46127 | N98: HRF2627000000684 | O98: 9156863 | P98: 46113 | Q98: Supplier | R98: 2770 | S98: CANON INDIA PVT. LTD. | T98: GURGAON-1A | U98: 06AAACC4175D1Z2 | V98: NOS | X98: 1 | Y98: 3956 | Z98: 3956 | AA98: GST_India | AB98: HRF2627000000684 | AC98: 46113 | AD98: BUDMINTIND | AE98: 997314 | AF98: Rental Charges For iR-ADV C | AI98: 3956 | AJ98: Normal | AK98: 18 | AL98: 0 | AM98: 0 | AN98: 712.08 | AO98: 0 | AP98: 0 | AQ98: 0 | AR98: 0 | AS98: 0 | AT98: 0 | AW98: 0 | AX98: 4668.08 | AY98: Y | AZ98: N | BA98: 11.7100.111.414703.1000.000000.0007.000000.000000.00000000 | BB98: 1126100092 | BC98: HO_INTER-STATE_OTH_REC_18% | BD98: INPUT_SERVICE | BF98: Fwd Rec | BG98: Fwd - Matched | BH98: Yes | BI98: 07 | BJ98: Delhi | BK98: 06AAACC4175D1Z2HRF2627000000684 | BL98: 712.08 | BM98: 712.08 | BN98: 0 | BO98: Matched | BP98: 9156863 | BQ98: Fwd Rec | BR98: FY 2026-27 | BS98: 1
A99: Payable Invoice | B99: AP_INVOICE | C99: 107 | D99: Godfrey_Phillips_India_Limited_HO | E99: GPIL_HO_New_Delhi(Services) | H99: 07AABCG4768K1Z9 | I99: AP_INVOICES | J99: STANDARD VALIDATED TAX | K99: Manual Invoice Entry | L99: STANDARD | M99: 46126 | N99: RENT-APR26 | O99: 9151217 | P99: 46113 | Q99: Supplier | R99: 43247 | S99: CHARU MODI | T99: DELHI-OFF | X99: 0 | Y99: 0 | Z99: 200000 | AA99: GST_India | AB99: GPI-HOC260400003 | AC99: 46113 | AE99: 997212 | AF99: K3, SATBARI FARM HOUSE RENT APRIL 2026 | AI99: 200000 | AJ99: Normal | AK99: 18 | AL99: 18000 | AM99: 18000 | AN99: 0 | AO99: 0 | AP99: 0 | AQ99: 0 | AR99: 0 | AS99: 0 | AT99: 0 | AW99: 0 | AX99: 236000 | AY99: N | AZ99: Y | BA99: 11.7100.111.424155.1000.000000.0007.000000.000000.00000000 | BB99: 1126100054 | BC99: HO_REV_CHARGE_NON_REC_18% | BD99: INPUT_SERVICE | BF99: RCM Non Rec | BG99: RCM-Not Matched | BH99: No | BI99: 07 | BJ99: Delhi | BK99: GPI-HOC260400003 | BL99: 36000 | BM99: #N/A | BN99: #N/A | BO99: RCM | BP99: 9151217 | BQ99: RCM Non Rec | BR99: RCM | BS99: 1
A100: Payable Invoice | B100: AP_INVOICE | C100: 107 | D100: Godfrey_Phillips_India_Limited_HO | E100: GPIL_HO_New_Delhi(Services) | G100: HO New Friends Colony | H100: 07AABCG4768K1Z9 | I100: AP_INVOICES | J100: STANDARD CREATED | K100: Manual Invoice Entry | L100: STANDARD | M100: 46140 | N100: DFSI2600000751 | O100: 9174963 | P100: 46129 | Q100: Supplier | R100: 35671 | S100: DEUTSCHE CARS PRIVATE LIMITED | T100: Faridabad-OFF | U100: 06AAGCD4246E1ZX | V100: NOS | X100: 275 | Y100: 7 | Z100: 1925 | AA100: GST_India | AB100: DFSI2600000751 | AC100: 46129 | AD100: BUDMINTIND | AE100: 998729 | AF100: ADJUSTING REAR AXLE | AI100: 1925 | AJ100: Normal | AK100: 18 | AL100: 0 | AM100: 0 | AN100: 346.5 | AO100: 0 | AP100: 0 | AQ100: 0 | AR100: 0 | AS100: 0 | AT100: 0 | AW100: 0 | AX100: 2271.5 | AY100: N | AZ100: N | BA100: 11.7100.111.414301.1000.100007.0007.000000.000000.00000000 | BB100: 1126100446 | BC100: HO_INTER-STATE_OTH_NON_REC_18% | BD100: INPUT_TDS_194C | BF100: Fwd Non Rec | BG100: Fwd - Matched | BH100: Yes | BI100: 07 | BJ100: Delhi | BK100: 06AAGCD4246E1ZXDFSI2600000751 | BL100: 346.5 | BM100: 36494.74 | BN100: -36148 | BO100: Matched | BP100: 9174963 | BQ100: Fwd Non Rec | BR100: FY 2026-27 | BS100: 36
...

Sheet NOT CONSIDER
A1: Document Type | B1: Trx Category | C1: Org Id | D1: Rec OU | E1: IO Name | F1: GST Inv No | G1: IO Location | H1: FP REGN | I1: ENTITY CODE | J1: EVENT TYPE CODE | K1: SOURCE | L1: TRX TYPE | M1: ACCOUNTING DATE | N1: TRX NUMBER | O1: TRX ID | P1: TRX DATE | Q1: PARTY TYPE | R1: PARTY NUMBER | S1: PARTY NAME | T1: PARTY SITE NAME | U1: TP REGNNO | V1: TRX UOM | W1: UNIT PRICE | X1: TRX QTY | Y1: LINE AMT | Z1: REGIME | AA1: SUPPLIER INVOICE NUM | AB1: SUPPLIER INVOICE DATE | AC1: ITEM CODE | AD1: HSN/SACCODE | AE1: ITEM DES | AF1: GST TAXABLE AMT | AG1: GST TAX RATE | AH1: SGST | AI1: CGST | AJ1: IGST | AK1: IGST IMPORT | AL1: UTGST | AM1: CESS1 RATE | AN1: CESS1 | AO1: CESS2 RATE | AP1: CESS2 | AQ1: TCS RATE/ADHOC | AR1: TCS AMOUNT | AS1: OTHER TAX | AT1: TOTAL AMT | AU1: TRX REC | AV1: TRX SELF | AW1: EXPENSE | AX1: VOUCHARNO | AY1: TAX CATEGORY | AZ1: ITC CATEGORY | BA1: Custom BOE No | BB1: Custom BOE Date | BC1: Port Code | BD1: State Code | BE1: State Name | BF1: GSTIN & INV | BG1: Total Tax | BH1: V-Lookuop | BI1: Diff | BJ1: Remark | BK1: ITC TYPE | BL1: 2B MONTH | BM1: a
